Workbook
Name _56F9DC9755BA473782653E2940F9FormId: "5pCRrV3EAEa8XOylVMz0l7yh5oewUHZNuOcbRYeM_iVUMEowWllFSElHMTJKWTNBN0NUNjFEWTJXVCQlQCN0PWcu"
Name _56F9DC9755BA473782653E2940F9ResponseSheet: "Form1"
Name _56F9DC9755BA473782653E2940F9SourceDocId: "{fe9cf1c0-e8ce-40da-a5ce-12054582ff1c}"

Sheet ProjetosNãoAcompanhados
A1: Projetos em excecução no Conselho Nacional de Justiça - Acompanhamento da ECP para o Painel | AN1: =TODAY() -> 46176
A2: SEI | B2: PROJETO | C2: OBJETO | D2: OBJETIVO | E2: Patrocinador | F2: UNIDADE PATROCINADORA | G2: GERENTE DO PROJETO | H2: UNIDADE GERENTE DO PROJETO | I2: ALINHAMENTO ESTRATÉGICO | J2: MACRODESAFIO | K2: POLÍTICA JUDICIÁRIA | L2: ÍNICIO DO PROJETO | M2: PREVISÃO DE TERMINO | N2: % PREVISTO | O2: % EXECUTADO | P2: MEDIÇÃO DE STATUS | Q2: DATA DE ATUALIZAÇÃO | R2: Dados de | S2: LINK PARA O PAINEL DO CNJ | T2: Programa | U2: Situação | V2: LINK PARA A PÁGINA DO PROJETO | W2: Status | X2: Entregas Previstas | Y2: Orçamento Previsto | Z2: Orçamento Executado | AA2: Link para a página do programa | AB2: Supervisor | AC2: Unidade Gestora (Negocial) | AD2: Capacidade / Benefício Estruturante | AE2: ENTREGAS REALIZADAS | AF2: Hoje | AG2: GERENTE INSTITUCIONAL | AH2: UNIDADE DO GERENTE INSTITUCIONAL | AI2: Lições Aprendidas | AJ2: Portfólio 2024 | AK2: Portfólio 2025 | AL2: Portfólio 2026 | AM2: Observações
A3: 04868/2023 | B3: SINAPSES – Melhorias Evolutivas e Corretivas | C3: Implementar melhorias e correções de funcionalidades da aplicação SINAPSES. | E3: Dr. Dorotheo Barbosa Neto | F3: SEP - Secretaria de Estratégia e Projetos | G3: Ana Angélica Rodrigues Alves | H3: PNUD | I3: Não definido | J3: Não definido | K3: Não definido | L3: 45006 | M3: 45607 | N3: 0.998 | O3: 1 | P3: =IFERROR(Tb_PortfólioNão[[#This Row],[% EXECUTADO]]/Tb_PortfólioNão[[#This Row],[% PREVISTO]],"0%") -> 1.002004 | Q3: =_xlfn.XLOOKUP(Tb_PortfólioNão[[#This Row],[SEI]],Tb_Atualizações[PROCESSO SEI],Tb_Atualizações[DATA DE ATUALIZAÇÃO],"",0,-1) | R3: 45627 | T3: Justiça 4.0 | U3: Cancelado | W3: =IFERROR(Tb_PortfólioNão[[#This Row],[% EXECUTADO]]/Tb_PortfólioNão[[#This Row],[% PREVISTO]],0) -> 1.002004 | X3: - Implantação de padrão Data Transfer Object (DTO); - Gestão de Usuários, Domínios e Integração Keycloak / Single Sign-On (SSO); - Unificação dos Modelos; - Auditoria/Histórico; - Catálogo de Modelos; - Interface Atualizadas; - Melhoria de interface – padrão PDPJ ; - Métricas de Monitoramento; - Documentação do Projeto, comunicação e divulgação do projeto | Y3: 3100000 | Z3: 1890848.2 | AA3: https://www.cnj.jus.br/tecnologia-da-informacao-e-comunicacao/justica-4-0/ | AE3: - Implantação de padrão Data Transfer Object (DTO); - Gestão de Usuários, Domínios e Integração Keycloak / Single Sign-On (SSO); - Unificação dos Modelos; - Auditoria/Histórico; - Catálogo de Modelos; - Interface Atualizadas; - Melhoria de interface – padrão PDPJ ; - Métricas de Monitoramento; - Documentação do Projeto, comunicação e divulgação do projeto | AF3: =TODAY() -> 46176 | AJ3: Sim | AK3: Sim | AL3: =IFERROR(IF(MATCH(#REF!,Atualizações!$P$1:$P$2994,0)>0, "Sim"), "Não") -> Não | AM3: TEP: https://www.cnj.jus.br/sei/controlador.php?acao=procedimento_trabalhar&id_procedimento=1670519&id_documento=2226063

Sheet Projetos
A1: Projetos em excecução no Conselho Nacional de Justiça - Acompanhamento da ECP para o Painel | AQ1: =TODAY() -> 46176
A2: SEI | B2: PROJETO | C2: OBJETO | D2: OBJETIVO | E2: Patrocinador | F2: UNIDADE PATROCINADORA | G2: GERENTE DO PROJETO | H2: UNIDADE GERENTE DO PROJETO | I2: ALINHAMENTO ESTRATÉGICO | J2: MACRODESAFIO | K2: POLÍTICA JUDICIÁRIA | L2: ÍNICIO DO PROJETO | M2: PREVISÃO DE TERMINO | N2: % PREVISTO | O2: % EXECUTADO | P2: MEDIÇÃO DE STATUS | Q2: DATA DE ATUALIZAÇÃO | R2: Dados de | S2: LINK PARA O PAINEL DO CNJ | T2: Programa | U2: Situação | V2: LINK PARA A PÁGINA DO PROJETO | W2: Status | X2: Entregas Previstas | Y2: Orçamento Previsto | Z2: Orçamento Executado | AA2: Link para a página do programa | AB2: Supervisor | AC2: Unidade Gestora (Negocial) | AD2: Capacidade / Benefício Estruturante | AE2: ENTREGAS REALIZADAS | AF2: Hoje | AG2: GERENTE INSTITUCIONAL | AH2: UNIDADE DO GERENTE INSTITUCIONAL | AI2: Lições Aprendidas | AJ2: Aux2024 | AK2: Portfólio 2024 | AL2: Aux2025 | AM2: Portfólio 2025 | AN2: Aux2026 | AO2: Portfólio 2026 | AP2: Observações | AQ2: Consultor
A3: 00030/2025 | B3: Phase-out: Transição Projetos X Operação | C3: O presente projeto visa estruturar a transição sustentável de soluções do Justiça 4.0 para o CNJ, considerando suporte, infraestrutura e treinamento. Tem como objetivo desenvolver e implementar boas práticas de transição dos serviços para a operação após a conclusão dos projetos de desenvolvimento, incluindo etapas obrigatórias no cronograma dos projetos, como treinamentos e repasse aos times de suporte técnico do DTI. Além disso, será padronizado que o repasse de conhecimento tenha início já na fase de homologação do sistema, otimizando a transferência de conhecimento e facilitando a integração com a operação. | E3: Dr. Dorotheo Barbosa Neto | F3: SEP - Secretaria de Estratégia e Projetos | G3: Renato Silveira | H3: PNUD | I3: 10. Aprimorar a governança e a gestão da tecnologia e comunicação sob a ótica de soluções colaborativas | J3: 12. Fortalecimento da estratégia nacional de TIC e de proteção de dados; 09. Aperfeiçoamento da gestão administrativa e da governança judiciária | K3: Estratégia Nacional de Tecnologia da Informação e Comunicação do Poder Judiciário (ENTIC-JUD), Resolução CNJ n. 370/2021, e com o Programa Justiça 4.0 - Eixo Fortalecimento de Capacidades Institucionais do CNJ (transferência de conhecimento e soluções com foco na segurança jurídica, sustentabilidade de projetos e eficiência da prestação jurisdicional)" | L3: 45659 | M3: 46387 | N3: =_xlfn.XLOOKUP(Tb_Portfólio[[#This Row],[SEI]],Tb_Atualizações[PROCESSO SEI],Tb_Atualizações[% PREVISTO],"",0,-1) -> 0.69 | O3: =_xlfn.XLOOKUP(Tb_Portfólio[[#This Row],[SEI]],Tb_Atualizações[PROCESSO SEI],Tb_Atualizações[% EXECUTADO],"",0,-1) -> 0.39 | P3: =IFERROR(Tb_Portfólio[[#This Row],[% EXECUTADO]]/Tb_Portfólio[[#This Row],[% PREVISTO]],"0%") -> 0.56521739 | Q3: =_xlfn.XLOOKUP(Tb_Portfólio[[#This Row],[SEI]],Tb_Atualizações[PROCESSO SEI],Tb_Atualizações[DATA DE ATUALIZAÇÃO],"",0,-1) -> 46167 | R3: =_xlfn.XLOOKUP(Tb_Portfólio[[#This Row],[SEI]],Tb_Atualizações[PROCESSO SEI],Tb_Atualizações[Mês],,0,-1) -> 46143 | T3: Justiça 4.0 | U3: =IF(Tb_Portfólio[[#This Row],[% EXECUTADO]]=100%,"Finalizado",IF(Tb_Portfólio[[#This Row],[PREVISÃO DE TERMINO]]<Tb_Portfólio[[#This Row],[Hoje]],"Atrasado ou Crítico",IF(Tb_Portfólio[[#This Row],[% EXECUTADO]]=0,"Autorizado",IF(Tb_Portfólio[[#This Row],[MEDIÇÃO DE STATUS]]>=95%,"No prazo",IF(Tb_Portfólio[[#This Row],[MEDIÇÃO DE STATUS]]<85%,"Atrasado ou Crítico",IF(Tb_Portfólio[[#This Row],[MEDIÇÃO DE STATUS]]<=95%,"Em atenção")))))) -> Atrasado ou Crítico | W3: =IFERROR(Tb_Portfólio[[#This Row],[% EXECUTADO]]/Tb_Portfólio[[#This Row],[% PREVISTO]],0) -> 0.56521739 | X3: - Definição da estrutura e responsáveis ; - Definição e elaboração da documentação técnica padrão dos sistemas, assim como dos Manuais de Usuário e Operação; | Y3: 409011.54 | AA3: https://www.cnj.jus.br/tecnologia-da-informacao-e-comunicacao/justica-4-0/ | AB3: Dr. Alexandre Libonati de Abreu | AC3: DTI - Departamento de Tecnologia da Informação e Comunicação | AD3: Benefício 1 - Capacitação e Criação de manuais e documentações - Esse benefício visa reduzir os riscos e falhas operacionais na transição do projeto para a operação. Benefício 2 - Melhoria no processo de transição de equipes - Facilidade de manutenção e melhorias contínuas, permitindo que eventuais novos integrantes da equipe e operadores entendam rapidamente o sistema, garantindo uma transição suave em qualquer evolução tecnológica ou de processo. | AF3: =TODAY() -> 46176 | AG3: Paulo Magnus Pereira Porto | AH3: DTI - Departamento de Tecnologia da Informação e Comunicação | AJ3: =2024&Tb_Portfólio[[#This Row],[SEI]] -> 202400030/2025 | AK3: =IFERROR(IF(MATCH(AJ3,Atualizações!$P$1:$P$1265,0)>0, "Sim"), "Não") -> Não | AL3: =2025&Tb_Portfólio[[#This Row],[SEI]] -> 202500030/2025 | AM3: =IFERROR(IF(MATCH(AL3,Atualizações!$P$1:$P$2994,0)>0, "Sim"), "Não") -> Sim | AN3: =2026&Tb_Portfólio[[#This Row],[SEI]] -> 202600030/2025 | AO3: =IFERROR(IF(MATCH(AN3,Atualizações!$P$1:$P$2994,0)>0, "Sim"), "Não") -> Sim | AP3: =_xlfn.XLOOKUP(Tb_Portfólio[[#This Row],[SEI]],Tb_Atualizações[PROCESSO SEI],Tb_Atualizações[Explicações],"",0,-1) -> 0 | AQ3: =_xlfn.XLOOKUP(Tb_Portfólio[[#This Row],[SEI]],Tb_Mapa[SEI],Tb_Mapa[CONSULTOR RESPONSÁVEL],"",0,-1) -> Tony
A4: 00139/2024 | B4: Mapa Nacional do Tribunal do Júri | C4: Identificar, por meio dos dados do Painel “Justiça em Números”, os gargalos específicos e, posteriormente, as questões a eles relacionadas que geram a morosidade e o acúmulo de processos de competência do Tribunal do Júri, criando soluções colaborativas e customizadas para resolução desses problemas em parceria com os tribunais envolvidos. | E4: Dr. Gláucio Roberto Brittes de Araujo | F4: SEP - Secretaria de Estratégia e Projetos | G4: Thiago Gontijo Vieira | H4: SEP - Secretaria de Estratégia e Projetos | I4: 01. Desenvolver políticas judiciárias e outros instrumentos para o aperfeiçoamento das atividades dos órgãos do Poder Judiciário e dos seus serviços auxiliares e dos serviços notariais e de registro, e dos demais órgãos correicionais | J4: 08. Aperfeiçoamento da gestão da justiça criminal | K4: Portaria CNJ nº 69/2017 | L4: 45328 | M4: 46658 | N4: =_xlfn.XLOOKUP(Tb_Portfólio[[#This Row],[SEI]],Tb_Atualizações[PROCESSO SEI],Tb_Atualizações[% PREVISTO],"",0,-1) -> 0.81 | O4: =_xlfn.XLOOKUP(Tb_Portfólio[[#This Row],[SEI]],Tb_Atualizações[PROCESSO SEI],Tb_Atualizações[% EXECUTADO],"",0,-1) -> 0.89 | P4: =IFERROR(Tb_Portfólio[[#This Row],[% EXECUTADO]]/Tb_Portfólio[[#This Row],[% PREVISTO]],"0%") -> 1.0987654 | Q4: =_xlfn.XLOOKUP(Tb_Portfólio[[#This Row],[SEI]],Tb_Atualizações[PROCESSO SEI],Tb_Atualizações[DATA DE ATUALIZAÇÃO],"",0,-1) -> 46035 | R4: =_xlfn.XLOOKUP(Tb_Portfólio[[#This Row],[SEI]],Tb_Atualizações[PROCESSO SEI],Tb_Atualizações[Mês],,0,-1) -> 45839 | U4: =IF(Tb_Portfólio[[#This Row],[% EXECUTADO]]=100%,"Finalizado",IF(Tb_Portfólio[[#This Row],[PREVISÃO DE TERMINO]]<Tb_Portfólio[[#This Row],[Hoje]],"Atrasado ou Crítico",IF(Tb_Portfólio[[#This Row],[% EXECUTADO]]=0,"Autorizado",IF(Tb_Portfólio[[#This Row],[MEDIÇÃO DE STATUS]]>=95%,"No prazo",IF(Tb_Portfólio[[#This Row],[MEDIÇÃO DE STATUS]]<85%,"Atrasado ou Crítico",IF(Tb_Portfólio[[#This Row],[MEDIÇÃO DE STATUS]]<=95%,"Em atenção")))))) -> No prazo | W4: =IFERROR(Tb_Portfólio[[#This Row],[% EXECUTADO]]/Tb_Portfólio[[#This Row],[% PREVISTO]],0) -> 1.0987654 | X4: Coleta de dados dos sistemas do DPJ; Apresentação do diagnóstico aos tribunais; Visitas in-loco e criação de soluções; Trinunais apresentam proposta para solução dos gargalos ao CNJ; Acompanhamento e medição dos resultados das soluções Relatório final do projeto | AB4: Dr. Paulo Marcos de Farias | AC4: SG - Secretaria Geral | AD4: • Diagnóstico dos gargalos locais dos processos do tribunal do júri • Soluções colaborativas • Diminuição dos gargalos | AE4: "- Diagnóstico dos gargalos locais dos processos do tribunal do júri; - Apresentação do diagnóstico aos tribunais; - Propostas de soluções de 23 tribunais; | AF4: =TODAY() -> 46176 | AJ4: =2024&Tb_Portfólio[[#This Row],[SEI]] -> 202400139/2024 | AK4: =IFERROR(IF(MATCH(AJ4,Atualizações!$P$1:$P$1265,0)>0, "Sim"), "Não") -> Sim | AL4: =2025&Tb_Portfólio[[#This Row],[SEI]] -> 202500139/2024 | AM4: =IFERROR(IF(MATCH(AL4,Atualizações!$P$1:$P$2994,0)>0, "Sim"), "Não") -> Sim | AN4: =2026&Tb_Portfólio[[#This Row],[SEI]] -> 202600139/2024 | AO4: =IFERROR(IF(MATCH(AN4,Atualizações!$P$1:$P$2994,0)>0, "Sim"), "Não") -> Sim | AP4: =_xlfn.XLOOKUP(Tb_Portfólio[[#This Row],[SEI]],Tb_Atualizações[PROCESSO SEI],Tb_Atualizações[Explicações],"",0,-1) -> Medição duplicada apenas para incluir no portfólio de 2026 | AQ4: =_xlfn.XLOOKUP(Tb_Portfólio[[#This Row],[SEI]],Tb_Mapa[SEI],Tb_Mapa[CONSULTOR RESPONSÁVEL],"",0,-1) -> Tony
A5: 00484/2024 | B5: Painel do Programa Desjudicializa | C5: Produzir novo painel digital denominado "Painel Desjudicializa", em que serão apresentados dados processuais detalhados a respeito do maior litigante do Poder Judiciário brasileiro, o Instituto Nacional de Seguro Social-INSS. | E5: Dra. Ana Lúcia Andrade de Aguiar | F5: SEP - Secretaria de Estratégia e Projetos | G5: André José da Silva Lima | H5: PNUD | I5: 03. Fomentar a gestão da qualidade dos dados no Poder Judiciário | J5: 05. Prevenção de litígios e adoção de soluções consensuais para os conflitos | K5: Programa Justiça 4.0, eixo 2: Gestão de dados e informações - aprimoramento de bases de dados e formulação, implantação e monitoramento de políticas judiciárias com base em evidências para fortalecer a promoção de direitos humanos e a transparência de dados. Ademais, o referido Projeto correlaciona-se com a Resolução CNJ Nº 235 de 29/06/2020 | L5: 45323 | M5: 46387 | N5: =_xlfn.XLOOKUP(Tb_Portfólio[[#This Row],[SEI]],Tb_Atualizações[PROCESSO SEI],Tb_Atualizações[% PREVISTO],"",0,-1) -> 0.78 | O5: =_xlfn.XLOOKUP(Tb_Portfólio[[#This Row],[SEI]],Tb_Atualizações[PROCESSO SEI],Tb_Atualizações[% EXECUTADO],"",0,-1) -> 0.7 | P5: =IFERROR(Tb_Portfólio[[#This Row],[% EXECUTADO]]/Tb_Portfólio[[#This Row],[% PREVISTO]],"0%") -> 0.8974359 | Q5: =_xlfn.XLOOKUP(Tb_Portfólio[[#This Row],[SEI]],Tb_Atualizações[PROCESSO SEI],Tb_Atualizações[DATA DE ATUALIZAÇÃO],"",0,-1) -> 46167 | R5: =_xlfn.XLOOKUP(Tb_Portfólio[[#This Row],[SEI]],Tb_Atualizações[PROCESSO SEI],Tb_Atualizações[Mês],,0,-1) -> 46143 | T5: Justiça 4.0 | U5: =IF(Tb_Portfólio[[#This Row],[% EXECUTADO]]=100%,"Finalizado",IF(Tb_Portfólio[[#This Row],[PREVISÃO DE TERMINO]]<Tb_Portfólio[[#This Row],[Hoje]],"Atrasado ou Crítico",IF(Tb_Portfólio[[#This Row],[% EXECUTADO]]=0,"Autorizado",IF(Tb_Portfólio[[#This Row],[MEDIÇÃO DE STATUS]]>=95%,"No prazo",IF(Tb_Portfólio[[#This Row],[MEDIÇÃO DE STATUS]]<85%,"Atrasado ou Crítico",IF(Tb_Portfólio[[#This Row],[MEDIÇÃO DE STATUS]]<=95%,"Em atenção")))))) -> Em atenção | W5: =IFERROR(Tb_Portfólio[[#This Row],[% EXECUTADO]]/Tb_Portfólio[[#This Row],[% PREVISTO]],0) -> 0.8974359 | X5: - fazer levantamento dos processos relacionados aos 10 maiores litigantes do judiciário brasileiro e elaborar regras negociais para escrita de script que extrairá os dados da base; - Identificar padrões com as variáveis estabelecidas negocialmente para o estudo; -Confecção do painel; | AA5: https://www.cnj.jus.br/tecnologia-da-informacao-e-comunicacao/justica-4-0/ | AB5: Dra. Ana Lúcia Andrade de Aguiar | AC5: DPJ - Departamento de Pesquisas Judiciárias | AD5: Identificação do maior litigante do judiciário brasileiro-INSS, como polo ativo e passivo. | AE5: - identificação dos 10 maiores litigantes, ativos e passivos. - Criação de script de banco de dados; -Criar base de dados com os 10 maiores litigantes; -Disponibilização de dados em Homologação; -Disponibilização de dados em Desenvolvimento | AF5: =TODAY() -> 46176 | AG5: Isabely Fontana da Mota | AH5: DPJ/CNJ | AJ5: =2024&Tb_Portfólio[[#This Row],[SEI]] -> 202400484/2024 | AK5: =IFERROR(IF(MATCH(AJ5,Atualizações!$P$1:$P$1265,0)>0, "Sim"), "Não") -> Sim | AL5: =2025&Tb_Portfólio[[#This Row],[SEI]] -> 202500484/2024 | AM5: =IFERROR(IF(MATCH(AL5,Atualizações!$P$1:$P$2994,0)>0, "Sim"), "Não") -> Sim | AN5: =2026&Tb_Portfólio[[#This Row],[SEI]] -> 202600484/2024 | AO5: =IFERROR(IF(MATCH(AN5,Atualizações!$P$1:$P$2994,0)>0, "Sim"), "Não") -> Sim | AP5: =_xlfn.XLOOKUP(Tb_Portfólio[[#This Row],[SEI]],Tb_Atualizações[PROCESSO SEI],Tb_Atualizações[Explicações],"",0,-1) -> 0 | AQ5: =_xlfn.XLOOKUP(Tb_Portfólio[[#This Row],[SEI]],Tb_Mapa[SEI],Tb_Mapa[CONSULTOR RESPONSÁVEL],"",0,-1) -> Tony
A6: 00535/2019 | B6: Execução Fiscal - Automação e Governança | C6: Automação dos processos de execução fiscal e instituição de medidas de governaça | D6: Projeto voltado à automação dos processos de execução fiscal e instituição de medidas de governança | E6: Dra. Lívia Cristina Marques Peres e Dra. Keity Saboia | F6: SEP - Secretaria de Estratégia e Projetos | G6: Fernando Landim Caetano | H6: Memora | I6: 13. Estimular a desburocratização no Poder Judiciário | J6: 03. Agilidade e produtividade na prestação jurisdicional | L6: 43557 | M6: 45930 | N6: =_xlfn.XLOOKUP(Tb_Portfólio[[#This Row],[SEI]],Tb_Atualizações[PROCESSO SEI],Tb_Atualizações[% PREVISTO],"",0,-1) -> 1 | O6: =_xlfn.XLOOKUP(Tb_Portfólio[[#This Row],[SEI]],Tb_Atualizações[PROCESSO SEI],Tb_Atualizações[% EXECUTADO],"",0,-1) -> 1 | P6: =IFERROR(Tb_Portfólio[[#This Row],[% EXECUTADO]]/Tb_Portfólio[[#This Row],[% PREVISTO]],"0%") -> 1 | Q6: =_xlfn.XLOOKUP(Tb_Portfólio[[#This Row],[SEI]],Tb_Atualizações[PROCESSO SEI],Tb_Atualizações[DATA DE ATUALIZAÇÃO],"",0,-1) -> 45624 | R6: =_xlfn.XLOOKUP(Tb_Portfólio[[#This Row],[SEI]],Tb_Atualizações[PROCESSO SEI],Tb_Atualizações[Mês],,0,-1) -> 45597 | T6: Resolve | U6: =IF(Tb_Portfólio[[#This Row],[% EXECUTADO]]=100%,"Finalizado",IF(Tb_Portfólio[[#This Row],[PREVISÃO DE TERMINO]]<Tb_Portfólio[[#This Row],[Hoje]],"Atrasado ou Crítico",IF(Tb_Portfólio[[#This Row],[% EXECUTADO]]=0,"Autorizado",IF(Tb_Portfólio[[#This Row],[MEDIÇÃO DE STATUS]]>=95%,"No prazo",IF(Tb_Portfólio[[#This Row],[MEDIÇÃO DE STATUS]]<85%,"Atrasado ou Crítico",IF(Tb_Portfólio[[#This Row],[MEDIÇÃO DE STATUS]]<=95%,"Em atenção")))))) -> Finalizado | V6: https://www.cnj.jus.br/programas-e-acoes/programa-resolve/execucao-fiscal/ | W6: =IFERROR(Tb_Portfólio[[#This Row],[% EXECUTADO]]/Tb_Portfólio[[#This Row],[% PREVISTO]],0) -> 1 | X6: Planejamento (compilação das medidas propostas, dados estatísticos e entrega, apresentação, critérios de aceitação e formalização do projeto); Criação do Grupo de Trabalho ; Capacitação; Desenvolvimento de medidas de Automação; Piloto com 6 tribunais; Acompanhamento do impacto; | Y6: 40936.83 | Z6: 40936.83 | AA6: https://www.cnj.jus.br/programas-e-acoes/programa-resolve/ | AB6: Dra. Lívia Cristina Marques Peres e Dra. Keity Saboia | AC6: SEP - Secretaria de Estratégia e Projetos | AE6: • Fluxos de automação de expedientes • Automação de fluxos de suspensão e Sobrestamento processual • Automação de fluxos de bens imóveis • Automação de fluxos básicos de processamento • Automação de fluxo de pós-conclusão • Automação de fluxo de pós convênio • Automação do fluxo de análise da inicial • Configuração de microfluxos integrado ao fluxo base nacional • Pilotos • APIs disponibilizadas • Operação assistida dos Tribunais Aderentes | AF6: =TODAY() -> 46176 | AJ6: =2024&Tb_Portfólio[[#This Row],[SEI]] -> 202400535/2019 | AK6: =IFERROR(IF(MATCH(AJ6,Atualizações!$P$1:$P$1265,0)>0, "Sim"), "Não") -> Sim | AL6: =2025&Tb_Portfólio[[#This Row],[SEI]] -> 202500535/2019 | AM6: =IFERROR(IF(MATCH(AL6,Atualizações!$P$1:$P$2994,0)>0, "Sim"), "Não") -> Não | AN6: =2026&Tb_Portfólio[[#This Row],[SEI]] -> 202600535/2019 | AO6: =IFERROR(IF(MATCH(AN6,Atualizações!$P$1:$P$2994,0)>0, "Sim"), "Não") -> Não | AP6: =_xlfn.XLOOKUP(Tb_Portfólio[[#This Row],[SEI]],Tb_Atualizações[PROCESSO SEI],Tb_Atualizações[Explicações],"",0,-1) -> Projeto finalizado - As atividades remanescentes e futuras melhorias serão tratadas no âmbito do Projeto “Fluxo Nacional Automatizado de Execuções Fiscais”, do programa Justiça 4.0 | AQ6: =_xlfn.XLOOKUP(Tb_Portfólio[[#This Row],[SEI]],Tb_Mapa[SEI],Tb_Mapa[CONSULTOR RESPONSÁVEL],"",0,-1) -> Tony/finalizado
A7: 00600/2023 | B7: Programa Nacional de Promoção da Equidade Racial no Poder Judiciário - 2024 | C7: Estruturar e implementar iniciativas e políticas para promover a equidade racial no Poder Judiciário | E7: Luis Roberto Barroso | F7: Presidência do CNJ | G7: Priscila Nunes Patel | H7: Gabinete da Presidência | I7: 01. Desenvolver políticas judiciárias e outros instrumentos para o aperfeiçoamento das atividades dos órgãos do Poder Judiciário e dos seus serviços auxiliares e dos serviços notariais e de registro, e dos demais órgãos correicionais. 07. Fomentar e fortalecer a atuação interinstitucional do CNJ para garantir os direitos dos cidadãos | J7: 01. Garantia dos direitos fundamentais | L7: 45390 | M7: 46022 | N7: =_xlfn.XLOOKUP(Tb_Portfólio[[#This Row],[SEI]],Tb_Atualizações[PROCESSO SEI],Tb_Atualizações[% PREVISTO],"",0,-1) -> 0.6283 | O7: =_xlfn.XLOOKUP(Tb_Portfólio[[#This Row],[SEI]],Tb_Atualizações[PROCESSO SEI],Tb_Atualizações[% EXECUTADO],"",0,-1) -> 0.6283 | P7: =IFERROR(Tb_Portfólio[[#This Row],[% EXECUTADO]]/Tb_Portfólio[[#This Row],[% PREVISTO]],"0%") -> 1 | Q7: =_xlfn.XLOOKUP(Tb_Portfólio[[#This Row],[SEI]],Tb_Atualizações[PROCESSO SEI],Tb_Atualizações[DATA DE ATUALIZAÇÃO],"",0,-1) -> 45799 | R7: =_xlfn.XLOOKUP(Tb_Portfólio[[#This Row],[SEI]],Tb_Atualizações[PROCESSO SEI],Tb_Atualizações[Mês],,0,-1) -> 45748 | T7: Programa Nacional de Promoção da Equidade Racial no Poder Judiciário | U7: =IF(Tb_Portfólio[[#This Row],[% EXECUTADO]]=100%,"Finalizado",IF(Tb_Portfólio[[#This Row],[PREVISÃO DE TERMINO]]<Tb_Portfólio[[#This Row],[Hoje]],"Atrasado ou Crítico",IF(Tb_Portfólio[[#This Row],[% EXECUTADO]]=0,"Autorizado",IF(Tb_Portfólio[[#This Row],[MEDIÇÃO DE STATUS]]>=95%,"No prazo",IF(Tb_Portfólio[[#This Row],[MEDIÇÃO DE STATUS]]<85%,"Atrasado ou Crítico",IF(Tb_Portfólio[[#This Row],[MEDIÇÃO DE STATUS]]<=95%,"Em atenção")))))) -> Atrasado ou Crítico | V7: https://www.cnj.jus.br/programas-e-acoes/direitos-humanos/pacto-nacional-do-judiciario-pela-equidade-racial/ | W7: =IFERROR(Tb_Portfólio[[#This Row],[% EXECUTADO]]/Tb_Portfólio[[#This Row],[% PREVISTO]],0) -> 1 | X7: -Elaborar e executar Plano de Comunicação; -Monitorar o engajamento dos tribunais que aderiram ao Pacto Nacional; -Divulgar os cadernos formativos elaborados em parceria com o programa Fazendo Justiça; - Realizar a primeira edição do Prêmio Anual de Equidade Racial do Poder Judiciário para homenagear os Tribunais que desenvolverem Programas cuja centralidade seja o combate ao racismo institucional, atendendo, ainda, aos Objetivos de Desenvolvimento Sustentável (ODS) que compõem a Agenda 2030; - Promoção, por meio de plano de comunicação, do credenciamento de cursos preparatórios junto à Fundação Getúlio Vargas dentro do programa CNJ de Bolsas; - Concessão do Selo CNJ de Bolsas de Ação Afirmativa para pelo menos um curso preparatório para a magistratura, por estado, junto à Fundação Getúlio Vargas dentro do programa CNJ de Bolsas; - Inclusão do IPER – Indicador de Desempenho na Promoção da Equidade Racial, no Prêmio CNJ de Qualidade de 2025 - Trabalhar junto aos tribunais para tornar os dados étnico-raciais enviados mais fidedignos; - Realizar nova turma para a formação inicial e continuada de magistrados(as) em relações étnico-raciais, Direito antidiscriminatório e Equidade Racial, em parceria com Enfam; - Realizar nova turma para a formação inicial e continuada de magistrados(as) em relações étnico-raciais, Direito antidiscriminatório e Equidade Racial, em parceria com Enamat; - Realizar formação inicial e continuada de servidores(as) e estagiários(as) em relações étnico-raciais, Direito antidiscriminatório e Equidade Racial (Ceajud); - Capacitar membros das comissões de heteroidentificação; - Capacitar servidores da comunicação; - Criação de banco de especialistas em heteroidentificação ; - Publicar o Protocolo de julgamento com perspectiva racial. - Publicar a Política Nacional do Poder Judiciário de Equidade Racial; - | AA7: https://www.cnj.jus.br/programas-e-acoes/direitos-humanos/pacto-nacional-do-judiciario-pela-equidade-racial/ | AB7: Dra. Karen Louise Vilanova batista de Souza | AC7: SG - Secretaria Geral | AD7: Benefício 1 - Tribunais engajados em torno do combate ao racismo e da promoção da equidade racial; Benefício 2 - Fomento à implementação de medidas estruturantes antirracistas, de combate ao racismo estrutural e promoção da equidade racial; Benefício 3 - Aumento da capacidade organizacional quanto ao conhecimento sobre a temática e a obtenção de dados sobre as questões raciais, para o planejamento dos projetos e ações do programa; Benefício 4 - Diretrizes para uma maior atuação dos órgãos do Poder Judiciário Nacional no combate ao racismo e na promoção da equidade racial | AE7: - Realizar a primeira edição do Prêmio Anual de Equidade Racial do Poder Judiciário para homenagear os Tribunais que desenvolverem Programas cuja centralidade seja o combate ao racismo institucional, atendendo, ainda, aos Objetivos de Desenvolvimento Sustentável (ODS) que compõem a Agenda 2030; - Capacitar membros das comissões de heteroidentificação; - Publicar o Protocolo de julgamento com perspectiva racial | AF7: =TODAY() -> 46176 | AG7: Cristina de Oliveira Winckler | AH7: ECP - Escritório Corporativo de Projetos Institucionais | AJ7: =2024&Tb_Portfólio[[#This Row],[SEI]] -> 202400600/2023 | AK7: =IFERROR(IF(MATCH(AJ7,Atualizações!$P$1:$P$1265,0)>0, "Sim"), "Não") -> Sim | AL7: =2025&Tb_Portfólio[[#This Row],[SEI]] -> 202500600/2023 | AM7: =IFERROR(IF(MATCH(AL7,Atualizações!$P$1:$P$2994,0)>0, "Sim"), "Não") -> Sim | AN7: =2026&Tb_Portfólio[[#This Row],[SEI]] -> 202600600/2023 | AO7: =IFERROR(IF(MATCH(AN7,Atualizações!$P$1:$P$2994,0)>0, "Sim"), "Não") -> Não | AP7: =_xlfn.XLOOKUP(Tb_Portfólio[[#This Row],[SEI]],Tb_Atualizações[PROCESSO SEI],Tb_Atualizações[Explicações],"",0,-1) -> 0 | AQ7: =_xlfn.XLOOKUP(Tb_Portfólio[[#This Row],[SEI]],Tb_Mapa[SEI],Tb_Mapa[CONSULTOR RESPONSÁVEL],"",0,-1) -> Tony / Cris
A8: 01167/2025 | B8: Data Lake - Melhorias Evolutivas e Corretivas | C8: O projeto visa implementar melhorias evolutivas, correções e novas funcionalidades no Data Lake, assegurando a continuidade da relevância, segurança e eficiência, e fortalecendo seu papel como um repositório centralizado e integrado para o grande volume de dados gerados pelos sistemas do Justiça 4.0. | E8: Dr. Dorotheo Barbosa Neto | F8: SEP - Secretaria de Estratégia e Projetos | G8: Marcos Cardoso | H8: PNUD | I8: 03. Fomentar a gestão da qualidade dos dados no Poder Judiciário; | J8: 12. Fortalecimento da estratégia nacional de TIC e de proteção de dados; 09. Aperfeiçoamento da gestão administrativa e da governança judiciária; e 03. Agilidade e produtividade na prestação jurisdicional | K8: Estratégia Nacional de Tecnologia da Informação e Comunicação do Poder Judiciário (ENTIC-JUD), Resolução CNJ n. 370/2021; e Programa Justiça 4.0 - Eixo Fortalecimento de Capacidades Institucionais do CNJ (transferência de conhecimento e soluções com foco na segurança jurídica, sustentabilidade de projetos e eficiência da prestação jurisdicional). | L8: 45658 | M8: 46387 | N8: =_xlfn.XLOOKUP(Tb_Portfólio[[#This Row],[SEI]],Tb_Atualizações[PROCESSO SEI],Tb_Atualizações[% PREVISTO],"",0,-1) -> 0.68 | O8: =_xlfn.XLOOKUP(Tb_Portfólio[[#This Row],[SEI]],Tb_Atualizações[PROCESSO SEI],Tb_Atualizações[% EXECUTADO],"",0,-1) -> 0.64 | P8: =IFERROR(Tb_Portfólio[[#This Row],[% EXECUTADO]]/Tb_Portfólio[[#This Row],[% PREVISTO]],"0%") -> 0.94117647 | Q8: =_xlfn.XLOOKUP(Tb_Portfólio[[#This Row],[SEI]],Tb_Atualizações[PROCESSO SEI],Tb_Atualizações[DATA DE ATUALIZAÇÃO],"",0,-1) -> 46167 | R8: =_xlfn.XLOOKUP(Tb_Portfólio[[#This Row],[SEI]],Tb_Atualizações[PROCESSO SEI],Tb_Atualizações[Mês],,0,-1) -> 46143 | T8: Justiça 4.0 | U8: =IF(Tb_Portfólio[[#This Row],[% EXECUTADO]]=100%,"Finalizado",IF(Tb_Portfólio[[#This Row],[PREVISÃO DE TERMINO]]<Tb_Portfólio[[#This Row],[Hoje]],"Atrasado ou Crítico",IF(Tb_Portfólio[[#This Row],[% EXECUTADO]]=0,"Autorizado",IF(Tb_Portfólio[[#This Row],[MEDIÇÃO DE STATUS]]>=95%,"No prazo",IF(Tb_Portfólio[[#This Row],[MEDIÇÃO DE STATUS]]<85%,"Atrasado ou Crítico",IF(Tb_Portfólio[[#This Row],[MEDIÇÃO DE STATUS]]<=95%,"Em atenção")))))) -> Em atenção | W8: =IFERROR(Tb_Portfólio[[#This Row],[% EXECUTADO]]/Tb_Portfólio[[#This Row],[% PREVISTO]],0) -> 0.94117647 | X8: - Melhorias na performance do sistema e garantia de alta disponibilidade; - Aprimoramento contínuo da segurança; - Correção de bugs; - Aumento da cobertura de testes e automatização de testes; - Documentação de regras de negócio, requisitos, refinamentos e arquitetura do sistema e gestão de releases; - Implementação de novas funcionalidades e melhorias evolutivas | Y8: 1919522.6 | AA8: https://www.cnj.jus.br/tecnologia-da-informacao-e-comunicacao/justica-4-0/ | AB8: Dr. João Thiago de França Guerra | AC8: DTI - Departamento de Tecnologia da Informação e Comunicação | AD8: BENEFÍCIO 1 - Melhoria da estabilidade e confiabilidade e Evolução do Data Lake. Benefício 2 - Melhorias Implementadas | AE8: P1 – Planejamento: Termo de Abertura de Projeto. P7 - Novas Funcionalidades e Melhorias Evolutivas • Implementação de situação processual e fase dos processos | AF8: =TODAY() -> 46176 | AG8: Antônio Augusto Silva Martins | AH8: DTI - Departamento de Tecnologia da Informação e Comunicação | AJ8: =2024&Tb_Portfólio[[#This Row],[SEI]] -> 202401167/2025 | AK8: =IFERROR(IF(MATCH(AJ8,Atualizações!$P$1:$P$1265,0)>0, "Sim"), "Não") -> Não | AL8: =2025&Tb_Portfólio[[#This Row],[SEI]] -> 202501167/2025 | AM8: =IFERROR(IF(MATCH(AL8,Atualizações!$P$1:$P$2994,0)>0, "Sim"), "Não") -> Sim | AN8: =2026&Tb_Portfólio[[#This Row],[SEI]] -> 202601167/2025 | AO8: =IFERROR(IF(MATCH(AN8,Atualizações!$P$1:$P$2994,0)>0, "Sim"), "Não") -> Sim | AP8: =_xlfn.XLOOKUP(Tb_Portfólio[[#This Row],[SEI]],Tb_Atualizações[PROCESSO SEI],Tb_Atualizações[Explicações],"",0,-1) -> 0 | AQ8: =_xlfn.XLOOKUP(Tb_Portfólio[[#This Row],[SEI]],Tb_Mapa[SEI],Tb_Mapa[CONSULTOR RESPONSÁVEL],"",0,-1) -> Tony
A9: 01179/2023 | B9: 6ª edição da Série Justiça e pesquisa | C9: contratação de pesquisas empíricas em eixos temáticos destinadas ao conhecimento da função jurisdicional brasileira, análise e diagnóstico dos problemas estruturais e conjunturais dos diversos segmentos do Poder Judiciário e para fornecer subsídios técnicos para a formulação de políticas judiciárias, nos termos do art. 5º, § 1º e § 2º, inc. II, da Lei nº 11.364/2006. | E9: Dra. Lívia Cristina Marques Peres | F9: SEP - Secretaria de Estratégia e Projetos | G9: Gabriela Moreira de Azevedo Soares | H9: DPJ - Departamento de Pesquisas Judiciárias | I9: 01. Desenvolver políticas judiciárias e outros instrumentos para o aperfeiçoamento das atividades dos órgãos do Poder Judiciário e dos seus serviços auxiliares e dos serviços notariais e de registro, e dos demais órgãos correicionais | J9: 09. Aperfeiçoamento da gestão administrativa e da governança judiciária | K9: Resolução 335 /2020 Justiça 4.0 | L9: 44963 | M9: 45597 | N9: =_xlfn.XLOOKUP(Tb_Portfólio[[#This Row],[SEI]],Tb_Atualizações[PROCESSO SEI],Tb_Atualizações[% PREVISTO],"",0,-1) -> 1 | O9: =_xlfn.XLOOKUP(Tb_Portfólio[[#This Row],[SEI]],Tb_Atualizações[PROCESSO SEI],Tb_Atualizações[% EXECUTADO],"",0,-1) -> 1 | P9: =IFERROR(Tb_Portfólio[[#This Row],[% EXECUTADO]]/Tb_Portfólio[[#This Row],[% PREVISTO]],"0%") -> 1 | Q9: =_xlfn.XLOOKUP(Tb_Portfólio[[#This Row],[SEI]],Tb_Atualizações[PROCESSO SEI],Tb_Atualizações[DATA DE ATUALIZAÇÃO],"",0,-1) -> 45726 | R9: =_xlfn.XLOOKUP(Tb_Portfólio[[#This Row],[SEI]],Tb_Atualizações[PROCESSO SEI],Tb_Atualizações[Mês],,0,-1) -> 45689 | U9: =IF(Tb_Portfólio[[#This Row],[% EXECUTADO]]=100%,"Finalizado",IF(Tb_Portfólio[[#This Row],[PREVISÃO DE TERMINO]]<Tb_Portfólio[[#This Row],[Hoje]],"Atrasado ou Crítico",IF(Tb_Portfólio[[#This Row],[% EXECUTADO]]=0,"Autorizado",IF(Tb_Portfólio[[#This Row],[MEDIÇÃO DE STATUS]]>=95%,"No prazo",IF(Tb_Portfólio[[#This Row],[MEDIÇÃO DE STATUS]]<85%,"Atrasado ou Crítico",IF(Tb_Portfólio[[#This Row],[MEDIÇÃO DE STATUS]]<=95%,"Em atenção")))))) -> Finalizado | V9: https://www.cnj.jus.br/editais-3/ | W9: =IFERROR(Tb_Portfólio[[#This Row],[% EXECUTADO]]/Tb_Portfólio[[#This Row],[% PREVISTO]],0) -> 1 | X9: 1-Instituto Cíclica - Estudo sobre a redução do número de adolescentes em cumprimento de medidas socioeducativas de meio fechado no Brasil"; 2- FADEP/USP - Características do racismo estrutural reproduzido no sistema de justiça; 3 - Centro Brasileiro de Análise e Planejamento – CEBRAP - Pessoas com transtorno mental em conflito com a lei no Brasil: itinerários jurídicos e portas de saída; 4 - Associação Brasileira de Jurimetria (ABJ) - Diagnóstico sobre a devolução de crianças e adolescentes em estágio de convivência e adotadas; 5 - Instituto Veredas - Trajetórias no mundo do trabalho de pessoas privadas de liberdade e egressas do sistema prisional: desafios e boas práticas na interface entre a garantia de Direitos Fundamentais e Justiça Criminal; 6 - INSPER - Instituto de Ensino e Pesquisa - Caminhos da tortura na justiça juvenil brasileira: o papel do poder judiciário; 7 - Publicação dos relatórios | Y9: 2937685 | Z9: 2406900.5 | AB9: Dra. Lívia Cristina Marques Peres | AC9: DPJ - Departamento de Pesquisas Judiciárias | AE9: • Instituto Cíclica - Estudo sobre a redução do número de adolescentes em cumprimento de medidas socioeducativas de meio fechado no Brasil". • FADEP/USP - Características do racismo estrutural reproduzido no sistema de justiça • Centro Brasileiro de Análise e Planejamento – CEBRAP - Pessoas com transtorno mental em conflito com a lei no Brasil: itinerários jurídicos e portas de saída. • Associação Brasileira de Jurimetria (ABJ) - Diagnóstico sobre a devolução de crianças e adolescentes em estágio de convivência e adotadas. • Instituto Veredas - Trajetórias no mundo do trabalho de pessoas privadas de liberdade e egressas do sistema prisional: desafios e boas práticas na interface entre a garantia de Direitos Fundamentais e Justiça Criminal. • INSPER - Instituto de Ensino e Pesquisa - Caminhos da tortura na justiça juvenil brasileira: o papel do poder judiciário • Publicação dos relatórios | AF9: =TODAY() -> 46176 | AJ9: =2024&Tb_Portfólio[[#This Row],[SEI]] -> 202401179/2023 | AK9: =IFERROR(IF(MATCH(AJ9,Atualizações!$P$1:$P$1265,0)>0, "Sim"), "Não") -> Sim | AL9: =2025&Tb_Portfólio[[#This Row],[SEI]] -> 202501179/2023 | AM9: =IFERROR(IF(MATCH(AL9,Atualizações!$P$1:$P$2994,0)>0, "Sim"), "Não") -> Sim | AN9: =2026&Tb_Portfólio[[#This Row],[SEI]] -> 202601179/2023 | AO9: =IFERROR(IF(MATCH(AN9,Atualizações!$P$1:$P$2994,0)>0, "Sim"), "Não") -> Não | AP9: =_xlfn.XLOOKUP(Tb_Portfólio[[#This Row],[SEI]],Tb_Atualizações[PROCESSO SEI],Tb_Atualizações[Explicações],"",0,-1) -> Projeto finalizado. O gerente está providenciando o Termo de Encerramento. | AQ9: =_xlfn.XLOOKUP(Tb_Portfólio[[#This Row],[SEI]],Tb_Mapa[SEI],Tb_Mapa[CONSULTOR RESPONSÁVEL],"",0,-1) -> Igor/Finalizado
A10: 01247/2025 | B10: Painel da Fazenda Nacional. | C10: Produzir novo painel digital denominado "Painel Fazenda Nacional”, de acordo com a Portaria Conjunta Nº 7 de 23/10/2023, que dispõe sobre procedimentos, iniciativas e estratégias para racionalizar e aprimorar o fluxo de execuções fiscais promovidas pela Procuradoria-Geral da Fazenda Nacional. | E10: Dra. Ana Lúcia Andrade de Aguiar | F10: SEP - Secretaria de Estratégia e Projetos | G10: André José da Silva Lima | H10: PNUD | I10: 03. Fomentar a gestão da qualidade dos dados no Poder Judiciário; 13. Estimular a desburocratização no Poder Judiciário; e 04. Promover a disseminação das informações, de forma padronizada e sistêmica | J10: 03. Agilidade e produtividade na prestação jurisdicional; e 02. Fortalecimento da Relação Institucional do Judiciário com a Sociedade | K10: Estratégia Nacional de Tecnologia da Informação e Comunicação do Poder Judiciário (ENTIC-JUD), Resolução CNJ n. 370/2021, e com o Programa Justiça 4.0 - Eixo Fortalecimento de Capacidades Institucionais do CNJ (transferência de conhecimento e soluções com foco na segurança jurídica, sustentabilidade de projetos e eficiência da prestação jurisdicional. | L10: 45689 | M10: 46387 | N10: =_xlfn.XLOOKUP(Tb_Portfólio[[#This Row],[SEI]],Tb_Atualizações[PROCESSO SEI],Tb_Atualizações[% PREVISTO],"",0,-1) -> 0.67 | O10: =_xlfn.XLOOKUP(Tb_Portfólio[[#This Row],[SEI]],Tb_Atualizações[PROCESSO SEI],Tb_Atualizações[% EXECUTADO],"",0,-1) -> 0.51 | P10: =IFERROR(Tb_Portfólio[[#This Row],[% EXECUTADO]]/Tb_Portfólio[[#This Row],[% PREVISTO]],"0%") -> 0.76119403 | Q10: =_xlfn.XLOOKUP(Tb_Portfólio[[#This Row],[SEI]],Tb_Atualizações[PROCESSO SEI],Tb_Atualizações[DATA DE ATUALIZAÇÃO],"",0,-1) -> 46167 | R10: =_xlfn.XLOOKUP(Tb_Portfólio[[#This Row],[SEI]],Tb_Atualizações[PROCESSO SEI],Tb_Atualizações[Mês],,0,-1) -> 46143 | T10: Justiça 4.0 | U10: =IF(Tb_Portfólio[[#This Row],[% EXECUTADO]]=100%,"Finalizado",IF(Tb_Portfólio[[#This Row],[PREVISÃO DE TERMINO]]<Tb_Portfólio[[#This Row],[Hoje]],"Atrasado ou Crítico",IF(Tb_Portfólio[[#This Row],[% EXECUTADO]]=0,"Autorizado",IF(Tb_Portfólio[[#This Row],[MEDIÇÃO DE STATUS]]>=95%,"No prazo",IF(Tb_Portfólio[[#This Row],[MEDIÇÃO DE STATUS]]<85%,"Atrasado ou Crítico",IF(Tb_Portfólio[[#This Row],[MEDIÇÃO DE STATUS]]<=95%,"Em atenção")))))) -> Atrasado ou Crítico | W10: =IFERROR(Tb_Portfólio[[#This Row],[% EXECUTADO]]/Tb_Portfólio[[#This Row],[% PREVISTO]],0) -> 0.76119403 | X10: - Extração dos dados do Datajud; - Tratamento e Processamento de Dados; - Análise Estatística e Criação de Indicadores; - Criação do Painel em BI; - Lançamento e divulgação e implementação de novas funcionalidades | Y10: 2958354.8 | AA10: https://www.cnj.jus.br/tecnologia-da-informacao-e-comunicacao/justica-4-0/ | AB10: Dra. Ana Lúcia Andrade de Aguiar | AC10: DPJ - Departamento de Pesquisas Judiciárias | AD10: Aumento da transparência ativa. | AF10: =TODAY() -> 46176 | AG10: Isabely Fontana da Mota | AH10: DPJ - Departamento de Pesquisas Judiciárias | AJ10: =2024&Tb_Portfólio[[#This Row],[SEI]] -> 202401247/2025 | AK10: =IFERROR(IF(MATCH(AJ10,Atualizações!$P$1:$P$1265,0)>0, "Sim"), "Não") -> Não | AL10: =2025&Tb_Portfólio[[#This Row],[SEI]] -> 202501247/2025 | AM10: =IFERROR(IF(MATCH(AL10,Atualizações!$P$1:$P$2994,0)>0, "Sim"), "Não") -> Sim | AN10: =2026&Tb_Portfólio[[#This Row],[SEI]] -> 202601247/2025 | AO10: =IFERROR(IF(MATCH(AN10,Atualizações!$P$1:$P$2994,0)>0, "Sim"), "Não") -> Sim | AP10: =_xlfn.XLOOKUP(Tb_Portfólio[[#This Row],[SEI]],Tb_Atualizações[PROCESSO SEI],Tb_Atualizações[Explicações],"",0,-1) -> 0 | AQ10: =_xlfn.XLOOKUP(Tb_Portfólio[[#This Row],[SEI]],Tb_Mapa[SEI],Tb_Mapa[CONSULTOR RESPONSÁVEL],"",0,-1) -> Tony
A11: 01487/2022 | B11: Domicílio Judicial Eletrônico | C11: Desenvolvimento de módulo intitulado "Domicílio Judicial Eletrônico" para centralizar as comunicações processuais através de desenvolvimento de API e outros mecanismos de integração assíncrona por meio de um sistema centralizador. | E11: Dr. Adriano da Silva Araújo | F11: DTI - Departamento de Tecnologia da Informação e Comunicação | G11: Luciana Martins Frassetto de Freitas | H11: PNUD | I11: 09. Fomentar e incrementar a produção de soluções tecnológicas, com foco em inovação e transformação digital | J11: 02. Fortalecimento da Relação Institucional do Judiciário com a Sociedade | K11: Resolução 335 /2020 Justiça 4.0 | L11: 44473 | M11: 45566 | N11: =_xlfn.XLOOKUP(Tb_Portfólio[[#This Row],[SEI]],Tb_Atualizações[PROCESSO SEI],Tb_Atualizações[% PREVISTO],"",0,-1) -> 1 | O11: =_xlfn.XLOOKUP(Tb_Portfólio[[#This Row],[SEI]],Tb_Atualizações[PROCESSO SEI],Tb_Atualizações[% EXECUTADO],"",0,-1) -> 1 | P11: =IFERROR(Tb_Portfólio[[#This Row],[% EXECUTADO]]/Tb_Portfólio[[#This Row],[% PREVISTO]],"0%") -> 1 | Q11: =_xlfn.XLOOKUP(Tb_Portfólio[[#This Row],[SEI]],Tb_Atualizações[PROCESSO SEI],Tb_Atualizações[DATA DE ATUALIZAÇÃO],"",0,-1) -> 45544 | R11: =_xlfn.XLOOKUP(Tb_Portfólio[[#This Row],[SEI]],Tb_Atualizações[PROCESSO SEI],Tb_Atualizações[Mês],,0,-1) -> 45505 | T11: Justiça 4.0 | U11: =IF(Tb_Portfólio[[#This Row],[% EXECUTADO]]=100%,"Finalizado",IF(Tb_Portfólio[[#This Row],[PREVISÃO DE TERMINO]]<Tb_Portfólio[[#This Row],[Hoje]],"Atrasado ou Crítico",IF(Tb_Portfólio[[#This Row],[% EXECUTADO]]=0,"Autorizado",IF(Tb_Portfólio[[#This Row],[MEDIÇÃO DE STATUS]]>=95%,"No prazo",IF(Tb_Portfólio[[#This Row],[MEDIÇÃO DE STATUS]]<85%,"Atrasado ou Crítico",IF(Tb_Portfólio[[#This Row],[MEDIÇÃO DE STATUS]]<=95%,"Em atenção")))))) -> Finalizado | V11: https://www.cnj.jus.br/tecnologia-da-informacao-e-comunicacao/justica-4-0/domicilio-judicial-eletronico/ | W11: =IFERROR(Tb_Portfólio[[#This Row],[% EXECUTADO]]/Tb_Portfólio[[#This Row],[% PREVISTO]],0) -> 1 | X11: - Etapa 1 – Iniciação e planejamento: Cooperação Técnica, resolução validada, documentação do projeto com os requisitos negociais, inception/capacitação da equipe; - Etapa 2 – Estruturação: Estruturação técnica, base estrutural do projeto, jornadas definidas, refactoring e versão inicial da API. - Etapa 3 – Evolução: Especificações funcionais, desenvolvimento (cadastro e API), início do stress test. - Etapa 4 – Consolidação: Piloto com os tribunais (teste de API), especificação faltante de novos serviços, validação com os bancos, homologação, implementação em produção. - Etapa 5 – Divulgação e encerramento: definição da estratégia de capacitação/divulgação do sistema, construção do site, ajustes e manutenções, encerramento da cooperação técnica. | AA11: https://www.cnj.jus.br/tecnologia-da-informacao-e-comunicacao/justica-4-0/ | AB11: Dr. Adriano da Silva Araújo | AC11: DTI - Departamento de Tecnologia da Informação e Comunicação | AD11: Disponibilizar funcionalidade que possibilitará maior velocidade na localização do destinatário da comunicação processual | AE11: Iniciação e Planejamento: 1. Termo de Cooperação Técnica - CNJ e FEBRABAN 2. Termo de Abertura do Projeto 3. Inception da equipe 4. Termo de Confidencialidade pela equipe 5. Plano Geral do Projeto 6. documento Análise de Requisitos 7. Plano de Trabalho Estruturação do sistema: 1. Termo de Adesão 2. Cadastro do CNPJ e CPF (público, privado e pessoa física) 3. Perfis de usuários (administrador, gestor e preposto) 4. Desenvolvimento da Autenticação PJ e PF 5. Definição da arquitetura 6. Vinculação de filiais e coligadas 7. Acesso à Comunicação processual 8. Filtros da Comunicação processual 9. realizar testes unitários e de usabilidade 10. Criação da base de log 11. integração front e back 12. Realização de testes de performance 13. Desenvolvimento do perfil advogado; 14. Criação do serviço de ticket | AF11: =TODAY() -> 46176 | AG11: Marcos Paulo Santos Calixto | AH11: DTI - Departamento de Tecnologia da Informação e Comunicação | AJ11: =2024&Tb_Portfólio[[#This Row],[SEI]] -> 202401487/2022 | AK11: =IFERROR(IF(MATCH(AJ11,Atualizações!$P$1:$P$1265,0)>0, "Sim"), "Não") -> Sim | AL11: =2025&Tb_Portfólio[[#This Row],[SEI]] -> 202501487/2022 | AM11: =IFERROR(IF(MATCH(AL11,Atualizações!$P$1:$P$2994,0)>0, "Sim"), "Não") -> Não | AN11: =2026&Tb_Portfólio[[#This Row],[SEI]] -> 202601487/2022 | AO11: =IFERROR(IF(MATCH(AN11,Atualizações!$P$1:$P$2994,0)>0, "Sim"), "Não") -> Não | AP11: =_xlfn.XLOOKUP(Tb_Portfólio[[#This Row],[SEI]],Tb_Atualizações[PROCESSO SEI],Tb_Atualizações[Explicações],"",0,-1) -> 0 | AQ11: =_xlfn.XLOOKUP(Tb_Portfólio[[#This Row],[SEI]],Tb_Mapa[SEI],Tb_Mapa[CONSULTOR RESPONSÁVEL],"",0,-1) -> Igor/Finalizado
A12: 01703/2024 | B12: Monitoramento: soluções da PDPJ-Br | C12: Criar uma plataforma integrada com dashboard unificado para monitorar globalmente a adoção e o impacto das soluções tecnológicas da PDPJ-Br | E12: Dr. Alexandre Libonati de Abreu | F12: DTI - Departamento de Tecnologia da Informação e Comunicação | G12: Gustavo Martins Pereira | H12: PNUD | I12: 09. Fomentar e incrementar a produção de soluções tecnológicas, com foco em inovação e transformação digital | J12: 12. Fortalecimento da estratégia nacional de TIC e de proteção de dados | K12: Programa Justiça 4.0 (Projeto BRA/20/003) | L12: 45373 | M12: 45639 | N12: =_xlfn.XLOOKUP(Tb_Portfólio[[#This Row],[SEI]],Tb_Atualizações[PROCESSO SEI],Tb_Atualizações[% PREVISTO],"",0,-1) -> 1 | O12: =_xlfn.XLOOKUP(Tb_Portfólio[[#This Row],[SEI]],Tb_Atualizações[PROCESSO SEI],Tb_Atualizações[% EXECUTADO],"",0,-1) -> 1 | P12: =IFERROR(Tb_Portfólio[[#This Row],[% EXECUTADO]]/Tb_Portfólio[[#This Row],[% PREVISTO]],"0%") -> 1 | Q12: =_xlfn.XLOOKUP(Tb_Portfólio[[#This Row],[SEI]],Tb_Atualizações[PROCESSO SEI],Tb_Atualizações[DATA DE ATUALIZAÇÃO],"",0,-1) -> 45645 | R12: =_xlfn.XLOOKUP(Tb_Portfólio[[#This Row],[SEI]],Tb_Atualizações[PROCESSO SEI],Tb_Atualizações[Mês],,0,-1) -> 45627 | T12: Justiça 4.0 | U12: =IF(Tb_Portfólio[[#This Row],[% EXECUTADO]]=100%,"Finalizado",IF(Tb_Portfólio[[#This Row],[PREVISÃO DE TERMINO]]<Tb_Portfólio[[#This Row],[Hoje]],"Atrasado ou Crítico",IF(Tb_Portfólio[[#This Row],[% EXECUTADO]]=0,"Autorizado",IF(Tb_Portfólio[[#This Row],[MEDIÇÃO DE STATUS]]>=95%,"No prazo",IF(Tb_Portfólio[[#This Row],[MEDIÇÃO DE STATUS]]<85%,"Atrasado ou Crítico",IF(Tb_Portfólio[[#This Row],[MEDIÇÃO DE STATUS]]<=95%,"Em atenção")))))) -> Finalizado | V12: https://app.powerbi.com/view?r=eyJrIjoiMjA5YmQwMjYtY2QwYy00YmYzLThmYmEtODg5YmUxZjJhNDg4IiwidCI6ImFkOTE5MGU2LWM0NWQtNDYwMC1iYzVjLWVjYTU1NGNjZjQ5NyIsImMiOjJ9 | W12: =IFERROR(Tb_Portfólio[[#This Row],[% EXECUTADO]]/Tb_Portfólio[[#This Row],[% PREVISTO]],0) -> 1 | AA12: https://www.cnj.jus.br/tecnologia-da-informacao-e-comunicacao/justica-4-0/ | AB12: Dr. Dorotheo Barbosa Neto | AC12: SEP - Secretaria de Estratégia e Projetos | AD12: Benefício 1 - Estruturar uma estratégia de monitoramento das integrações dos Tribunais aos sistemas do Portal de Serviços do Programa Justiça 4.0 Benefício 2 - Elaboração de um Painel de BI único de Monitoramento do Programa Justiça 4.0 | AF12: =TODAY() -> 46176 | AG12: Flávio Feitosa Costa | AH12: DTI - Departamento de Tecnologia da Informação e Comunicação | AJ12: =2024&Tb_Portfólio[[#This Row],[SEI]] -> 202401703/2024 | AK12: =IFERROR(IF(MATCH(AJ12,Atualizações!$P$1:$P$1265,0)>0, "Sim"), "Não") -> Sim | AL12: =2025&Tb_Portfólio[[#This Row],[SEI]] -> 202501703/2024 | AM12: =IFERROR(IF(MATCH(AL12,Atualizações!$P$1:$P$2994,0)>0, "Sim"), "Não") -> Não | AN12: =2026&Tb_Portfólio[[#This Row],[SEI]] -> 202601703/2024 | AO12: =IFERROR(IF(MATCH(AN12,Atualizações!$P$1:$P$2994,0)>0, "Sim"), "Não") -> Não | AP12: =_xlfn.XLOOKUP(Tb_Portfólio[[#This Row],[SEI]],Tb_Atualizações[PROCESSO SEI],Tb_Atualizações[Explicações],"",0,-1) -> Projeto finalizado e já consta TEP no processo. Todavia, o despacho de encaminhamento para o ECP ainda não foi assinado. Daniel informa que estão esperando o retorno do dr. Dorotheo, no dia 20/1, para assinatura do despacho | AQ12: =_xlfn.XLOOKUP(Tb_Portfólio[[#This Row],[SEI]],Tb_Mapa[SEI],Tb_Mapa[CONSULTOR RESPONSÁVEL],"",0,-1) -> Igor/Finalizado
A13: 01764/2020 | B13: Mineração de Processos do Pje | C13: Desenvolvimento de uma metodologia para aplicação de técnicas de mineração de processos nas bases de dados do PJE | D13: presente projeto tem por objetivo criar um laboratório de mineração de processos no âmbito do judiciário brasileiro e instrumentalizar servidores e magistrados no uso dessa tecnologia, visando à redução do retrabalho através da identificação de oportunidades de melhorias nos fluxos dos processos, mensuração dos efeitos das mudanças realizadas, implementação de melhorias contínuas nos fluxos existentes, aumento da produtividade pela eliminação de gargalos, reconhecimento e ajuste de desvios nos fluxos estabelecidos e redução dos custos operacionais. E tem como objetivos específicos: Análise das ferramentas comerciais e acadêmicas de mineração de processos disponíveis com vistas a identificar quais funcionalidades de cada uma delas mais se adequam às necessidades do judiciário; Implantação do laboratório virtual, incluindo ferramentas, equipes técnica e gestora, bibliografia de referência, infraestrutura de comunicação interna e externa; Desenvolvimento de metodologia para aplicação de técnicas de mineração de processos nas bases de dados do PJe com o objetivo de identificar, melhorar e padronizar os fluxos de processos no judiciário; Validação da metodologia desenvolvida nos tribunais participantes deste projeto; Aplicação da metodologia em tribunais parceiros, contemplando treinamento para uso autônomo da metodologia; Documentação da metodologia e melhores práticas para sua aplicação. Utilização da base nacional do PJe, mantida pelo DPJ/CNJ, como repositório central para projetos de Mineração de Processo. | E13: Dr. João Thiago de França Guerra | F13: DTI - Departamento de Tecnologia da Informação e Comunicação | G13: Antônio Augusto Raposo | H13: Memora | I13: 09. Fomentar e incrementar a produção de soluções tecnológicas, com foco em inovação e transformação digital | J13: 12. Fortalecimento da estratégia nacional de TIC e de proteção de dados | L13: 44013 | M13: 46630 | N13: =_xlfn.XLOOKUP(Tb_Portfólio[[#This Row],[SEI]],Tb_Atualizações[PROCESSO SEI],Tb_Atualizações[% PREVISTO],"",0,-1) -> 0.89 | O13: =_xlfn.XLOOKUP(Tb_Portfólio[[#This Row],[SEI]],Tb_Atualizações[PROCESSO SEI],Tb_Atualizações[% EXECUTADO],"",0,-1) -> 0.89 | P13: =IFERROR(Tb_Portfólio[[#This Row],[% EXECUTADO]]/Tb_Portfólio[[#This Row],[% PREVISTO]],"0%") -> 1 | Q13: =_xlfn.XLOOKUP(Tb_Portfólio[[#This Row],[SEI]],Tb_Atualizações[PROCESSO SEI],Tb_Atualizações[DATA DE ATUALIZAÇÃO],"",0,-1) -> 46142 | R13: =_xlfn.XLOOKUP(Tb_Portfólio[[#This Row],[SEI]],Tb_Atualizações[PROCESSO SEI],Tb_Atualizações[Mês],,0,-1) -> 46113 | U13: =IF(Tb_Portfólio[[#This Row],[% EXECUTADO]]=100%,"Finalizado",IF(Tb_Portfólio[[#This Row],[PREVISÃO DE TERMINO]]<Tb_Portfólio[[#This Row],[Hoje]],"Atrasado ou Crítico",IF(Tb_Portfólio[[#This Row],[% EXECUTADO]]=0,"Autorizado",IF(Tb_Portfólio[[#This Row],[MEDIÇÃO DE STATUS]]>=95%,"No prazo",IF(Tb_Portfólio[[#This Row],[MEDIÇÃO DE STATUS]]<85%,"Atrasado ou Crítico",IF(Tb_Portfólio[[#This Row],[MEDIÇÃO DE STATUS]]<=95%,"Em atenção")))))) -> No prazo | W13: =IFERROR(Tb_Portfólio[[#This Row],[% EXECUTADO]]/Tb_Portfólio[[#This Row],[% PREVISTO]],0) -> 1 | X13: Meta 1: desenvolvimento de uma metodologia para aplicação de técnicas de mineração de processos nas bases de dados do PJe; Meta 2: análise das 22 (vinte e duas) ferramentas de mineração de processos citadas no relatório Market Guide for Process Mining (publicado em 17 de junho de 2019 - ID G00387812 - Gartner).; Meta 3: implantação de um Laboratório Virtual de Mineração de Processos; O ambiente virtual contará com uma ferramenta comercial e de uma ferramenta acadêmica para mineração de processos.; Meta 4: validação da metodologia com magistrados e servidores em tribunais participantes deste projeto; Meta 5: projeto de expansão do laboratório. Meta 5: Lançamento da ferramenta de mineração de processos do CNJ e projeto de expansão do laboratório. Meta 6: Apropriação tecnológica da atual versão do protótipo funcional para mineração de processos a partir do log de eventos do CODEX e treinamento da equipe nas tecnologias a serem utilizadas. Meta 7: Explorar a base de dados do CODEX para descobrir redes sociais[1] do relacionamento funcional entre os servidores e magistrados do judiciário brasileiro. Meta 8: Explorar a base de dados do CODEX para identificar as atividades executadas por cada servidor e aferir seu nível de eficiência global e durante a realização de atividades específicas. Meta 9: Realizar pesquisas para contribuir com o trabalho das corregedorias Meta 10: Treinar magistrados e servidores de tribunais integrados ao CODEX sobre mineração de processos e uso da ferramenta, coletando subsídios para aprimorar a ferramenta desenvolvida neste projeto. Meta 11: Avaliar aspectos não funcionais como desempenho da ferramenta Meta 12: Transferência tecnológica da ferramenta de mineração de processos para a equipe técnica do CNJ. | AB13: Dr. João Thiago de França Guerra | AC13: DTI - Departamento de Tecnologia da Informação e Comunicação | AE13: - Metodologia - Treinamento - Ferramenta Jump | AF13: =TODAY() -> 46176 | AJ13: =2024&Tb_Portfólio[[#This Row],[SEI]] -> 202401764/2020 | AK13: =IFERROR(IF(MATCH(AJ13,Atualizações!$P$1:$P$1265,0)>0, "Sim"), "Não") -> Sim | AL13: =2025&Tb_Portfólio[[#This Row],[SEI]] -> 202501764/2020 | AM13: =IFERROR(IF(MATCH(AL13,Atualizações!$P$1:$P$2994,0)>0, "Sim"), "Não") -> Sim | AN13: =2026&Tb_Portfólio[[#This Row],[SEI]] -> 202601764/2020 | AO13: =IFERROR(IF(MATCH(AN13,Atualizações!$P$1:$P$2994,0)>0, "Sim"), "Não") -> Sim | AP13: =_xlfn.XLOOKUP(Tb_Portfólio[[#This Row],[SEI]],Tb_Atualizações[PROCESSO SEI],Tb_Atualizações[Explicações],"",0,-1) -> 0 | AQ13: =_xlfn.XLOOKUP(Tb_Portfólio[[#This Row],[SEI]],Tb_Mapa[SEI],Tb_Mapa[CONSULTOR RESPONSÁVEL],"",0,-1) -> Tony
A14: 01809/2025 | B14: Gestão de Clientes | C14: Implementar uma solução integrada para a gestão de acessos e credenciais às APIs da PDPJ-Br, garantindo maior segurança, controle e eficiência. A iniciativa envolve a centralização da gestão de credenciais (Client ID e Secret ID), a automação do processo de tarifação e o desenvolvimento de um Portal do Desenvolvedor para facilitar a integração com as APIs. Além disso, será implementado um sistema de monitoramento em tempo real e rate limiting para garantir a estabilidade e rastreabilidade no uso dos serviços | E14: Dr. Dorotheo Barbosa Neto | F14: SEP - Secretaria de Estratégia e Projetos | G14: Cristiany dos Santos Souza | H14: PNUD | I14: 09. Fomentar e incrementar a produção de soluções tecnológicas, com foco em inovação e transformação digital | J14: 09. Aperfeiçoamento da gestão administrativa e da governança judiciária; e 12. Fortalecimento da estratégia nacional de TIC e de proteção de dados | L14: 45743 | M14: 46083 | N14: =_xlfn.XLOOKUP(Tb_Portfólio[[#This Row],[SEI]],Tb_Atualizações[PROCESSO SEI],Tb_Atualizações[% PREVISTO],"",0,-1) -> 1 | O14: =_xlfn.XLOOKUP(Tb_Portfólio[[#This Row],[SEI]],Tb_Atualizações[PROCESSO SEI],Tb_Atualizações[% EXECUTADO],"",0,-1) -> 1 | P14: =IFERROR(Tb_Portfólio[[#This Row],[% EXECUTADO]]/Tb_Portfólio[[#This Row],[% PREVISTO]],"0%") -> 1 | Q14: =_xlfn.XLOOKUP(Tb_Portfólio[[#This Row],[SEI]],Tb_Atualizações[PROCESSO SEI],Tb_Atualizações[DATA DE ATUALIZAÇÃO],"",0,-1) -> 46057 | R14: =_xlfn.XLOOKUP(Tb_Portfólio[[#This Row],[SEI]],Tb_Atualizações[PROCESSO SEI],Tb_Atualizações[Mês],,0,-1) -> 46023 | T14: Justiça 4.0 | U14: =IF(Tb_Portfólio[[#This Row],[% EXECUTADO]]=100%,"Finalizado",IF(Tb_Portfólio[[#This Row],[PREVISÃO DE TERMINO]]<Tb_Portfólio[[#This Row],[Hoje]],"Atrasado ou Crítico",IF(Tb_Portfólio[[#This Row],[% EXECUTADO]]=0,"Autorizado",IF(Tb_Portfólio[[#This Row],[MEDIÇÃO DE STATUS]]>=95%,"No prazo",IF(Tb_Portfólio[[#This Row],[MEDIÇÃO DE STATUS]]<85%,"Atrasado ou Crítico",IF(Tb_Portfólio[[#This Row],[MEDIÇÃO DE STATUS]]<=95%,"Em atenção")))))) -> Finalizado | W14: =IFERROR(Tb_Portfólio[[#This Row],[% EXECUTADO]]/Tb_Portfólio[[#This Row],[% PREVISTO]],0) -> 1 | X14: Portal do Desenvolvedor e Gestão de Acessos; Monitoramento e Segurança; Integração de Tarifação e Faturamento. | Y14: 1059115.6 | AA14: https://www.cnj.jus.br/tecnologia-da-informacao-e-comunicacao/justica-4-0/ | AB14: Dr. Dorotheo Barbosa Neto | AC14: SEP - Secretaria de Estratégia e Projetos | AD14: Benefício 1: Implementação da Gestão de Clientes | AE14: -Base e preparação -Portal do desenvovedor -Catátlogo e conteúdo -Governança de acesso -Integrações e produção -Monitoramento e bilhetagem | AF14: =TODAY() -> 46176 | AG14: Thiago de Andrade Vieira | AH14: DTI - Departamento de Tecnologia da Informação e Comunicação | AJ14: =2024&Tb_Portfólio[[#This Row],[SEI]] -> 202401809/2025 | AK14: =IFERROR(IF(MATCH(AJ14,Atualizações!$P$1:$P$1265,0)>0, "Sim"), "Não") -> Não | AL14: =2025&Tb_Portfólio[[#This Row],[SEI]] -> 202501809/2025 | AM14: =IFERROR(IF(MATCH(AL14,Atualizações!$P$1:$P$2994,0)>0, "Sim"), "Não") -> Sim | AN14: =2026&Tb_Portfólio[[#This Row],[SEI]] -> 202601809/2025 | AO14: =IFERROR(IF(MATCH(AN14,Atualizações!$P$1:$P$2994,0)>0, "Sim"), "Não") -> Sim | AP14: =_xlfn.XLOOKUP(Tb_Portfólio[[#This Row],[SEI]],Tb_Atualizações[PROCESSO SEI],Tb_Atualizações[Explicações],"",0,-1) -> 0 | AQ14: =_xlfn.XLOOKUP(Tb_Portfólio[[#This Row],[SEI]],Tb_Mapa[SEI],Tb_Mapa[CONSULTOR RESPONSÁVEL],"",0,-1) -> Raphael
A15: 01913/2025 | B15: Desenvolvimento de um Conjunto de Solução em Gestão de Dados para a Corregedoria Nacional de Justiça | C15: O projeto visa implementar um conjunto de soluções em gestão de dados e tecnologia da informação que possibilite à Corregedoria Nacional de Justiça acessar, extrair, agrupar e analisar, de forma eficiente e segura, o desenvolvimento e a implementação de ferramentas de controle, monitoramento e automação envolvendo todos os Tribunais de Justiça dos Estados e do Distrito Federal, Tribunais Regionais Federais e Tribunais Regionais do Trabalho do Brasil | E15: Ministro Mauro Campbell | F15: Corregedoria Nacional de Justiça | G15: Caio Henrique Faustino da Silva | H15: Corregedoria Nacional de Justiça | I15: 05. Aprimorar as inspeções e correições | J15: 03. Agilidade e produtividade na prestação jurisdicional; 04. Enfrentamento à corrupção, à improbidade administrativa e aos ilícitos eleitorais; e 09. Aperfeiçoamento da gestão administrativa e da governança judiciária | L15: 45700 | M15: 45807 | N15: =_xlfn.XLOOKUP(Tb_Portfólio[[#This Row],[SEI]],Tb_Atualizações[PROCESSO SEI],Tb_Atualizações[% PREVISTO],"",0,-1) -> 1 | O15: =_xlfn.XLOOKUP(Tb_Portfólio[[#This Row],[SEI]],Tb_Atualizações[PROCESSO SEI],Tb_Atualizações[% EXECUTADO],"",0,-1) -> 0.75 | P15: =IFERROR(Tb_Portfólio[[#This Row],[% EXECUTADO]]/Tb_Portfólio[[#This Row],[% PREVISTO]],"0%") -> 0.75 | Q15: =_xlfn.XLOOKUP(Tb_Portfólio[[#This Row],[SEI]],Tb_Atualizações[PROCESSO SEI],Tb_Atualizações[DATA DE ATUALIZAÇÃO],"",0,-1) -> 46038 | R15: =_xlfn.XLOOKUP(Tb_Portfólio[[#This Row],[SEI]],Tb_Atualizações[PROCESSO SEI],Tb_Atualizações[Mês],,0,-1) -> 45931 | U15: =IF(Tb_Portfólio[[#This Row],[% EXECUTADO]]=100%,"Finalizado",IF(Tb_Portfólio[[#This Row],[PREVISÃO DE TERMINO]]<Tb_Portfólio[[#This Row],[Hoje]],"Atrasado ou Crítico",IF(Tb_Portfólio[[#This Row],[% EXECUTADO]]=0,"Autorizado",IF(Tb_Portfólio[[#This Row],[MEDIÇÃO DE STATUS]]>=95%,"No prazo",IF(Tb_Portfólio[[#This Row],[MEDIÇÃO DE STATUS]]<85%,"Atrasado ou Crítico",IF(Tb_Portfólio[[#This Row],[MEDIÇÃO DE STATUS]]<=95%,"Em atenção")))))) -> Atrasado ou Crítico | W15: =IFERROR(Tb_Portfólio[[#This Row],[% EXECUTADO]]/Tb_Portfólio[[#This Row],[% PREVISTO]],0) -> 0.75 | X15: Mapeamento e Seleção dos Dados; Painel de BI | AB15: Dra. Luciana Dória de Medeiros Chaves | AC15: Corregedoria Nacional de Justiça | AD15: Benefício 1: Garantir maior eficiência aos expedientes de inspeção e fiscalização da CN/CNJ; Benefício 2: Assegurar o constante aprimoramento das estratégias de monitoramento e fiscalização da CN/CNJ Benefício 3:Permitir que a CN/CNJ gerencie riscos e mitigue crises no Poder Judiciário | AE15: Mapeamento e Seleção dos Dados; Painel de BI | AF15: =TODAY() -> 46176 | AJ15: =2024&Tb_Portfólio[[#This Row],[SEI]] -> 202401913/2025 | AK15: =IFERROR(IF(MATCH(AJ15,Atualizações!$P$1:$P$1265,0)>0, "Sim"), "Não") -> Não | AL15: =2025&Tb_Portfólio[[#This Row],[SEI]] -> 202501913/2025 | AM15: =IFERROR(IF(MATCH(AL15,Atualizações!$P$1:$P$2994,0)>0, "Sim"), "Não") -> Sim | AN15: =2026&Tb_Portfólio[[#This Row],[SEI]] -> 202601913/2025 | AO15: =IFERROR(IF(MATCH(AN15,Atualizações!$P$1:$P$2994,0)>0, "Sim"), "Não") -> Sim | AP15: =_xlfn.XLOOKUP(Tb_Portfólio[[#This Row],[SEI]],Tb_Atualizações[PROCESSO SEI],Tb_Atualizações[Explicações],"",0,-1) -> Medição duplicada para inclusão no portfólio de 2026 | AQ15: =_xlfn.XLOOKUP(Tb_Portfólio[[#This Row],[SEI]],Tb_Mapa[SEI],Tb_Mapa[CONSULTOR RESPONSÁVEL],"",0,-1) -> Igor
A16: 01945/2022 | B16: Capacitação técnica para desenvolvedores nas tecnologias da PDPJ - BR | C16: Desenvolvimento de capacitações em tecnologias Java e Angular aplicadas à PDPJ-Br, na modalidade de Educação a Distância, para o Poder Judiciário brasileiro. | E16: Dr. Dorotheo Barbosa Neto | F16: SEP - Secretaria de Estratégia e Projetos | G16: Tamires Aparecida Ferreira Souza | H16: PNUD | I16: 16. Aperfeiçoar políticas e práticas de Gestão de Pessoas | J16: 10. Aperfeiçoamento da gestão de pessoas | K16: Resolução 335 /2020 Justiça 4.0 | L16: 44971 | M16: 45866 | N16: =_xlfn.XLOOKUP(Tb_Portfólio[[#This Row],[SEI]],Tb_Atualizações[PROCESSO SEI],Tb_Atualizações[% PREVISTO],"",0,-1) -> 1 | O16: =_xlfn.XLOOKUP(Tb_Portfólio[[#This Row],[SEI]],Tb_Atualizações[PROCESSO SEI],Tb_Atualizações[% EXECUTADO],"",0,-1) -> 1 | P16: =IFERROR(Tb_Portfólio[[#This Row],[% EXECUTADO]]/Tb_Portfólio[[#This Row],[% PREVISTO]],"0%") -> 1 | Q16: =_xlfn.XLOOKUP(Tb_Portfólio[[#This Row],[SEI]],Tb_Atualizações[PROCESSO SEI],Tb_Atualizações[DATA DE ATUALIZAÇÃO],"",0,-1) -> 45895 | R16: =_xlfn.XLOOKUP(Tb_Portfólio[[#This Row],[SEI]],Tb_Atualizações[PROCESSO SEI],Tb_Atualizações[Mês],,0,-1) -> 45870 | T16: Justiça 4.0 | U16: =IF(Tb_Portfólio[[#This Row],[% EXECUTADO]]=100%,"Finalizado",IF(Tb_Portfólio[[#This Row],[PREVISÃO DE TERMINO]]<Tb_Portfólio[[#This Row],[Hoje]],"Atrasado ou Crítico",IF(Tb_Portfólio[[#This Row],[% EXECUTADO]]=0,"Autorizado",IF(Tb_Portfólio[[#This Row],[MEDIÇÃO DE STATUS]]>=95%,"No prazo",IF(Tb_Portfólio[[#This Row],[MEDIÇÃO DE STATUS]]<85%,"Atrasado ou Crítico",IF(Tb_Portfólio[[#This Row],[MEDIÇÃO DE STATUS]]<=95%,"Em atenção")))))) -> Finalizado | V16: https://www.cnj.jus.br/tecnologia-da-informacao-e-comunicacao/justica-4-0/capacitacoes/ | W16: =IFERROR(Tb_Portfólio[[#This Row],[% EXECUTADO]]/Tb_Portfólio[[#This Row],[% PREVISTO]],0) -> 1 | X16: 1 - Relatório técnico; 2 - Curso de Java Básico; 3 - Curso de Java Básico - EAD; 4 - Curso de Java Avançado; 5 - 4 - Curso de Java Avançado - EAD; 6 - Curso de Angular; 7 - Curso de Testes Automatizados; 8 - Curso de Angular - EAD; 9 - Curso de Testes Automatizados - EAD. | AA16: https://www.cnj.jus.br/tecnologia-da-informacao-e-comunicacao/justica-4-0/ | AB16: Dr. Adriano da Silva Araújo | AC16: DTI - Departamento de Tecnologia da Informação e Comunicação | AD16: Promoção da qualificação do quadro de servidores do Poder Judiciário nas tecnologias Java e Angular aplicadas à PDPJ-Br, que de forma direta ou indireta contribuem ou pretende contribuir com o desenvolvimento soluções colaborativas na PDPJ-Br. | AE16: • Relatório Técnico • Curso de Java Básico • Curso de Java Básico - EAD • Curso de Java Avançado • Curso de Java Avançado - EAD | AF16: =TODAY() -> 46176 | AG16: Paulo Magnus Pereira Porto | AH16: DTI - Departamento de Tecnologia da Informação e Comunicação | AJ16: =2024&Tb_Portfólio[[#This Row],[SEI]] -> 202401945/2022 | AK16: =IFERROR(IF(MATCH(AJ16,Atualizações!$P$1:$P$1265,0)>0, "Sim"), "Não") -> Sim | AL16: =2025&Tb_Portfólio[[#This Row],[SEI]] -> 202501945/2022 | AM16: =IFERROR(IF(MATCH(AL16,Atualizações!$P$1:$P$2994,0)>0, "Sim"), "Não") -> Sim | AN16: =2026&Tb_Portfólio[[#This Row],[SEI]] -> 202601945/2022 | AO16: =IFERROR(IF(MATCH(AN16,Atualizações!$P$1:$P$2994,0)>0, "Sim"), "Não") -> Não | AP16: =_xlfn.XLOOKUP(Tb_Portfólio[[#This Row],[SEI]],Tb_Atualizações[PROCESSO SEI],Tb_Atualizações[Explicações],"",0,-1) -> TEP formalizado no dia 26/8/2025 por meio do documento 2300117 | AQ16: =_xlfn.XLOOKUP(Tb_Portfólio[[#This Row],[SEI]],Tb_Mapa[SEI],Tb_Mapa[CONSULTOR RESPONSÁVEL],"",0,-1) -> Tony
A17: 02024/2024 | B17: Aperfeiçoamento funcional em temáticas prioritárias para o CNJ e para Justiça Federal (cursos, capacitações, metodologias e ferramentas avançados) – Ciclo Avançado | C17: Desenvolvimento de metodologias e elaboração de cursos, materiais e ferramentas de capacitação na modalidade de Educação a Distância (EaD) na temática de ciência de dados e em nível avançado, em complemento ao projeto anterior finalizado. | E17: Dra. Ana Lúcia Andrade de Aguiar | F17: SEP - Secretaria de Estratégia e Projetos | G17: Gladis Maddalozzo | H17: PNUD | I17: 03. Fomentar a gestão da qualidade dos dados no Poder Judiciário; e 16. perfeiçoar políticas e práticas de Gestão de Pessoas | J17: 10. Aperfeiçoamento da Gestão de Pessoas; e 09. Aperfeiçoamento da gestão administrativa e da governança judiciária | K17: Estratégia Nacional de Tecnologia da Informação e Comunicação do Poder Judiciário (ENTIC-JUD), Resolução CNJ n. 370/2021; Programa Justiça 4.0 - Eixo Fortalecimento de Capacidades Institucionais do CNJ (transferência de conhecimento e soluções com foco na segurança jurídica, sustentabilidade de projetos e eficiência da prestação jurisdicional); O projeto também relaciona-se à Política Nacional de Formação e Aperfeiçoamento dos Servidores do Poder Judiciário, Resolução Nº 192/2014 | L17: 45700 | M17: 46246 | N17: =_xlfn.XLOOKUP(Tb_Portfólio[[#This Row],[SEI]],Tb_Atualizações[PROCESSO SEI],Tb_Atualizações[% PREVISTO],"",0,-1) -> 0.84 | O17: =_xlfn.XLOOKUP(Tb_Portfólio[[#This Row],[SEI]],Tb_Atualizações[PROCESSO SEI],Tb_Atualizações[% EXECUTADO],"",0,-1) -> 0.88 | P17: =IFERROR(Tb_Portfólio[[#This Row],[% EXECUTADO]]/Tb_Portfólio[[#This Row],[% PREVISTO]],"0%") -> 1.047619 | Q17: =_xlfn.XLOOKUP(Tb_Portfólio[[#This Row],[SEI]],Tb_Atualizações[PROCESSO SEI],Tb_Atualizações[DATA DE ATUALIZAÇÃO],"",0,-1) -> 46167 | R17: =_xlfn.XLOOKUP(Tb_Portfólio[[#This Row],[SEI]],Tb_Atualizações[PROCESSO SEI],Tb_Atualizações[Mês],,0,-1) -> 46143 | T17: Justiça 4.0 | U17: =IF(Tb_Portfólio[[#This Row],[% EXECUTADO]]=100%,"Finalizado",IF(Tb_Portfólio[[#This Row],[PREVISÃO DE TERMINO]]<Tb_Portfólio[[#This Row],[Hoje]],"Atrasado ou Crítico",IF(Tb_Portfólio[[#This Row],[% EXECUTADO]]=0,"Autorizado",IF(Tb_Portfólio[[#This Row],[MEDIÇÃO DE STATUS]]>=95%,"No prazo",IF(Tb_Portfólio[[#This Row],[MEDIÇÃO DE STATUS]]<85%,"Atrasado ou Crítico",IF(Tb_Portfólio[[#This Row],[MEDIÇÃO DE STATUS]]<=95%,"Em atenção")))))) -> No prazo | W17: =IFERROR(Tb_Portfólio[[#This Row],[% EXECUTADO]]/Tb_Portfólio[[#This Row],[% PREVISTO]],0) -> 1.047619 | X17: Curso R Avançado para Ciência de Dados ; Curso Python Avançado para Ciência de Dados ; Curso Power BI Avançado para Análise de Dados ; Curso R Avançado para Ciência de Dados ; Curso Python Avançado para Ciência de Dados (autoinstrucional); Curso Power BI Avançado para Análise de Dados (autoinstrucional); Curso Relatórios e Automações Profissionais com R; Curso Processamento de Big Data em R e Python; Curso Mineração de Texto Avançada ; Curso Relatórios e Automações Profissionais com R (autoinstrucional); Curso Processamento de Big Data em R e Python (autoinstrucional); Curso Mineração de Texto Avançada (autoinstrucional); Curso Machine Learning Avançado; Curso Aplicações e Dashboard Avançado com R ; Curso Machine Learning Avançado (autoinstrucional); Curso Aplicações e Dashboard Avançado com R (autoinstrucional); | Y17: 448695 | AA17: https://www.cnj.jus.br/tecnologia-da-informacao-e-comunicacao/justica-4-0/ | AB17: Dra. Ana Lúcia Andrade de Aguiar | AC17: SEP - Secretaria de Estratégia e Projetos | AD17: BENEFÍCIO 1 - Sensibilização de magistrados/as e servidores/as do Poder Judiciário sobre a importância de capacitações na área de Ciência de Dados em nível avançado, a fim de fomentar a cultura de dados no judiciário. BENEFÍCIO 2 - Desenvolvimento de capacidades avançadas, na área de Ciência de Dados, de magistrados/as e servidores/as do Poder Judiciário. | AF17: =TODAY() -> 46176 | AG17: Gabriela Moreira de Azevedo Soares | AH17: Departamento de Pesquisas Judiciárias (DPJ) | AJ17: =2024&Tb_Portfólio[[#This Row],[SEI]] -> 202402024/2024 | AK17: =IFERROR(IF(MATCH(AJ17,Atualizações!$P$1:$P$1265,0)>0, "Sim"), "Não") -> Não | AL17: =2025&Tb_Portfólio[[#This Row],[SEI]] -> 202502024/2024 | AM17: =IFERROR(IF(MATCH(AL17,Atualizações!$P$1:$P$2994,0)>0, "Sim"), "Não") -> Sim | AN17: =2026&Tb_Portfólio[[#This Row],[SEI]] -> 202602024/2024 | AO17: =IFERROR(IF(MATCH(AN17,Atualizações!$P$1:$P$2994,0)>0, "Sim"), "Não") -> Sim | AP17: =_xlfn.XLOOKUP(Tb_Portfólio[[#This Row],[SEI]],Tb_Atualizações[PROCESSO SEI],Tb_Atualizações[Explicações],"",0,-1) -> 0 | AQ17: =_xlfn.XLOOKUP(Tb_Portfólio[[#This Row],[SEI]],Tb_Mapa[SEI],Tb_Mapa[CONSULTOR RESPONSÁVEL],"",0,-1) -> Raphael
A18: 02080/2023 | B18: Gabinete do Juízo | C18: Criação de uma solução modular que permita a realização dos atos de gabinete dos juízes, com arquiteturabaseada em microsserviços, aderente à Plataforma Digital do Poder Judiciário Nacional, instituída pelaResolução CNJ Nº 335/2020 (https://atos.cnj.jus.br/atos/detalhar/3496), e que atenda aos requisitos técnicose de arquitetura fixados pelo CNJ por meio da Portaria CNJ Nº 253-2020(https://atos.cnj.jus.br/atos/detalhar/3582), publicada em 18 de novembro de 2020, que instituiu os critériose diretrizes técnicas para o processo de desenvolvimento de módulos e serviços na Plataforma Digital doPoder Judiciário Brasileiro – PDPJ-Br. | E18: Dr. Dorotheo Barbosa Neto | F18: SEP - Secretaria de Estratégia e Projetos | G18: Diogo dos Santos Moreira | H18: PNUD | I18: 13. Estimular a desburocratização no Poder Judiciário | J18: 09. Aperfeiçoamento da gestão administrativa e da governança judiciária | K18: Resolução 335 /2020 Justiça 4.0 | L18: 45078 | M18: 46379 | N18: =_xlfn.XLOOKUP(Tb_Portfólio[[#This Row],[SEI]],Tb_Atualizações[PROCESSO SEI],Tb_Atualizações[% PREVISTO],"",0,-1) -> 0.85 | O18: =_xlfn.XLOOKUP(Tb_Portfólio[[#This Row],[SEI]],Tb_Atualizações[PROCESSO SEI],Tb_Atualizações[% EXECUTADO],"",0,-1) -> 0.66 | P18: =IFERROR(Tb_Portfólio[[#This Row],[% EXECUTADO]]/Tb_Portfólio[[#This Row],[% PREVISTO]],"0%") -> 0.77647059 | Q18: =_xlfn.XLOOKUP(Tb_Portfólio[[#This Row],[SEI]],Tb_Atualizações[PROCESSO SEI],Tb_Atualizações[DATA DE ATUALIZAÇÃO],"",0,-1) -> 46167 | R18: =_xlfn.XLOOKUP(Tb_Portfólio[[#This Row],[SEI]],Tb_Atualizações[PROCESSO SEI],Tb_Atualizações[Mês],,0,-1) -> 46143 | T18: Justiça 4.0 | U18: =IF(Tb_Portfólio[[#This Row],[% EXECUTADO]]=100%,"Finalizado",IF(Tb_Portfólio[[#This Row],[PREVISÃO DE TERMINO]]<Tb_Portfólio[[#This Row],[Hoje]],"Atrasado ou Crítico",IF(Tb_Portfólio[[#This Row],[% EXECUTADO]]=0,"Autorizado",IF(Tb_Portfólio[[#This Row],[MEDIÇÃO DE STATUS]]>=95%,"No prazo",IF(Tb_Portfólio[[#This Row],[MEDIÇÃO DE STATUS]]<85%,"Atrasado ou Crítico",IF(Tb_Portfólio[[#This Row],[MEDIÇÃO DE STATUS]]<=95%,"Em atenção")))))) -> Atrasado ou Crítico | W18: =IFERROR(Tb_Portfólio[[#This Row],[% EXECUTADO]]/Tb_Portfólio[[#This Row],[% PREVISTO]],0) -> 0.77647059 | X18: • Finalização do novo editor de texto • Variáveis e tópico síntese | AA18: https://www.cnj.jus.br/tecnologia-da-informacao-e-comunicacao/justica-4-0/ | AB18: Dr. Adriano da Silva Araújo | AC18: DTI - Departamento de Tecnologia da Informação e Comunicação | AD18: Viabilizar a possibilidade dos tribunais imprimirem maior celeridade e controle aos processos conduzidos pelos gabinetes das varas de justiça dos tribunais do judiciário brasileiro. | AE18: • Módulo em ambiente de produção - março de 2024 • Lançamento Nacional do Gabinete em 25/03/2025 • Módulo em ambiente de produção no TJAP – setembro de 2025 • Realease 4 – fevereiro de 2026 • Realese 5 • Realese 6 • Entrega do novo editor de texto Badon | AF18: =TODAY() -> 46176 | AG18: Antônio Augusto Silva Martins | AH18: DTI - Departamento de Tecnologia da Informação e Comunicação | AJ18: =2024&Tb_Portfólio[[#This Row],[SEI]] -> 202402080/2023 | AK18: =IFERROR(IF(MATCH(AJ18,Atualizações!$P$1:$P$1265,0)>0, "Sim"), "Não") -> Sim | AL18: =2025&Tb_Portfólio[[#This Row],[SEI]] -> 202502080/2023 | AM18: =IFERROR(IF(MATCH(AL18,Atualizações!$P$1:$P$2994,0)>0, "Sim"), "Não") -> Sim | AN18: =2026&Tb_Portfólio[[#This Row],[SEI]] -> 202602080/2023 | AO18: =IFERROR(IF(MATCH(AN18,Atualizações!$P$1:$P$2994,0)>0, "Sim"), "Não") -> Sim | AP18: =_xlfn.XLOOKUP(Tb_Portfólio[[#This Row],[SEI]],Tb_Atualizações[PROCESSO SEI],Tb_Atualizações[Explicações],"",0,-1) -> Apesar de o projeto encontra-se em atraso, o gerente relata que o projeto encontra-se sendo executado conforme o esperado, sendo o atraso registrado decorrente de um problema na ferramenta de acompanhamento do projeto. A equipe do PNUD já está ciente da situação e encontra-se trabalhando para regularizar a ferramenta de acompanhamento. | AQ18: =_xlfn.XLOOKUP(Tb_Portfólio[[#This Row],[SEI]],Tb_Mapa[SEI],Tb_Mapa[CONSULTOR RESPONSÁVEL],"",0,-1) -> Tony
A19: 02245/2025 | B19: SEEU - Reescrita | C19: Otimização do Sistema Eletrônico de Execução Unificado (SEEU), com foco em elevar a disponibilidade da solução, otimizar o consumo dos recursos de nuvem na plataforma AWS e viabilizar a absorção progressiva dos tribunais de São Paulo. | E19: Thiago de Andrade Vieira | F19: DTI - Departamento de Tecnologia da Informação e Comunicação | G19: Tiago Ribeiro Gonçalves | H19: PNUD | I19: 07. Fomentar e fortalecer a atuação interinstitucional do CNJ para garantir os direitos dos cidadãos | J19: 08. Aperfeiçoamento da gestão da justiça criminal; e 12. Fortalecimento da estratégia nacional de TIC e de proteção de dados | L19: 45707 | M19: 46387 | N19: =_xlfn.XLOOKUP(Tb_Portfólio[[#This Row],[SEI]],Tb_Atualizações[PROCESSO SEI],Tb_Atualizações[% PREVISTO],"",0,-1) -> 1 | O19: =_xlfn.XLOOKUP(Tb_Portfólio[[#This Row],[SEI]],Tb_Atualizações[PROCESSO SEI],Tb_Atualizações[% EXECUTADO],"",0,-1) -> 0.85 | P19: =IFERROR(Tb_Portfólio[[#This Row],[% EXECUTADO]]/Tb_Portfólio[[#This Row],[% PREVISTO]],"0%") -> 0.85 | Q19: =_xlfn.XLOOKUP(Tb_Portfólio[[#This Row],[SEI]],Tb_Atualizações[PROCESSO SEI],Tb_Atualizações[DATA DE ATUALIZAÇÃO],"",0,-1) -> 46137 | R19: =_xlfn.XLOOKUP(Tb_Portfólio[[#This Row],[SEI]],Tb_Atualizações[PROCESSO SEI],Tb_Atualizações[Mês],,0,-1) -> 46143 | T19: Justiça 4.0 | U19: =IF(Tb_Portfólio[[#This Row],[% EXECUTADO]]=100%,"Finalizado",IF(Tb_Portfólio[[#This Row],[PREVISÃO DE TERMINO]]<Tb_Portfólio[[#This Row],[Hoje]],"Atrasado ou Crítico",IF(Tb_Portfólio[[#This Row],[% EXECUTADO]]=0,"Autorizado",IF(Tb_Portfólio[[#This Row],[MEDIÇÃO DE STATUS]]>=95%,"No prazo",IF(Tb_Portfólio[[#This Row],[MEDIÇÃO DE STATUS]]<85%,"Atrasado ou Crítico",IF(Tb_Portfólio[[#This Row],[MEDIÇÃO DE STATUS]]<=95%,"Em atenção")))))) -> Em atenção | W19: =IFERROR(Tb_Portfólio[[#This Row],[% EXECUTADO]]/Tb_Portfólio[[#This Row],[% PREVISTO]],0) -> 0.85 | X19: 1. Relatório de Diagnóstico e Proposta de Trabalho; 2. Implementação da proposta de trabalho | Y19: 2959138.1 | AA19: https://www.cnj.jus.br/tecnologia-da-informacao-e-comunicacao/justica-4-0/ | AB19: Dr. Ricardo Alexandre Da Silva Costa | AC19: DMF - Departamento de Monitoramento e Fiscalização do Sistema Carcerário e do Sistema de Execução de Medidas Socioeducativas | AD19: Benefício 1: Aumento da robustez e capacidade de absorção de demandas futuras, assim como o aumento de usuários/acessos e processos que tramitam no sistema diariamente. Benefício 2: Otimização (Redução) dos custos relacionados aos serviços AWS (Estruturante) | AE19: Fase: Planejamento • P1 – Elaboração Canvas • P2 – Elaboração Termo de Abertura do Projeto (TAP) • P3 - Elaboração Plano de Gestão do Projeto (PGP) / 1.1 Elaboração Fase: Execução / P1 - Relatório de Diagnóstico e Proposta de Trabalho Fase: Execução / P2 - Implementação da Proposta de Trabalho: • Sprint 0 - Onboarding FAJU X Justiça 4.0 • Sprint 1 - SDK AWS • Sprint 2 - Entregar a Prova de Conceito do Upload S3-SDK • Sprint 3 - Análise dos Padrões, Transfer e Accelerator - SDK • Sprint 4 - MicroService - Adicionar S3 ao Novo Projeto • Sprint 5 - SEEU Utilizar as APIs de Arquivo do microsserviço • Sprint 6 - Remover Dependências de S3 do SEEU e liberar Versão do microsserviço de Arquivo • Sprint 7 - Consumir microsserviço de Arquivo Carimbado • Sprint 8 - Juntar Documentos - Consumir MS de Assinatura Simples e Completa • Sprint 9 - Preparação e entrega do microserviço de arquivos (download, upload, carimbo, assinatura) • Sprint 10 - Consumir URL de Assinatura nas Funcionalidades do SEEU Medição dos benefícios do Projeto • Marco 1 - Medição dos benefícios (Técnico e financeiro) - Antes e Depois sempre mesmo dia da semana e horário | AF19: =TODAY() -> 46176 | AJ19: =2024&Tb_Portfólio[[#This Row],[SEI]] -> 202402245/2025 | AK19: =IFERROR(IF(MATCH(AJ19,Atualizações!$P$1:$P$1265,0)>0, "Sim"), "Não") -> Não | AL19: =2025&Tb_Portfólio[[#This Row],[SEI]] -> 202502245/2025 | AM19: =IFERROR(IF(MATCH(AL19,Atualizações!$P$1:$P$2994,0)>0, "Sim"), "Não") -> Não | AN19: =2026&Tb_Portfólio[[#This Row],[SEI]] -> 202602245/2025 | AO19: =IFERROR(IF(MATCH(AN19,Atualizações!$P$1:$P$2994,0)>0, "Sim"), "Não") -> Sim | AP19: =_xlfn.XLOOKUP(Tb_Portfólio[[#This Row],[SEI]],Tb_Atualizações[PROCESSO SEI],Tb_Atualizações[Explicações],"",0,-1) -> Outros fatos relevantes a registrar  Sprint 17 - Monitorar Performance de Release 19.8.0 em Produção.  Incidente Redis: • Causado por sobrescrita/consumo incorreto de chaves no Redis e precisa de uma busca ativa para identificar a origem. • Aplicada correção no gateway que restaurou o funcionamento, mas uma investigação mais profunda foi solicitada aos arquitetos/DevOps. • Equipe do projeto identificou problemas de infraestrutura do CNJ que estão impactando o BNP. Tema escalonado ao PMO e coordenação PNUD para definição de responsabilidades.  Ataques, credenciais e impacto operacional: revogação massiva de credenciais após tentativas de ataque, com desabilitação preventiva e reabilitações pontuais conforme necessidade.  Sprint 17 — entregas e arquitetura de exportação • Entregue prova de conceito da exportação de processo; • Definida arquitetura desacoplada entre exportação e arquivo para reduzir carga no SEEU; • Proposta de melhorias de observabilidade aprovada e implementação do primeiro item começa • Sprint 6 - Remover Dependências de S3 do SEEU e liberar Versão do microsserviço de Arquivo • Sprint 7 - Consumir microsserviço de Arquivo Carimbado • Sprint 8 - Juntar Documentos - Consumir MS de Assinatura Simples e Completa • Sprint 9 - Preparação e entrega do microserviço de arquivos (download, upload, carimbo, assinatura) • Sprint 10 - Consumir URL de Assinatura nas Funcionalidades do SEEU • Sprint 11 - Entregar para esteira de Produção a Versão Validada para URL Pré Assinada • Sprint 12 – Otimização de Queries com a Master Release 19.1.10. • Sprint 13 - SEEU integrado a Arquivos utilizando bucket temporário e variáveis de ambiente aplicadas • Sprint 14 - Finalizar Épico de Otimização de Queries • Sprint 15 - Implementar Relatório de Expurgo de Dados • Sprint 16 - Teste do particionamento e coleta de indicadores  Medição dos benefícios do Projeto • Marco 1 - Medição dos benefícios (Técnico e financeiro) - Antes e Depois sempre mesmo dia da semana e horário • Marco 2 - Medição dos benefícios (Técnico e financeiro) - Antes e Depois sempre mesmo dia da semana e horário Relatório de Status Mensal de Projetos de TIC na Sprint 18.  Performance: Revisitados os relatórios que mostram ganhos de performance relacionados à versão 19.8 e várias otimizações. Ganhos maiores dependem de entregas represadas e do expurgo de dados que exige ambiente elástico para testes.  Sanitização para o CloudFront: arquivos dinâmicos removidos, mas exige testes de navegação com apoio do SEEU/negócio e aplicação das configurações por infra.  AWS – OS2: • Terá como entrega apenas o assessment via Kiro. Externalização de sessão será tratada em outra OS; • Não há datas formais de início/fim da OS2, o trabalho ainda está na fase de acessos, embora seja esperado um prazo curto (cerca de duas semanas); • Kick-off ocorrido em 22/05/2026, sexta-feira, formalizando o início da execução da OS em 25/05/2026.  Solicitado ajustes e correções no cronograma do projeto (PWA) ao Gerente do Projeto, em abril de 2026, visando corrigir: atividades sem informação de datas de início e término planejadas, não conformidade entre as datas de início e término reais e as datas planejadas, e duração das atividades.  O “%Concluído: 85%” informado neste relatório, não reflete a evolução do projeto. Os ajustes de cronograma solicitados seguem em elaboração pelo gerente do projeto. | AQ19: =_xlfn.XLOOKUP(Tb_Portfólio[[#This Row],[SEI]],Tb_Mapa[SEI],Tb_Mapa[CONSULTOR RESPONSÁVEL],"",0,-1) -> Tony
A20: 02394/2024 | B20: Portal de Serviços | C20: O projeto Portal de Serviços tem como objetivo o desenvolvimento e publicação de serviços judiciários, que farão parte de um Portal de acesso unificado aos serviços da Justiça, buscando contribuir para criação de uma identidade visual única para os serviços do Judiciário Nacional. Para tanto, serão criadas funcionalidades para o público interno, que atua no dia a dia da justiça, e para o público externo, demandantes da justiça. | E20: Dr. Dorotheo Barbosa Neto | F20: SEP - Secretaria de Estratégia e Projetos | G20: Tania Essabbá | H20: PNUD | I20: 01. Desenvolver políticas judiciárias e outros instrumentos para o aperfeiçoamento das atividades dos órgãos do Poder Judiciário e dos seus serviços auxiliares e dos serviços notariais e de registro, e dos demais órgãos correicionais. 07. Fomentar e fortalecer a atuação interinstitucional do CNJ para garantir os direitos dos cidadãos; e 13. Estimular a desburocratização no Poder Judiciário | J20: 09. Aperfeiçoamento da gestão administrativa e da governança judiciária. 03. Agilidade e produtividade na prestação jurisdicional | K20: Programa Justiça 4.0 - Eixo fortalecimento de capacidades institucionais do CNJ. O projeto também apoia a Resolução CNJ N. 335/2020, que institui uma política pública de governança e gestão do processo judicial eletrônico, integrando os tribunais por meio da Plataforma Digital do Poder Judiciário Brasileiro (PDPJ-Br), mantendo o PJe como sistema prioritário do CNJ. | L20: 45200 | M20: 46387 | N20: =_xlfn.XLOOKUP(Tb_Portfólio[[#This Row],[SEI]],Tb_Atualizações[PROCESSO SEI],Tb_Atualizações[% PREVISTO],"",0,-1) -> 0.8 | O20: =_xlfn.XLOOKUP(Tb_Portfólio[[#This Row],[SEI]],Tb_Atualizações[PROCESSO SEI],Tb_Atualizações[% EXECUTADO],"",0,-1) -> 0.55 | P20: =IFERROR(Tb_Portfólio[[#This Row],[% EXECUTADO]]/Tb_Portfólio[[#This Row],[% PREVISTO]],"0%") -> 0.6875 | Q20: =_xlfn.XLOOKUP(Tb_Portfólio[[#This Row],[SEI]],Tb_Atualizações[PROCESSO SEI],Tb_Atualizações[DATA DE ATUALIZAÇÃO],"",0,-1) -> 46167 | R20: =_xlfn.XLOOKUP(Tb_Portfólio[[#This Row],[SEI]],Tb_Atualizações[PROCESSO SEI],Tb_Atualizações[Mês],,0,-1) -> 46143 | T20: Justiça 4.0 | U20: =IF(Tb_Portfólio[[#This Row],[% EXECUTADO]]=100%,"Finalizado",IF(Tb_Portfólio[[#This Row],[PREVISÃO DE TERMINO]]<Tb_Portfólio[[#This Row],[Hoje]],"Atrasado ou Crítico",IF(Tb_Portfólio[[#This Row],[% EXECUTADO]]=0,"Autorizado",IF(Tb_Portfólio[[#This Row],[MEDIÇÃO DE STATUS]]>=95%,"No prazo",IF(Tb_Portfólio[[#This Row],[MEDIÇÃO DE STATUS]]<85%,"Atrasado ou Crítico",IF(Tb_Portfólio[[#This Row],[MEDIÇÃO DE STATUS]]<=95%,"Em atenção")))))) -> Atrasado ou Crítico | W20: =IFERROR(Tb_Portfólio[[#This Row],[% EXECUTADO]]/Tb_Portfólio[[#This Row],[% PREVISTO]],0) -> 0.6875 | X20: (Atividades recorrentes / evolutivas)  Funcionalidades para a Justiça • Ajustes em Carta Precatória/Resposta • Ajustes Ofícios • Ajustes Declínio de Competência Serviços Estruturantes  Funcionalidades para o público em geral • Ajustes das funcionalidades do Portal Interno • Integração com sistema de Execução Fiscal (EFIN)  Backlog 2026 | Y20: 6575248.6 | AA20: https://www.cnj.jus.br/tecnologia-da-informacao-e-comunicacao/justica-4-0/ | AB20: Dr. Dorotheo Barbosa Neto | AC20: SEP - Secretaria de Estratégia e Projetos | AD20: BENEFÍCIO 1 - Padronização do envio de remessas digitais: Proporcionar aos tribunais a capacidade de envio e recebimento de Cartas Precatórias, Declínios de Competência e envios de Ofícios. BENEFÍCIO 2 - Unificação do local de acesso:Reduzir a necessidade de acessar múltiplos sistemas, otimizando o tempo e esforço dedicados à obtenção de informações e andamento processual, promovendo maior transparência no sistema judiciário, permitindo que as partes envolvidas e o público em geral tenham acesso fácil e direto às informações processuais. | AE20: Funcionalidades para a Justiça: '-Carta Precatória; -Resposta à Carta precatória. Funcionalidades para o público em geral: -Consultar Processos; -Peticionar Intercorrente; -Minhas Petições; -Autos Digitais; -Integração ao Domicílio Eletrônico; -Integração ao Diário da Justiça; -Integração Peticionamento Intercorrente. Tratamentos de cenários críticos: • Limitar Declínio e Petição Inicial para classes escolhidas | AF20: =TODAY() -> 46176 | AG20: Thiago de Andrade Vieira | AH20: DTI - Departamento de Tecnologia da Informação e Comunicação | AJ20: =2024&Tb_Portfólio[[#This Row],[SEI]] -> 202402394/2024 | AK20: =IFERROR(IF(MATCH(AJ20,Atualizações!$P$1:$P$1265,0)>0, "Sim"), "Não") -> Sim | AL20: =2025&Tb_Portfólio[[#This Row],[SEI]] -> 202502394/2024 | AM20: =IFERROR(IF(MATCH(AL20,Atualizações!$P$1:$P$2994,0)>0, "Sim"), "Não") -> Sim | AN20: =2026&Tb_Portfólio[[#This Row],[SEI]] -> 202602394/2024 | AO20: =IFERROR(IF(MATCH(AN20,Atualizações!$P$1:$P$2994,0)>0, "Sim"), "Não") -> Sim | AP20: =_xlfn.XLOOKUP(Tb_Portfólio[[#This Row],[SEI]],Tb_Atualizações[PROCESSO SEI],Tb_Atualizações[Explicações],"",0,-1) -> 0 | AQ20: =_xlfn.XLOOKUP(Tb_Portfólio[[#This Row],[SEI]],Tb_Mapa[SEI],Tb_Mapa[CONSULTOR RESPONSÁVEL],"",0,-1) -> Tony
A21: 02465/2024 | B21: SisPreq – Sistema de Precatórios e Requisições de Pequeno Valor | C21: Solução nacional para a expedição de ofícios requisitórios, gestão de fila e pagamento de Requisições de Pequeno Valor (RPVs) e Precatórios | E21: Dr. Dorotheo Barbosa Neto | F21: SEP - Secretaria de Estratégia e Projetos | G21: Artur Nascimento | H21: PNUD | I21: 07. Fomentar e fortalecer a atuação interinstitucional do CNJ para garantir os direitos dos cidadãos | J21: 03. Agilidade e produtividade na prestação jurisdicional | K21: Política Judiciária de Gestão de Precatórios | L21: 45293 | M21: 15/12/2026 | N21: =_xlfn.XLOOKUP(Tb_Portfólio[[#This Row],[SEI]],Tb_Atualizações[PROCESSO SEI],Tb_Atualizações[% PREVISTO],"",0,-1) -> 0.77 | O21: =_xlfn.XLOOKUP(Tb_Portfólio[[#This Row],[SEI]],Tb_Atualizações[PROCESSO SEI],Tb_Atualizações[% EXECUTADO],"",0,-1) -> 0.5 | P21: =IFERROR(Tb_Portfólio[[#This Row],[% EXECUTADO]]/Tb_Portfólio[[#This Row],[% PREVISTO]],"0%") -> 0.64935065 | Q21: =_xlfn.XLOOKUP(Tb_Portfólio[[#This Row],[SEI]],Tb_Atualizações[PROCESSO SEI],Tb_Atualizações[DATA DE ATUALIZAÇÃO],"",0,-1) -> 46167 | R21: =_xlfn.XLOOKUP(Tb_Portfólio[[#This Row],[SEI]],Tb_Atualizações[PROCESSO SEI],Tb_Atualizações[Mês],,0,-1) -> 46143 | T21: Justiça 4.0 | U21: =IF(Tb_Portfólio[[#This Row],[% EXECUTADO]]=100%,"Finalizado",IF(Tb_Portfólio[[#This Row],[PREVISÃO DE TERMINO]]<Tb_Portfólio[[#This Row],[Hoje]],"Atrasado ou Crítico",IF(Tb_Portfólio[[#This Row],[% EXECUTADO]]=0,"Autorizado",IF(Tb_Portfólio[[#This Row],[MEDIÇÃO DE STATUS]]>=95%,"No prazo",IF(Tb_Portfólio[[#This Row],[MEDIÇÃO DE STATUS]]<85%,"Atrasado ou Crítico",IF(Tb_Portfólio[[#This Row],[MEDIÇÃO DE STATUS]]<=95%,"Em atenção")))))) -> Atrasado ou Crítico | W21: =IFERROR(Tb_Portfólio[[#This Row],[% EXECUTADO]]/Tb_Portfólio[[#This Row],[% PREVISTO]],0) -> 0.64935065 | X21: - Formulário de pré-cadastro de Precatórios - Tela de visuaização de cadastro - Funcionalidade de edição de cadastros - Geração e expedição de minuta - Implementações técnicas | Y21: 3897842.7 | AA21: https://www.cnj.jus.br/tecnologia-da-informacao-e-comunicacao/justica-4-0/ | AB21: Dr. Dorotheo Barbosa Neto | AC21: SEP - Secretaria de Estratégia e Projetos | AD21: - Controle e padronização dos processos de Precatórios e RPVs pelos Tribunais - Geração de informações relevantes para subsidiar tomada de decisão, otimizando recursos públicos - Aumento de velocidade e eficiência no pagamento de precatórios e RPVs | AE21: • Entrada de recurso (Rafael Medrado) no projeto (ainda em phase-out anterior). • Reunião de ponto de controle com a Dra. Paula (apresentação do time, modularização e formação de equipe) • Reunião com a DB (Carlos) sobre modularização / repasse. • Indicação de arquiteto responsável (Rafael Chagas) | AF21: =TODAY() -> 46176 | AG21: Thiago de Andrade Vieira | AH21: DTI - Departamento de Tecnologia da Informação e Comunicação | AJ21: =2024&Tb_Portfólio[[#This Row],[SEI]] -> 202402465/2024 | AK21: =IFERROR(IF(MATCH(AJ21,Atualizações!$P$1:$P$1265,0)>0, "Sim"), "Não") -> Sim | AL21: =2025&Tb_Portfólio[[#This Row],[SEI]] -> 202502465/2024 | AM21: =IFERROR(IF(MATCH(AL21,Atualizações!$P$1:$P$2994,0)>0, "Sim"), "Não") -> Sim | AN21: =2026&Tb_Portfólio[[#This Row],[SEI]] -> 202602465/2024 | AO21: =IFERROR(IF(MATCH(AN21,Atualizações!$P$1:$P$2994,0)>0, "Sim"), "Não") -> Sim | AP21: =_xlfn.XLOOKUP(Tb_Portfólio[[#This Row],[SEI]],Tb_Atualizações[PROCESSO SEI],Tb_Atualizações[Explicações],"",0,-1) -> Entregas Realizadas: * Realizado no período: Subida para produção da funcionalidade de Retificação de Ofício; reuniões de demonstração técnica realizadas para os tribunais TJAC, TJPB, TJMG, TJAL, TJPA, TJTO, TJRR, TJPE e TJMA. * Em andamento: Desenvolvimento e homologação do módulo Calculadora com regras retroativas a 2015 (IPCA-E e juros da poupança). Entregas planejadas para o próximo mês : * Planejado: Formalização e publicação da portaria de criação do Grupo de Trabalho de Dados de Precatórios envolvendo a Justiça do Trabalho, CJF e TJSP. Outros fatos relevantes a registrar: * A integração física com o ambiente do Data Lake está travada/pendente há três semanas por falta de disponibilização de ambiente. * Página oficial sobre Precatórios desatualizada no portal do CNJ. * Solicitação: Alocação emergencial de mais um Analista de Requisitos para suprir a alta demanda de novos tribunais aderindo ao sistema. | AQ21: =_xlfn.XLOOKUP(Tb_Portfólio[[#This Row],[SEI]],Tb_Mapa[SEI],Tb_Mapa[CONSULTOR RESPONSÁVEL],"",0,-1) -> Raphael
A22: 02476/2024 | B22: Itinerância Cooperativa na Amazônia Legal – 1ª Edição de 2024 – Humaitá e Lábrea/AM | C22: Estruturar e implementar acesso à Justiça por meio da realização de Itinerância cooperativa na Amazônia Legal. | E22: Dra. Lívia Cristina Marques Peres | F22: SEP - Secretaria de Estratégia e Projetos | G22: Angela Maria dos Santos | H22: SEP - Secretaria de Estratégia e Projetos | I22: 07. Fomentar e fortalecer a atuação interinstitucional do CNJ para garantir os direitos dos cidadãos | J22: 02. Fortalecimento da Relação Institucional do Judiciário com a Sociedade | K22: Resolução CNJ n. 460, de 6 de maio de 2022 | L22: 45344 | M22: 45590 | N22: =_xlfn.XLOOKUP(Tb_Portfólio[[#This Row],[SEI]],Tb_Atualizações[PROCESSO SEI],Tb_Atualizações[% PREVISTO],"",0,-1) -> 1 | O22: =_xlfn.XLOOKUP(Tb_Portfólio[[#This Row],[SEI]],Tb_Atualizações[PROCESSO SEI],Tb_Atualizações[% EXECUTADO],"",0,-1) -> 1 | P22: =IFERROR(Tb_Portfólio[[#This Row],[% EXECUTADO]]/Tb_Portfólio[[#This Row],[% PREVISTO]],"0%") -> 1 | Q22: =_xlfn.XLOOKUP(Tb_Portfólio[[#This Row],[SEI]],Tb_Atualizações[PROCESSO SEI],Tb_Atualizações[DATA DE ATUALIZAÇÃO],"",0,-1) -> 45714 | R22: =_xlfn.XLOOKUP(Tb_Portfólio[[#This Row],[SEI]],Tb_Atualizações[PROCESSO SEI],Tb_Atualizações[Mês],,0,-1) -> 45689 | U22: =IF(Tb_Portfólio[[#This Row],[% EXECUTADO]]=100%,"Finalizado",IF(Tb_Portfólio[[#This Row],[PREVISÃO DE TERMINO]]<Tb_Portfólio[[#This Row],[Hoje]],"Atrasado ou Crítico",IF(Tb_Portfólio[[#This Row],[% EXECUTADO]]=0,"Autorizado",IF(Tb_Portfólio[[#This Row],[MEDIÇÃO DE STATUS]]>=95%,"No prazo",IF(Tb_Portfólio[[#This Row],[MEDIÇÃO DE STATUS]]<85%,"Atrasado ou Crítico",IF(Tb_Portfólio[[#This Row],[MEDIÇÃO DE STATUS]]<=95%,"Em atenção")))))) -> Finalizado | W22: =IFERROR(Tb_Portfólio[[#This Row],[% EXECUTADO]]/Tb_Portfólio[[#This Row],[% PREVISTO]],0) -> 1 | X22: -Desenvolver planos de ação por eixos temáticos - realizar itinerância - compilar, avaliar e apresentar resultados | AB22: Dra. Lívia Cristina Marques Peres | AC22: SEP - Secretaria de Estratégia e Projetos | AD22: - Garantir acesso à Justiça e promover cidadania à população da região sede da itinerância - Documentar os dados da localidade atendida, empiricamente coletados, e as informações dos serviços prestados | AF22: =TODAY() -> 46176 | AJ22: =2024&Tb_Portfólio[[#This Row],[SEI]] -> 202402476/2024 | AK22: =IFERROR(IF(MATCH(AJ22,Atualizações!$P$1:$P$1265,0)>0, "Sim"), "Não") -> Sim | AL22: =2025&Tb_Portfólio[[#This Row],[SEI]] -> 202502476/2024 | AM22: =IFERROR(IF(MATCH(AL22,Atualizações!$P$1:$P$2994,0)>0, "Sim"), "Não") -> Sim | AN22: =2026&Tb_Portfólio[[#This Row],[SEI]] -> 202602476/2024 | AO22: =IFERROR(IF(MATCH(AN22,Atualizações!$P$1:$P$2994,0)>0, "Sim"), "Não") -> Não | AP22: =_xlfn.XLOOKUP(Tb_Portfólio[[#This Row],[SEI]],Tb_Atualizações[PROCESSO SEI],Tb_Atualizações[Explicações],"",0,-1) -> Projeto concluído com a entrega do TEP. Resultados da itinerância disponíveis no relatório 2101807, páginas 63 a 138 | AQ22: =_xlfn.XLOOKUP(Tb_Portfólio[[#This Row],[SEI]],Tb_Mapa[SEI],Tb_Mapa[CONSULTOR RESPONSÁVEL],"",0,-1) -> Igor/Finalizado
A23: 02483/2023 | B23: SNA – Novo Sistema Nacional de Adoção e Acolhimento | C23: Desenvolvimento de uma nova versão do Sistema Nacional de Adoção e Acolhimento (Novo SNA) com inclusão de soluções adequadas aos padrões da PDPJ. | E23: Dr. Gabriel Da Silveira Matos | F23: SEP - Secretaria de Estratégia e Projetos | G23: Ana Angélica Rodrigues Alves | H23: PNUD | I23: 09. Fomentar e incrementar a produção de soluções tecnológicas, com foco em inovação e transformação digital | J23: 01. Garantia dos direitos fundamentais | K23: Resolução 335 /2020 Justiça 4.0 | L23: 45293 | M23: 46022 | N23: =_xlfn.XLOOKUP(Tb_Portfólio[[#This Row],[SEI]],Tb_Atualizações[PROCESSO SEI],Tb_Atualizações[% PREVISTO],"",0,-1) -> 0.85 | O23: =_xlfn.XLOOKUP(Tb_Portfólio[[#This Row],[SEI]],Tb_Atualizações[PROCESSO SEI],Tb_Atualizações[% EXECUTADO],"",0,-1) -> 0.76 | P23: =IFERROR(Tb_Portfólio[[#This Row],[% EXECUTADO]]/Tb_Portfólio[[#This Row],[% PREVISTO]],"0%") -> 0.89411765 | Q23: =_xlfn.XLOOKUP(Tb_Portfólio[[#This Row],[SEI]],Tb_Atualizações[PROCESSO SEI],Tb_Atualizações[DATA DE ATUALIZAÇÃO],"",0,-1) -> 45985 | R23: =_xlfn.XLOOKUP(Tb_Portfólio[[#This Row],[SEI]],Tb_Atualizações[PROCESSO SEI],Tb_Atualizações[Mês],,0,-1) -> 45962 | T23: Justiça 4.0 | U23: Finalizado | W23: =IFERROR(Tb_Portfólio[[#This Row],[% EXECUTADO]]/Tb_Portfólio[[#This Row],[% PREVISTO]],0) -> 0.89411765 | X23: • Etapa 1: Mapeamento de processos e requisitos; • Etapa 2: Integração PDPJ; • Etapa 3: Módulo de Pretendentes (Parte 1); • Etapa 4: Treinamento, disseminação das informações; • Etapa 5: Monitoramento da qualidade/uso da solução. | Y23: 2733325.3 | AA23: https://www.cnj.jus.br/tecnologia-da-informacao-e-comunicacao/justica-4-0/ | AB23: Dra. Rebeca de Mendonça Lima | AC23: SEP - Secretaria de Estratégia e Projetos | AD23: Benefício 1: Mapeamento amplo do processo de adoção e acolhimento Benefício 2: Integração do SNA aos sistemas processuais do Poder Judiciário e Poder Executivo, por meio da PDPJ. Benefício 3: Melhoria e evolução das demandas identificadas no SNA anterior (legado). Benefício 4: Controle, monitoramento e disseminação das informações, com garantia de padrões éticos e auditáveis. Benefício 5: Avanço na eficácia do Sistema Nacional de Adoção e Acolhimento. | AF23: =TODAY() -> 46176 | AG23: Isabely Fontana da Mota | AH23: DPJ - Departamento de Pesquisas Judiciárias | AJ23: =2024&Tb_Portfólio[[#This Row],[SEI]] -> 202402483/2023 | AK23: =IFERROR(IF(MATCH(AJ23,Atualizações!$P$1:$P$1265,0)>0, "Sim"), "Não") -> Sim | AL23: =2025&Tb_Portfólio[[#This Row],[SEI]] -> 202502483/2023 | AM23: =IFERROR(IF(MATCH(AL23,Atualizações!$P$1:$P$2994,0)>0, "Sim"), "Não") -> Sim | AN23: =2026&Tb_Portfólio[[#This Row],[SEI]] -> 202602483/2023 | AO23: =IFERROR(IF(MATCH(AN23,Atualizações!$P$1:$P$2994,0)>0, "Sim"), "Não") -> Não | AP23: =_xlfn.XLOOKUP(Tb_Portfólio[[#This Row],[SEI]],Tb_Atualizações[PROCESSO SEI],Tb_Atualizações[Explicações],"",0,-1) -> 0 | AQ23: =_xlfn.XLOOKUP(Tb_Portfólio[[#This Row],[SEI]],Tb_Mapa[SEI],Tb_Mapa[CONSULTOR RESPONSÁVEL],"",0,-1) -> Igor
A24: 02626/2025 | B24: Fortalecimento da Segurança Cibernética e da Transparência para Governança e Efetividade da Atuação do Poder Judiciário (Projeto BRA/24/021) | C24: Criar ferramentas e estratégias para melhorar a segurança cibernética, a preservação de documentos e o gerenciamento de informações e conhecimentos dos sistemas do Conselho Nacional de Justiça. | E24: Dr. João Felipe Menezes Lopes | F24: DTI - Departamento de Tecnologia da Informação e Comunicação | G24: A definir | H24: PNUD | I24: 09. Fomentar e incrementar a produção de soluções tecnológicas, com foco em inovação e transformação digital; 13. Estimular a desburocratização no Poder Judiciário | J24: 09. Aperfeiçoamento da gestão administrativa e da governança judiciária; 12. Fortalecimento da estratégia nacional de TIC e de proteção de dados | K24: Estratégia Nacional de Segurança Cibernética do Poder Judiciário (ENSEC-PJ), instituída pela Resolução CNJ Nº 396/2021; Política da Estratégia Nacional de Tecnologia da Informação e Comunicação do Poder Judiciário (ENTIC-JUD), instituída pela Resolução CNJ Nº 370/2021. | L24: 45922 | M24: 47118 | N24: =_xlfn.XLOOKUP(Tb_Portfólio[[#This Row],[SEI]],Tb_Atualizações[PROCESSO SEI],Tb_Atualizações[% PREVISTO],"",0,-1) -> 0 | O24: =_xlfn.XLOOKUP(Tb_Portfólio[[#This Row],[SEI]],Tb_Atualizações[PROCESSO SEI],Tb_Atualizações[% EXECUTADO],"",0,-1) -> 0 | P24: =IFERROR(Tb_Portfólio[[#This Row],[% EXECUTADO]]/Tb_Portfólio[[#This Row],[% PREVISTO]],"0%") -> 0% | Q24: =_xlfn.XLOOKUP(Tb_Portfólio[[#This Row],[SEI]],Tb_Atualizações[PROCESSO SEI],Tb_Atualizações[DATA DE ATUALIZAÇÃO],"",0,-1) -> 46036 | R24: =_xlfn.XLOOKUP(Tb_Portfólio[[#This Row],[SEI]],Tb_Atualizações[PROCESSO SEI],Tb_Atualizações[Mês],,0,-1) -> 45901 | U24: =IF(Tb_Portfólio[[#This Row],[% EXECUTADO]]=100%,"Finalizado",IF(Tb_Portfólio[[#This Row],[PREVISÃO DE TERMINO]]<Tb_Portfólio[[#This Row],[Hoje]],"Atrasado ou Crítico",IF(Tb_Portfólio[[#This Row],[% EXECUTADO]]=0,"Autorizado",IF(Tb_Portfólio[[#This Row],[MEDIÇÃO DE STATUS]]>=95%,"No prazo",IF(Tb_Portfólio[[#This Row],[MEDIÇÃO DE STATUS]]<85%,"Atrasado ou Crítico",IF(Tb_Portfólio[[#This Row],[MEDIÇÃO DE STATUS]]<=95%,"Em atenção")))))) -> Autorizado | W24: =IFERROR(Tb_Portfólio[[#This Row],[% EXECUTADO]]/Tb_Portfólio[[#This Row],[% PREVISTO]],0) -> 0 | Y24: 2.5514997e+08 | AB24: Dr. Dorotheo Barbosa Neto | AC24: SEP - Secretaria de Estratégia e Projetos | AD24: Benefício 1: Fortalecimento da segurança cibernética nas ferramentas digitais do Judiciário. Benefício 2: Aprimoramento da usabilidade negocial e técnica dos serviços tecnológicos do CNJ, alinhado aos protocolos de segurança cibernética para usuários internos e externos Benefício 3:Preservação digital e de gestão documental para produção e análise de dados de formulação, apoio à implantação e monitoramento de políticas judiciárias Benefício 4: Gestão eficiente e gestão de conhecimento do projeto realizadas em atendimento ao usuário | AF24: =TODAY() -> 46176 | AJ24: =2024&Tb_Portfólio[[#This Row],[SEI]] -> 202402626/2025 | AK24: =IFERROR(IF(MATCH(AJ24,Atualizações!$P$1:$P$1265,0)>0, "Sim"), "Não") -> Não | AL24: =2025&Tb_Portfólio[[#This Row],[SEI]] -> 202502626/2025 | AM24: =IFERROR(IF(MATCH(AL24,Atualizações!$P$1:$P$2994,0)>0, "Sim"), "Não") -> Sim | AN24: =2026&Tb_Portfólio[[#This Row],[SEI]] -> 202602626/2025 | AO24: =IFERROR(IF(MATCH(AN24,Atualizações!$P$1:$P$2994,0)>0, "Sim"), "Não") -> Sim | AP24: =_xlfn.XLOOKUP(Tb_Portfólio[[#This Row],[SEI]],Tb_Atualizações[PROCESSO SEI],Tb_Atualizações[Explicações],"",0,-1) -> Medição duplicada para inserir os dados no portfólio de 2026 | AQ24: =_xlfn.XLOOKUP(Tb_Portfólio[[#This Row],[SEI]],Tb_Mapa[SEI],Tb_Mapa[CONSULTOR RESPONSÁVEL],"",0,-1) -> Tony / Cris
A25: 02633/2025 | B25: Itinerância Cooperativa na Amazônia Legal – Edição de 2025 – Boca do Acre (AM) e Xapuri (AC) | C25: Estruturar e implementar acesso a direitos por meio do Programa Itinerância Cooperativa na Amazônia Legal. | E25: Dra. Lívia Cristina Marques Peres | F25: SEP - Secretaria de Estratégia e Projetos | G25: Thais Martins Bosch | H25: SEP - Secretaria de Estratégia e Projetos | I25: 07. Fomentar e fortalecer a atuação interinstitucional do CNJ para garantir os direitos dos cidadãos | J25: 01. Garantia dos direitos fundamentais e 02. Fortalecimento da Relação Institucional do Judiciário com a Sociedade | K25: Política de Cooperação Judiciária, instutuída pela Resolução Nº 350 de 27/10/2020 | L25: 45714 | M25: 45912 | N25: =_xlfn.XLOOKUP(Tb_Portfólio[[#This Row],[SEI]],Tb_Atualizações[PROCESSO SEI],Tb_Atualizações[% PREVISTO],"",0,-1) -> 1 | O25: =_xlfn.XLOOKUP(Tb_Portfólio[[#This Row],[SEI]],Tb_Atualizações[PROCESSO SEI],Tb_Atualizações[% EXECUTADO],"",0,-1) -> 1 | P25: =IFERROR(Tb_Portfólio[[#This Row],[% EXECUTADO]]/Tb_Portfólio[[#This Row],[% PREVISTO]],"0%") -> 1 | Q25: =_xlfn.XLOOKUP(Tb_Portfólio[[#This Row],[SEI]],Tb_Atualizações[PROCESSO SEI],Tb_Atualizações[DATA DE ATUALIZAÇÃO],"",0,-1) -> 45925 | R25: =_xlfn.XLOOKUP(Tb_Portfólio[[#This Row],[SEI]],Tb_Atualizações[PROCESSO SEI],Tb_Atualizações[Mês],,0,-1) -> 45901 | U25: =IF(Tb_Portfólio[[#This Row],[% EXECUTADO]]=100%,"Finalizado",IF(Tb_Portfólio[[#This Row],[PREVISÃO DE TERMINO]]<Tb_Portfólio[[#This Row],[Hoje]],"Atrasado ou Crítico",IF(Tb_Portfólio[[#This Row],[% EXECUTADO]]=0,"Autorizado",IF(Tb_Portfólio[[#This Row],[MEDIÇÃO DE STATUS]]>=95%,"No prazo",IF(Tb_Portfólio[[#This Row],[MEDIÇÃO DE STATUS]]<85%,"Atrasado ou Crítico",IF(Tb_Portfólio[[#This Row],[MEDIÇÃO DE STATUS]]<=95%,"Em atenção")))))) -> Finalizado | W25: =IFERROR(Tb_Portfólio[[#This Row],[% EXECUTADO]]/Tb_Portfólio[[#This Row],[% PREVISTO]],0) -> 1 | X25: Itinerância na Boca do Acre (AM) e Xapuri (AC) | AB25: Dra. Lívia Cristina Marques Peres | AC25: SEP - Secretaria de Estratégia e Projetos | AD25: Benefício 1 - Garantir acesso à justiça e promover cidadania à população da região sede da itinerância; e Benefício 2 - Documentar os dados da localidade atendida, empiricamente coletados, e as informações dos serviços prestados | AF25: =TODAY() -> 46176 | AJ25: =2024&Tb_Portfólio[[#This Row],[SEI]] -> 202402633/2025 | AK25: =IFERROR(IF(MATCH(AJ25,Atualizações!$P$1:$P$1265,0)>0, "Sim"), "Não") -> Não | AL25: =2025&Tb_Portfólio[[#This Row],[SEI]] -> 202502633/2025 | AM25: =IFERROR(IF(MATCH(AL25,Atualizações!$P$1:$P$2994,0)>0, "Sim"), "Não") -> Sim | AN25: =2026&Tb_Portfólio[[#This Row],[SEI]] -> 202602633/2025 | AO25: =IFERROR(IF(MATCH(AN25,Atualizações!$P$1:$P$2994,0)>0, "Sim"), "Não") -> Não | AP25: =_xlfn.XLOOKUP(Tb_Portfólio[[#This Row],[SEI]],Tb_Atualizações[PROCESSO SEI],Tb_Atualizações[Explicações],"",0,-1) -> TEP recebido. | AQ25: =_xlfn.XLOOKUP(Tb_Portfólio[[#This Row],[SEI]],Tb_Mapa[SEI],Tb_Mapa[CONSULTOR RESPONSÁVEL],"",0,-1) -> Raphael/ CRIS
A26: 02660/2023 | B26: Propagar - Inclusão, Acessibilidade, Justiça e Cidadania | C26: Promover eventos virtuais visando a difusão de ações e projetos implementados nos tribunais que estejam relacionados à inclusão do cidadão, à acessibilidade e à cidadania. | E26: Conselheiro Mário Goulart Maia | F26: Gabinete do Conselheiro Mário Goulart Maia | G26: Eneida Pimentel Barreto | H26: Gab. Cons. Juiz Trabalho | I26: 14. Impulsionar a implantação e a gestão das Políticas de Sustentabilidade e Acessibilidade | J26: 01. Garantia dos direitos fundamentais | K26: Resolução 401/2021 - Diretrizes de acessibilidade e inclusão de pessoas com deficiência nos órgãos do Poder Judiciário e de seus serviços auxiliares, e regulamenta o funcionamento de unidades de acessibilidade e inclusão. | L26: 44959 | M26: 45485 | N26: =_xlfn.XLOOKUP(Tb_Portfólio[[#This Row],[SEI]],Tb_Atualizações[PROCESSO SEI],Tb_Atualizações[% PREVISTO],"",0,-1) -> 1 | O26: =_xlfn.XLOOKUP(Tb_Portfólio[[#This Row],[SEI]],Tb_Atualizações[PROCESSO SEI],Tb_Atualizações[% EXECUTADO],"",0,-1) -> 1 | P26: =IFERROR(Tb_Portfólio[[#This Row],[% EXECUTADO]]/Tb_Portfólio[[#This Row],[% PREVISTO]],"0%") -> 1 | Q26: =_xlfn.XLOOKUP(Tb_Portfólio[[#This Row],[SEI]],Tb_Atualizações[PROCESSO SEI],Tb_Atualizações[DATA DE ATUALIZAÇÃO],"",0,-1) -> 45645 | R26: =_xlfn.XLOOKUP(Tb_Portfólio[[#This Row],[SEI]],Tb_Atualizações[PROCESSO SEI],Tb_Atualizações[Mês],,0,-1) -> 45627 | U26: =IF(Tb_Portfólio[[#This Row],[% EXECUTADO]]=100%,"Finalizado",IF(Tb_Portfólio[[#This Row],[PREVISÃO DE TERMINO]]<Tb_Portfólio[[#This Row],[Hoje]],"Atrasado ou Crítico",IF(Tb_Portfólio[[#This Row],[% EXECUTADO]]=0,"Autorizado",IF(Tb_Portfólio[[#This Row],[MEDIÇÃO DE STATUS]]>=95%,"No prazo",IF(Tb_Portfólio[[#This Row],[MEDIÇÃO DE STATUS]]<85%,"Atrasado ou Crítico",IF(Tb_Portfólio[[#This Row],[MEDIÇÃO DE STATUS]]<=95%,"Em atenção")))))) -> Finalizado | W26: =IFERROR(Tb_Portfólio[[#This Row],[% EXECUTADO]]/Tb_Portfólio[[#This Row],[% PREVISTO]],0) -> 1 | AB26: Não há | AC26: Gabinete do Conselheiro Mário Goulart Maia | AD26: 1) Impulsionar a implementação e a gestão de políticas de Sustentabilidade e Acessibilidade. 2) Fomentar e fortalecer a atuação interinstitucional do CNJ para garantir os direitos do cidadão._x000D_ | AE26: • Ciclo 1 - Projeto Linguagem Simples - TJBA • Ciclo 2 - Balcão Visual. TRT15 • Ciclo 3 - Central Judicial do Idoso. TJDFT • Ciclo 4 - Construção de novos protocolos PoPruajud • Ciclo 5 - Aguardando tema • Compilação e análise de dados • Publicação revista | AF26: =TODAY() -> 46176 | AJ26: =2024&Tb_Portfólio[[#This Row],[SEI]] -> 202402660/2023 | AK26: =IFERROR(IF(MATCH(AJ26,Atualizações!$P$1:$P$1265,0)>0, "Sim"), "Não") -> Sim | AL26: =2025&Tb_Portfólio[[#This Row],[SEI]] -> 202502660/2023 | AM26: =IFERROR(IF(MATCH(AL26,Atualizações!$P$1:$P$2994,0)>0, "Sim"), "Não") -> Não | AN26: =2026&Tb_Portfólio[[#This Row],[SEI]] -> 202602660/2023 | AO26: =IFERROR(IF(MATCH(AN26,Atualizações!$P$1:$P$2994,0)>0, "Sim"), "Não") -> Não | AP26: =_xlfn.XLOOKUP(Tb_Portfólio[[#This Row],[SEI]],Tb_Atualizações[PROCESSO SEI],Tb_Atualizações[Explicações],"",0,-1) -> 0 | AQ26: =_xlfn.XLOOKUP(Tb_Portfólio[[#This Row],[SEI]],Tb_Mapa[SEI],Tb_Mapa[CONSULTOR RESPONSÁVEL],"",0,-1) -> Igor/Finalizado
A27: 02887/2024 | B27: Apoio a implantação de soluções da PDPJ-Br | C27: O objetivo principal é assegurar que todos os participantes do sistema tenham acesso a um suporte técnico eficiente, capaz de solucionar problemas mais complexos que exijam conhecimentos especializados, garantindo assim a continuidade e a eficiência dos serviços prestados pela PDPJ-Br. | E27: Dr. Alexandre Libonati de Abreu | F27: DTI - Departamento de Tecnologia da Informação e Comunicação | G27: Renato Silveira | H27: PNUD | I27: 01. Desenvolver políticas judiciárias e outros instrumentos para o aperfeiçoamento das atividades dos órgãos do Poder Judiciário e dos seus serviços auxiliares e dos serviços notariais e de registro, e dos demais órgãos correicionais; 09. Fomentar e incrementar a produção de soluções tecnológicas, com foco em inovação e transformação digital; 10. Aprimorar a governança e a gestão da tecnologia e comunicação sob a ótica de soluções colaborativas. | J27: 12. Fortalecimento da estratégia nacional de TIC e de proteção de dados | K27: Programa Justiça 4.0 (Projeto BRA/20/003) | L27: 45200 | M27: 46387 | N27: =_xlfn.XLOOKUP(Tb_Portfólio[[#This Row],[SEI]],Tb_Atualizações[PROCESSO SEI],Tb_Atualizações[% PREVISTO],"",0,-1) -> 0.8 | O27: =_xlfn.XLOOKUP(Tb_Portfólio[[#This Row],[SEI]],Tb_Atualizações[PROCESSO SEI],Tb_Atualizações[% EXECUTADO],"",0,-1) -> 0.8 | P27: =IFERROR(Tb_Portfólio[[#This Row],[% EXECUTADO]]/Tb_Portfólio[[#This Row],[% PREVISTO]],"0%") -> 1 | Q27: =_xlfn.XLOOKUP(Tb_Portfólio[[#This Row],[SEI]],Tb_Atualizações[PROCESSO SEI],Tb_Atualizações[DATA DE ATUALIZAÇÃO],"",0,-1) -> 46137 | R27: =_xlfn.XLOOKUP(Tb_Portfólio[[#This Row],[SEI]],Tb_Atualizações[PROCESSO SEI],Tb_Atualizações[Mês],,0,-1) -> 46143 | T27: Justiça 4.0 | U27: =IF(Tb_Portfólio[[#This Row],[% EXECUTADO]]=100%,"Finalizado",IF(Tb_Portfólio[[#This Row],[PREVISÃO DE TERMINO]]<Tb_Portfólio[[#This Row],[Hoje]],"Atrasado ou Crítico",IF(Tb_Portfólio[[#This Row],[% EXECUTADO]]=0,"Autorizado",IF(Tb_Portfólio[[#This Row],[MEDIÇÃO DE STATUS]]>=95%,"No prazo",IF(Tb_Portfólio[[#This Row],[MEDIÇÃO DE STATUS]]<85%,"Atrasado ou Crítico",IF(Tb_Portfólio[[#This Row],[MEDIÇÃO DE STATUS]]<=95%,"Em atenção")))))) -> No prazo | W27: =IFERROR(Tb_Portfólio[[#This Row],[% EXECUTADO]]/Tb_Portfólio[[#This Row],[% PREVISTO]],0) -> 1 | X27:  Etapa 2 – Planejamento da Operação, Mapeamento e Capacitação: • Realizar o mapeamento dos sistemas legados sem fila de atendimento no GLPI ou filas sem atendimento • Reestruturar as filas de atendimento no GLPI conforme necessidade  Etapa 3 -Triagem e atendimento técnico N2 • Realizar a triagem dos chamados/tarefas direcionados pelo N1 para atendimento • Realizar a atendimento dos chamados/tarefas Nivel 2  Etapa 4 – Escalação, Documentação e Comunicação  Etapa 5 – Apoio às soluções PDPJ e Monitoramento | Y27: 1182811.3 | AA27: https://www.cnj.jus.br/tecnologia-da-informacao-e-comunicacao/justica-4-0/ | AB27: Dr. Dorotheo Barbosa Neto | AC27: SEP - Secretaria de Estratégia e Projetos | AD27: - Melhoria do Suporte Técnico à Implementação das soluções da PDPJ | AE27: Etapa 1 – Planejamento do projeto  Etapa 2 – Planejamento da Operação, Mapeamento e Capacitação / Criar as novas filas de atendimento conforme necessidade / Realizar a capacitação do time de suporte N2 • Serviços Estruturantes • CODEX • Domicílio Judicial Eletrônico • SNGB • BNMP • SNA • INTEGRA • PREVJUD • SISPERJUD • SPVATJUD • Portal JUS.BR • Consulta Nacional de Pessoas (API Pessoas) • Gestão de Clientes | AF27: =TODAY() -> 46176 | AG27: Thiago de Andrade Vieira | AH27: DTI - Departamento de Tecnologia da Informação e Comunicação | AJ27: =2024&Tb_Portfólio[[#This Row],[SEI]] -> 202402887/2024 | AK27: =IFERROR(IF(MATCH(AJ27,Atualizações!$P$1:$P$1265,0)>0, "Sim"), "Não") -> Sim | AL27: =2025&Tb_Portfólio[[#This Row],[SEI]] -> 202502887/2024 | AM27: =IFERROR(IF(MATCH(AL27,Atualizações!$P$1:$P$2994,0)>0, "Sim"), "Não") -> Sim | AN27: =2026&Tb_Portfólio[[#This Row],[SEI]] -> 202602887/2024 | AO27: =IFERROR(IF(MATCH(AN27,Atualizações!$P$1:$P$2994,0)>0, "Sim"), "Não") -> Sim | AP27: =_xlfn.XLOOKUP(Tb_Portfólio[[#This Row],[SEI]],Tb_Atualizações[PROCESSO SEI],Tb_Atualizações[Explicações],"",0,-1) -> ▪ Etapa atual: Atendimento N2 e Apoio técnico (sistemas/soluções desenvolvidas pelo PNUD). ▪ Soluções em atendimento – Suporte Nível 2 em andamento: • BNMP; • CODEX; • Consulta Nacional de Pessoas; • Delegação de Perfil; • Domicílio Judicial Eletrônico; • INTEGRA; • Integração PDPJ; • Serviços Estruturantes; • SISPERJUD; • SNA; • SISPREQ; • SPVATJUD. ▪ Tarefas N2 atendidas: • 186 tarefas no período de 15 a 21/05/2026; • 225 tarefas no período anterior. ▪ Tarefas N2 criadas: • 172 tarefas no período de 15 a 21/05/2026; • 267 tarefas no período anterior. ▪ Tarefas N2 pendentes: • 86 tarefas em 21/05/2026; • 85 tarefas no período anterior. ▪ Sistemas mais demandados pelo Time de Apoio no período de 15 a 21/05/2026: • BNMP: o 75 tarefas criadas; o 105 tarefas atendidas; o Maior ofensor: erros de servidor (500/403/404), travamento de tela em carregamento, falhas na finalização de peças e bugs de integração de lotação; o Impossibilidade de inclusão de CPF, duplicidade de nomes de genitores e ajustes em registros de irmãos gêmeos; o Dúvidas sobre o novo fluxo de exclusão, regras de unificação de RJI, cadastro de CPFs e orientações sobre alertas de monitoramento; o Mensagens de "HTTP ERROR 404" e "Status 500" no ambiente de produção e testes; o Ponto crítico identificado: ID 220744 - trata de um cumprimento fraudulento de mandado de prisão decorrente de uma invasão no sistema. • Domicílio Judicial Eletrônico: o 35 tarefas criadas; o 32 tarefas atendidas; o Maior ofensor: solicitações de informações relacionadas ao DJE, acesso, perfil, coligadas e notificações por email; o Problemas relacionados a instabilidades temporárias do DJE; o Solicitação direcionadas para outras filas, exemplo: perguntas sobre autenticação de duas etapas; o Usuários com dificuldade para visualizar comunicações processuais devido à ausência de permissão ou ao não recebimento das comunicações; | AQ27: =_xlfn.XLOOKUP(Tb_Portfólio[[#This Row],[SEI]],Tb_Mapa[SEI],Tb_Mapa[CONSULTOR RESPONSÁVEL],"",0,-1) -> juloi
A28: 02888/2024 | B28: Delegação de Perfis | C28: Ampliar a utilização da Plataforma de Delegação de Perfis para abranger outros módulos básicos e negociais da PDPJ, possibilitando a consolidação da delegação de acessos em uma plataforma centralizada. | E28: Dr. Adriano da Silva Araújo | F28: DTI - Departamento de Tecnologia da Informação e Comunicação | G28: Juliano Pinto | H28: PNUD | I28: 01. Desenvolver políticas judiciárias e outros instrumentos para o aperfeiçoamento das atividades dos órgãos do Poder Judiciário e dos seus serviços auxiliares e dos serviços notariais e de registro, e dos demais órgãos correicionais | J28: 03. Agilidade e produtividade na prestação jurisdicional | K28: Programa Justiça 4.0 (Projeto BRA/20/003) | L28: 45170 | M28: 45473 | N28: =_xlfn.XLOOKUP(Tb_Portfólio[[#This Row],[SEI]],Tb_Atualizações[PROCESSO SEI],Tb_Atualizações[% PREVISTO],"",0,-1) -> 1 | O28: =_xlfn.XLOOKUP(Tb_Portfólio[[#This Row],[SEI]],Tb_Atualizações[PROCESSO SEI],Tb_Atualizações[% EXECUTADO],"",0,-1) -> 1 | P28: =IFERROR(Tb_Portfólio[[#This Row],[% EXECUTADO]]/Tb_Portfólio[[#This Row],[% PREVISTO]],"0%") -> 1 | Q28: =_xlfn.XLOOKUP(Tb_Portfólio[[#This Row],[SEI]],Tb_Atualizações[PROCESSO SEI],Tb_Atualizações[DATA DE ATUALIZAÇÃO],"",0,-1) -> 45576 | R28: =_xlfn.XLOOKUP(Tb_Portfólio[[#This Row],[SEI]],Tb_Atualizações[PROCESSO SEI],Tb_Atualizações[Mês],,0,-1) -> 45536 | T28: Justiça 4.0 | U28: =IF(Tb_Portfólio[[#This Row],[% EXECUTADO]]=100%,"Finalizado",IF(Tb_Portfólio[[#This Row],[PREVISÃO DE TERMINO]]<Tb_Portfólio[[#This Row],[Hoje]],"Atrasado ou Crítico",IF(Tb_Portfólio[[#This Row],[% EXECUTADO]]=0,"Autorizado",IF(Tb_Portfólio[[#This Row],[MEDIÇÃO DE STATUS]]>=95%,"No prazo",IF(Tb_Portfólio[[#This Row],[MEDIÇÃO DE STATUS]]<85%,"Atrasado ou Crítico",IF(Tb_Portfólio[[#This Row],[MEDIÇÃO DE STATUS]]<=95%,"Em atenção")))))) -> Finalizado | W28: =IFERROR(Tb_Portfólio[[#This Row],[% EXECUTADO]]/Tb_Portfólio[[#This Row],[% PREVISTO]],0) -> 1 | Y28: 279886.73 | AA28: https://www.cnj.jus.br/tecnologia-da-informacao-e-comunicacao/justica-4-0/ | AB28: Dr. Dorotheo Barbosa Neto | AC28: SEP - Secretaria de Estratégia e Projetos | AF28: =TODAY() -> 46176 | AG28: Thiago de Andrade Vieira | AH28: DTI - Departamento de Tecnologia da Informação e Comunicação | AJ28: =2024&Tb_Portfólio[[#This Row],[SEI]] -> 202402888/2024 | AK28: =IFERROR(IF(MATCH(AJ28,Atualizações!$P$1:$P$1265,0)>0, "Sim"), "Não") -> Sim | AL28: =2025&Tb_Portfólio[[#This Row],[SEI]] -> 202502888/2024 | AM28: =IFERROR(IF(MATCH(AL28,Atualizações!$P$1:$P$2994,0)>0, "Sim"), "Não") -> Não | AN28: =2026&Tb_Portfólio[[#This Row],[SEI]] -> 202602888/2024 | AO28: =IFERROR(IF(MATCH(AN28,Atualizações!$P$1:$P$2994,0)>0, "Sim"), "Não") -> Não | AP28: =_xlfn.XLOOKUP(Tb_Portfólio[[#This Row],[SEI]],Tb_Atualizações[PROCESSO SEI],Tb_Atualizações[Explicações],"",0,-1) -> 0 | AQ28: =_xlfn.XLOOKUP(Tb_Portfólio[[#This Row],[SEI]],Tb_Mapa[SEI],Tb_Mapa[CONSULTOR RESPONSÁVEL],"",0,-1) -> Finalizado
A29: 02938/2021 | B29: SNGB - Sistema Nacional de Gestão de Bens | C29: Produzir nova ferramenta digital para cadastro e controle dos bens apreendidos no âmbito dos processos da justiça brasileira, em substituição à ferramenta atual, denominada Sistema Nacional de Bens Apreendidos (SNBA). | D29: OBJETIVO GERAL Contratar uma empresa para desenvolvimento do Novo SNBA, um sistema que visa o cadastramento e registro debens apreendidos nos procedimentos tramitados na justiça brasileira, permitindo um melhor controle dos processos e bens pelos órgãos judiciais. OBJETIVOS ESPECÍFICOS O Novo SNBA deverá favorecer a integração do Poder Judiciário no âmbito da gestão de bens apreendidos, atuando com eficácia no controle desses bens. O sistema a ser desenvolvido no contexto desta seleção deverá observar as seguintes premissas: Ser um sistema agnóstico, capaz de se integrar a todos os sistemas de processos eletrônicos, nos termos da Resolução CNJ nº 335/2020, que institui a PDPJ-Br. Controlar a situação do bem apreendido desde o registro no sistema até a sua destinação final, sinalizando aos sistemas de processo eletrônico a existência de bem sem destinação, com o fito de impedir o arquivamento definitivo de inquérito ou processo sem que seja dada destinação definitiva a todos os objetos, bens e valores apreendidos e a ele relacionados. Deverá ser capaz de armazenar informações sobre centenas de milhares de registros de bens apreendidos e seus vínculos processuais (pessoas físicas, jurídicas, bens e processos) e possivelmente milhões de vínculos entre esses registros. A tecnologia utilizada deverá se desenvolver através de um banco de dados para o armazenamento e busca dos vínculos. Atender a realidade de tribunais que não possuem central de gestão de bens apreendidos (sendo a gestão realizada ao nível da unidade judiciária), sem deixar de atender tribunais que a possuem ou desejam criá-la. A ferramenta deverá ser acessível através da Web, utilizando os navegadores recentes e sem a necessidade de instalação de plugins ou programas adicionais. A estratégia de disseminação do sistema deverá incluir um Manual Técnico (contendo a produção de conhecimentos gerados) e atividades específicas de transferência da informação e conhecimento aos beneficiários e usuários da ferramenta. Nesse sentido, as atividades de disseminação dos produtos do SNBA não ocorrerão apenas em formato de ação pedagógica, mas deverão criar condições de familiaridade e encorajar o real uso sistema. Os objetivos específicos da estratégia são a difusão do sistema e seus benefícios, criação de ambientes de informação e capacitação e o constante incentivo ao uso e aprendizado. Para isso, as equipes dos Eixos 1 e 3 trabalharão em conjunto no desenvolvimento do sistema para o alinhamento da estratégia e sua correta disseminação. | E29: Dr. Gabriel Da Silveira Matos | F29: SEP - Secretaria de Estratégia e Projetos | G29: Alexandre Alves de Oliveira | H29: PNUD | I29: 09. Fomentar e incrementar a produção de soluções tecnológicas, com foco em inovação e transformação digital | J29: 12. Fortalecimento da estratégia nacional de TIC e de proteção de dados | K29: Resolução 335 /2020 Justiça 4.0 | L29: 44390 | M29: 45519 | N29: =_xlfn.XLOOKUP(Tb_Portfólio[[#This Row],[SEI]],Tb_Atualizações[PROCESSO SEI],Tb_Atualizações[% PREVISTO],"",0,-1) -> 1 | O29: =_xlfn.XLOOKUP(Tb_Portfólio[[#This Row],[SEI]],Tb_Atualizações[PROCESSO SEI],Tb_Atualizações[% EXECUTADO],"",0,-1) -> 1 | P29: =IFERROR(Tb_Portfólio[[#This Row],[% EXECUTADO]]/Tb_Portfólio[[#This Row],[% PREVISTO]],"0%") -> 1 | Q29: =_xlfn.XLOOKUP(Tb_Portfólio[[#This Row],[SEI]],Tb_Atualizações[PROCESSO SEI],Tb_Atualizações[DATA DE ATUALIZAÇÃO],"",0,-1) -> 45519 | R29: =_xlfn.XLOOKUP(Tb_Portfólio[[#This Row],[SEI]],Tb_Atualizações[PROCESSO SEI],Tb_Atualizações[Mês],,0,-1) -> 45474 | T29: Justiça 4.0 | U29: =IF(Tb_Portfólio[[#This Row],[% EXECUTADO]]=100%,"Finalizado",IF(Tb_Portfólio[[#This Row],[PREVISÃO DE TERMINO]]<Tb_Portfólio[[#This Row],[Hoje]],"Atrasado ou Crítico",IF(Tb_Portfólio[[#This Row],[% EXECUTADO]]=0,"Autorizado",IF(Tb_Portfólio[[#This Row],[MEDIÇÃO DE STATUS]]>=95%,"No prazo",IF(Tb_Portfólio[[#This Row],[MEDIÇÃO DE STATUS]]<85%,"Atrasado ou Crítico",IF(Tb_Portfólio[[#This Row],[MEDIÇÃO DE STATUS]]<=95%,"Em atenção")))))) -> Finalizado | V29: https://www.cnj.jus.br/tecnologia-da-informacao-e-comunicacao/justica-4-0/sistema-nacional-de-gestao-de-bens-sngb/ | W29: =IFERROR(Tb_Portfólio[[#This Row],[% EXECUTADO]]/Tb_Portfólio[[#This Row],[% PREVISTO]],0) -> 1 | X29: 1 - Especificações de requisitos funcionais e não funcionais para o desenvolvimento e implantação do Novo SNBA; 2 - Entrega e instalação do módulo de cadastramento e registro de bens apreendidos; 3 - Especificações para o desenvolvimento de painéis BI para apresentação de dados; 4 - Entrega e instalação do módulo de painéis BI; 5 - Especificações de requisitos funcionais e não funcionais para os módulos referentes ao acesso e controle de perfis no sistema e demais módulos relacionados ao acompanhamento da tramitação, movimentação, status (ativação/desativação) e destinação dos bens. 6 - Entrega e instalação dos módulos do Novo SNBA no ambiente do CNJ; 7 - Especificações de requisitos funcionais e não funcionais para prover arquitetura de back end baseada em API; 8 - Entrega e instalação do módulo de interligação do SNBA; 9 - Especificações de requisitos funcionais e não funcionais para prover funcionalidades de Controle e Segurança para o sistema; 10 - Entrega e instalação das funcionalidades de Controle e Segurança para o sistema; 11 - Material para capacitação autoinstrucional | AA29: https://www.cnj.jus.br/tecnologia-da-informacao-e-comunicacao/justica-4-0/ | AB29: Dr. Dorotheo Barbosa Neto | AC29: SEP - Secretaria de Estratégia e Projetos | AD29: 1 - Acabar com as fragilidades identificadas no sistema anterior de Gestão de Bens (por meio do novo sistema SNGB, que já será construído de forma a sanar as fragilidades identificadas); 2 - Possibilitar o uso do sistema de gestão de bens (SNGB) em qualquer processo judicial eletrônico (por meio da elaboração de nova versão, com arquitetura agnóstica, capaz de se integrar a todos os sistemas processuais eletrônicos por meio da PDPJ); | AE29: Produto 1 - Documento técnico contendo especificações de requisitos funcionais e não funcionais para o desenvolvimento e implantação do Novo SNBA (1265206); Produto 2 - Relatório técnico de entrega e instalação do módulo de cadastramento e registro de bens apreendidos (1277784); Produto 3 - Documento técnico contendo especificações para o desenvolvimento de painéis BI para apresentação de dados (1312982); Produto 4 - Relatório técnico de entrega e instalação do módulo de painéis BI (1312992); Produto 5 - Documento técnico contendo especificações de requisitos funcionais e não funcionais para os módulos referentes ao acesso e controle de perfis no sistema e demais módulos relacionados ao acompanhamento da tramitação, movimentação, status (ativação/desativação) e destinação dos bens (1342917); Produto 6 - Relatório técnico de entrega e instalação dos módulos do Novo SNBA no ambiente do CNJ (1352740); Produto 7 - Documento técnico contendo especificações de requisitos funcionais e não funcionais para prover arquitetura de back end baseada em API (1363432); Produto 8 - Relatório técnico de entrega e instalação do módulo de interligação do SNBA (1395454); Produto 9 - Documento técnico contendo especificações de requisitos funcionais e não funcionais para prover funcionalidades de Controle e Segurança para o sistema (1398543); Produto 10 - Relatório técnico de entrega e instalação das funcionalidades de Controle e Segurança para o sistema (1428550); Produto 11 - Relatório Final e material para capacitação autoinstrucional (1456264, 1456268 e 1456271); Produto 12 - Documento técnico contendo (1) a especificação de requisitos funcionais e não funcionais utilizados para a implementação do serviço de busca de informações processuais do Codex ou de outras bases centralizadas (2) atualização da documentação do sistema (FAQ, manuais e outros) (1722780); Produto 13 - Documento técnico contendo (1) a especificação de requisitos funcionais e não funcionais utilizados para implementação da integração do novo SNBA ao serviço de busca de informações processuais do Codex ou outras bases centralizadas (2) atualização da documentação do sistema (FAQ, manuais e outros) (1920162); Produto 14 - Documento técnico contendo (1) especificações de requisitos funcionais e não funcionais utilizados para a implementação de plug in de integração do Novo SNBA com outros sistemas integrantes à PDPJ (2) atualização da documentação do sistema (FAQ, manuais e outros) (1782570); Produto 15 - Documento técnico contendo (1) especificações de requisitos funcionais e não funcionais para a implementação de evoluções nos módulos já existentes no Novo SNBA, preferencialmente os módulos de cadastro e remessas de bens ou integrações com usuários internos e externos (2) atualização da documentação do sistema (FAQ, manuais e outros) (1782571); Produto 16 - Documento técnico contendo: (1) especificações de requisitos funcionais e não funcionais para a implementação de evoluções nos módulos já existentes no Novo SNBA, preferencialmenete os módulos de controle e segurança (2) atualização da documentação do sistema (FAQ, manuais e outros) (1884745); Produto 17 - Documento técnico contendo (1) especificações de requisitos funcionais e não funcionais para a implementação de evoluções nos módulos já existentes no Novo SNBA, preferencialmente as consultas e relatórios estatísticos do sistema (2) atualização da documentação do sistema (FAQ, manuais e outros) e Relatório final contendo avaliação dos resultados alcançados e da estratégia adotada ao longo do trabalho, destacando lições técnicas aprendidas, pontos de melhoria na evolução dos sistemas trabalhados, bem como avaliação dos resultados obtidos (1890538). | AF29: =TODAY() -> 46176 | AG29: Marcos Paulo Santos Calixto | AH29: DTI - Departamento de Tecnologia da Informação e Comunicação | AJ29: =2024&Tb_Portfólio[[#This Row],[SEI]] -> 202402938/2021 | AK29: =IFERROR(IF(MATCH(AJ29,Atualizações!$P$1:$P$1265,0)>0, "Sim"), "Não") -> Sim | AL29: =2025&Tb_Portfólio[[#This Row],[SEI]] -> 202502938/2021 | AM29: =IFERROR(IF(MATCH(AL29,Atualizações!$P$1:$P$2994,0)>0, "Sim"), "Não") -> Não | AN29: =2026&Tb_Portfólio[[#This Row],[SEI]] -> 202602938/2021 | AO29: =IFERROR(IF(MATCH(AN29,Atualizações!$P$1:$P$2994,0)>0, "Sim"), "Não") -> Não | AP29: =_xlfn.XLOOKUP(Tb_Portfólio[[#This Row],[SEI]],Tb_Atualizações[PROCESSO SEI],Tb_Atualizações[Explicações],"",0,-1) -> 0 | AQ29: =_xlfn.XLOOKUP(Tb_Portfólio[[#This Row],[SEI]],Tb_Mapa[SEI],Tb_Mapa[CONSULTOR RESPONSÁVEL],"",0,-1) -> Tony/finalizado
A30: 02941/2021 | B30: SNIPER - Justiça 4.0 | C30: Desenvolver ferramenta de análise financeira e busca de ativos do Poder Judiciário. A ferramenta será denominada SNIPER. | D30: O objetivo do projeto é o desenvolvimento do SNIPER, um sistema que visa a implantação de ferramenta cuja funcionalidade principal será a possibilidade de cruzar informações contidas em bases de dados diferentes, abertas e fechadas, destacando os vínculos societários, patrimoniais e financeiros existentes entre pessoas físicas e jurídicas, que não seriam perceptíveis por uma análise apenas documental, realizados a partir de uma decisão judicial pertinente. A ferramenta dará a possibilidade de os usuários explorarem graficamente esses vínculos, fazendo com que as investigações sejam feitas de maneira mais rápida e eficiente. | E30: Dr. Gabriel Da Silveira Matos | F30: SEP - Secretaria de Estratégia e Projetos | G30: Carlo Borsoi Moura | H30: PNUD | I30: 09. Fomentar e incrementar a produção de soluções tecnológicas, com foco em inovação e transformação digital | J30: 12. Fortalecimento da estratégia nacional de TIC e de proteção de dados | K30: Resolução 335 /2020 Justiça 4.0 | L30: 44433 | M30: 45442 | N30: =_xlfn.XLOOKUP(Tb_Portfólio[[#This Row],[SEI]],Tb_Atualizações[PROCESSO SEI],Tb_Atualizações[% PREVISTO],"",0,-1) -> 1 | O30: =_xlfn.XLOOKUP(Tb_Portfólio[[#This Row],[SEI]],Tb_Atualizações[PROCESSO SEI],Tb_Atualizações[% EXECUTADO],"",0,-1) -> 1 | P30: =IFERROR(Tb_Portfólio[[#This Row],[% EXECUTADO]]/Tb_Portfólio[[#This Row],[% PREVISTO]],"0%") -> 1 | Q30: =_xlfn.XLOOKUP(Tb_Portfólio[[#This Row],[SEI]],Tb_Atualizações[PROCESSO SEI],Tb_Atualizações[DATA DE ATUALIZAÇÃO],"",0,-1) -> 45392 | R30: =_xlfn.XLOOKUP(Tb_Portfólio[[#This Row],[SEI]],Tb_Atualizações[PROCESSO SEI],Tb_Atualizações[Mês],,0,-1) -> 45352 | T30: Justiça 4.0 | U30: =IF(Tb_Portfólio[[#This Row],[% EXECUTADO]]=100%,"Finalizado",IF(Tb_Portfólio[[#This Row],[PREVISÃO DE TERMINO]]<Tb_Portfólio[[#This Row],[Hoje]],"Atrasado ou Crítico",IF(Tb_Portfólio[[#This Row],[% EXECUTADO]]=0,"Autorizado",IF(Tb_Portfólio[[#This Row],[MEDIÇÃO DE STATUS]]>=95%,"No prazo",IF(Tb_Portfólio[[#This Row],[MEDIÇÃO DE STATUS]]<85%,"Atrasado ou Crítico",IF(Tb_Portfólio[[#This Row],[MEDIÇÃO DE STATUS]]<=95%,"Em atenção")))))) -> Finalizado | V30: https://www.cnj.jus.br/tecnologia-da-informacao-e-comunicacao/justica-4-0/sniper/ | W30: =IFERROR(Tb_Portfólio[[#This Row],[% EXECUTADO]]/Tb_Portfólio[[#This Row],[% PREVISTO]],0) -> 1 | X30: 1 - Módulo "mapa de relacionamentos"; 2 - Módulo “ferramenta de pesquisa e busca de ativos”; 3 - Módulo “mapa de relacionamentos CNJ”; 4 - Módulo “dados sigilosos” ; 5 - Garantia | Y30: 375089 | Z30: 533000.65 | AA30: https://www.cnj.jus.br/tecnologia-da-informacao-e-comunicacao/justica-4-0/ | AB30: Dr. Dorotheo Barbosa Neto | AC30: SEP - Secretaria de Estratégia e Projetos | AD30: Ferramenta de análise de entidades e ativos | AE30: - Módulo Mapa de Relacionamento com dados aberto - Módulo de pesquisa e busca de ativos - Módulo Mapa de Relacionamento CNJ - Módulo de dados sigilosos | AF30: =TODAY() -> 46176 | AG30: Francisco Gonçalves de Araújo Filho | AH30: DTI - Departamento de Tecnologia da Informação e Comunicação | AJ30: =2024&Tb_Portfólio[[#This Row],[SEI]] -> 202402941/2021 | AK30: =IFERROR(IF(MATCH(AJ30,Atualizações!$P$1:$P$1265,0)>0, "Sim"), "Não") -> Sim | AL30: =2025&Tb_Portfólio[[#This Row],[SEI]] -> 202502941/2021 | AM30: =IFERROR(IF(MATCH(AL30,Atualizações!$P$1:$P$2994,0)>0, "Sim"), "Não") -> Não | AN30: =2026&Tb_Portfólio[[#This Row],[SEI]] -> 202602941/2021 | AO30: =IFERROR(IF(MATCH(AN30,Atualizações!$P$1:$P$2994,0)>0, "Sim"), "Não") -> Não | AP30: =_xlfn.XLOOKUP(Tb_Portfólio[[#This Row],[SEI]],Tb_Atualizações[PROCESSO SEI],Tb_Atualizações[Explicações],"",0,-1) -> 0 | AQ30: =_xlfn.XLOOKUP(Tb_Portfólio[[#This Row],[SEI]],Tb_Mapa[SEI],Tb_Mapa[CONSULTOR RESPONSÁVEL],"",0,-1) -> Tony/finalizado
A31: 03096/2021 | B31: PMO Jud -Redesenho dos processos do Escritório de Projetos do CNJ | C31: Redesenho dos processos do Escritório de Projetos do CNJ | D31: Objetivo Geral Estruturar escritório de projetos no CNJ, com foco na otimização e coordenação, transparência e gestão estratégica das iniciativas implantadas pelo CNJ. Objetivos Específicos Fortalecer a capacidade do CNJ para elaborar, acompanhar e difundir seus programas e projetos estratégicos. Fortalecer a capacidade do CNJ para monitorar os resultados de políticas judiciárias, programas e projetos. Ampliar o acesso do público a dados atualizados sobre Portfólio do CNJ. Fortalecer a capacidade do CNJ para monitorar os indicadores de desempenho da Estratégia Nacional do Poder Judiciário (2021-2026). | E31: Dr. Gabriel Da Silveira Matos | F31: SEP - Secretaria de Estratégia e Projetos | G31: Claudia Lopes Correa | H31: PNUD | I31: 12. Promover práticas inovadoras de gestão e de incentivo ao trabalho colaborativo | J31: 09. Aperfeiçoamento da gestão administrativa e da governança judiciária | K31: Resolução 335 /2020 Justiça 4.0 | L31: 44306 | M31: 45291 | N31: =_xlfn.XLOOKUP(Tb_Portfólio[[#This Row],[SEI]],Tb_Atualizações[PROCESSO SEI],Tb_Atualizações[% PREVISTO],"",0,-1) -> 1 | O31: =_xlfn.XLOOKUP(Tb_Portfólio[[#This Row],[SEI]],Tb_Atualizações[PROCESSO SEI],Tb_Atualizações[% EXECUTADO],"",0,-1) -> 1 | P31: =IFERROR(Tb_Portfólio[[#This Row],[% EXECUTADO]]/Tb_Portfólio[[#This Row],[% PREVISTO]],"0%") -> 1 | Q31: =_xlfn.XLOOKUP(Tb_Portfólio[[#This Row],[SEI]],Tb_Atualizações[PROCESSO SEI],Tb_Atualizações[DATA DE ATUALIZAÇÃO],"",0,-1) -> 45512 | R31: =_xlfn.XLOOKUP(Tb_Portfólio[[#This Row],[SEI]],Tb_Atualizações[PROCESSO SEI],Tb_Atualizações[Mês],,0,-1) -> 45474 | T31: Justiça 4.0 | U31: =IF(Tb_Portfólio[[#This Row],[% EXECUTADO]]=100%,"Finalizado",IF(Tb_Portfólio[[#This Row],[PREVISÃO DE TERMINO]]<Tb_Portfólio[[#This Row],[Hoje]],"Atrasado ou Crítico",IF(Tb_Portfólio[[#This Row],[% EXECUTADO]]=0,"Autorizado",IF(Tb_Portfólio[[#This Row],[MEDIÇÃO DE STATUS]]>=95%,"No prazo",IF(Tb_Portfólio[[#This Row],[MEDIÇÃO DE STATUS]]<85%,"Atrasado ou Crítico",IF(Tb_Portfólio[[#This Row],[MEDIÇÃO DE STATUS]]<=95%,"Em atenção")))))) -> Finalizado | W31: =IFERROR(Tb_Portfólio[[#This Row],[% EXECUTADO]]/Tb_Portfólio[[#This Row],[% PREVISTO]],0) -> 1 | X31: Produto 01 - Plano de trabalho, Produto Produto 02 - Diagnóstico de Maturidade em Gestão, Produto 03 - Capacitação em Gerenciamento de Portfólios e Projetos, Produto 04 - Plano de Melhorias, Produto 05 – Revisão da Metodologia de Gerenciamento de Projetos, Produto 06 - Implementação e Monitoramento do Escritório de Projetos - FASE 1, Produto 07 - Implementação e Monitoramento do Escritório de Projetos - FASE 2 e Produto 08 – Avaliação e Guia com Ferramentas e Melhores Práticas de Gestão de Projetos. | AA31: https://www.cnj.jus.br/tecnologia-da-informacao-e-comunicacao/justica-4-0/ | AB31: Dra. Dayse Starling Motta | AC31: SEP - Secretaria de Estratégia e Projetos | AE31: - Entrega 01: Plano de Trabalho - Entrega 02: Capacitações em gerenciamento de projetos - Entrega 03: Relatório final de diagnóstico P3M3 e MMGP - Entrega 04: Plano de Melhorias - Entrega 05: Proposta de atualização da metodologia de gerenciamento de projetos do centro de serviços -Entrega 06: Modelos e documentos complementares à metodologia definida no produto “Revisão da Metodologia de Gerenciamento de Projetos”, bem como modelos de relatórios e dashboards, conforme necessário; Definição dos requisitos para implementação, customização ou utilização de ferramentas para gestão de projetos; Execução das configurações, parametrizações ou implantações de sistemas necessários, incluindo Microsoft Project Online, Power BI e Microsoft 365, conforme plano de trabalho. - Entrega 07: Monitoramento e acompanhamento junto à equipe CNJ. - Entrega 08: Relatório de encerramento do projeto. | AF31: =TODAY() -> 46176 | AG31: Cristina de Oliveira Winckler | AH31: ECP - Escritório Corporativo de Projetos Institucionais | AJ31: =2024&Tb_Portfólio[[#This Row],[SEI]] -> 202403096/2021 | AK31: =IFERROR(IF(MATCH(AJ31,Atualizações!$P$1:$P$1265,0)>0, "Sim"), "Não") -> Sim | AL31: =2025&Tb_Portfólio[[#This Row],[SEI]] -> 202503096/2021 | AM31: =IFERROR(IF(MATCH(AL31,Atualizações!$P$1:$P$2994,0)>0, "Sim"), "Não") -> Não | AN31: =2026&Tb_Portfólio[[#This Row],[SEI]] -> 202603096/2021 | AO31: =IFERROR(IF(MATCH(AN31,Atualizações!$P$1:$P$2994,0)>0, "Sim"), "Não") -> Não | AP31: =_xlfn.XLOOKUP(Tb_Portfólio[[#This Row],[SEI]],Tb_Atualizações[PROCESSO SEI],Tb_Atualizações[Explicações],"",0,-1) -> 0 | AQ31: =_xlfn.XLOOKUP(Tb_Portfólio[[#This Row],[SEI]],Tb_Mapa[SEI],Tb_Mapa[CONSULTOR RESPONSÁVEL],"",0,-1) -> Cristina de Oliveira Winckler /Finalizado
A32: 03545/2021 | B32: Painel de Estatística - Justiça 4.0 | C32: Produzir novo painel digital, denominado "Painel de Estatística", seguindo o disposto na Resolução n. 333/2020, que determina a inclusão de campo/espaço denominado "Estatística" na página principal dos sítios eletrônicos dos órgãos do Poder Judiciário, disponibilizando dados de um banco de dados massivo em um painel de simples navegação e acesso, compilando as estatísticas judiciárias processuais mais relevantes. | D32: O objetivo do presente projeto é possibilitar, por meio do desenvolvimento de um painel de estatísticas, com vistas a facilitar o acesso às informações consolidadas da atividade-fim dos órgãos do Poder Judiciário, ressaltando que a atividade-meio é a produção dos dados gerados pelos referidos Órgãos do Poder Judiciário em suas respectivas esferas, de modo a fundamentar a tomada de decisões tanto do CNJ quanto dos próprios Tribunais. Essa disponibilidade de dados se justifica pela imprescindibilidade do uso de dados atuais, confiáveis e desagregados, disponíveis em um mesmo campo/espaço no portal do tribunal, com vistas a reunir dados abertos, melhorando a transparência e o acesso a esses dados e informações por meio de Painéis de Business Intelligence e Relatórios Estatísticos referentes à atividade-fim do Poder Judiciário. | E32: Dra. Ana Lúcia Andrade de Aguiar | F32: SEP - Secretaria de Estratégia e Projetos | G32: André José da Silva Lima | H32: PNUD | I32: 03. Fomentar a gestão da qualidade dos dados no Poder Judiciário | J32: 09. Aperfeiçoamento da gestão administrativa e da governança judiciária | K32: Resolução n. 76/2019 | L32: 44317 | M32: 46387 | N32: =_xlfn.XLOOKUP(Tb_Portfólio[[#This Row],[SEI]],Tb_Atualizações[PROCESSO SEI],Tb_Atualizações[% PREVISTO],"",0,-1) -> 0.89 | O32: =_xlfn.XLOOKUP(Tb_Portfólio[[#This Row],[SEI]],Tb_Atualizações[PROCESSO SEI],Tb_Atualizações[% EXECUTADO],"",0,-1) -> 0.77 | P32: =IFERROR(Tb_Portfólio[[#This Row],[% EXECUTADO]]/Tb_Portfólio[[#This Row],[% PREVISTO]],"0%") -> 0.86516854 | Q32: =_xlfn.XLOOKUP(Tb_Portfólio[[#This Row],[SEI]],Tb_Atualizações[PROCESSO SEI],Tb_Atualizações[DATA DE ATUALIZAÇÃO],"",0,-1) -> 46167 | R32: =_xlfn.XLOOKUP(Tb_Portfólio[[#This Row],[SEI]],Tb_Atualizações[PROCESSO SEI],Tb_Atualizações[Mês],,0,-1) -> 46143 | T32: Justiça 4.0 | U32: =IF(Tb_Portfólio[[#This Row],[% EXECUTADO]]=100%,"Finalizado",IF(Tb_Portfólio[[#This Row],[PREVISÃO DE TERMINO]]<Tb_Portfólio[[#This Row],[Hoje]],"Atrasado ou Crítico",IF(Tb_Portfólio[[#This Row],[% EXECUTADO]]=0,"Autorizado",IF(Tb_Portfólio[[#This Row],[MEDIÇÃO DE STATUS]]>=95%,"No prazo",IF(Tb_Portfólio[[#This Row],[MEDIÇÃO DE STATUS]]<85%,"Atrasado ou Crítico",IF(Tb_Portfólio[[#This Row],[MEDIÇÃO DE STATUS]]<=95%,"Em atenção")))))) -> Em atenção | W32: =IFERROR(Tb_Portfólio[[#This Row],[% EXECUTADO]]/Tb_Portfólio[[#This Row],[% PREVISTO]],0) -> 0.86516854 | X32: I – Entrega do painel de estatística em pleno funcionamento e com uso aberto aos usuários; 2 - Usabilidade da ferramenta por todos os tribunais do país; 3 - Utilização dos dados do painel como referência para obtenção de pontuação dos tribunais no prêmio CNJ de qualidade; 4 - Disponibilização de acesso para corregedoria nacional de justiça para a extração de dados customizados, além de realização de reuniões periódicas para apresentação do painel, verificação do uso e sugestão de implementações; 5 - Desenvolvimento de 6 painéis; 6 - Reestruturação do Sistema de Gestão de Tabelas (SGT) em suas tabelas de consultas de classes, movimentos e assuntos | AA32: https://www.cnj.jus.br/tecnologia-da-informacao-e-comunicacao/justica-4-0/ | AB32: Dra. Ana Lúcia Andrade de Aguiar | AC32: DPJ - Departamento de Pesquisas Judiciárias | AD32: 1 - Disponibilização de dados saneados e padronizados; 2 - Desenvolvimento de tecnologia que servirá como modelo para a atualização de parâmetros vigentes e para o desenvolvimento de outros painéis temáticos do CNJ; 3 - Redução do nível de inconsistência detectado pelo DPJ nos painéis de qualificação dos dados, a partir da qualificação do DataJud. | AE32: • Entrega do painel de estatística em pleno funcionamento e com uso aberto aos usuários • Usabilidade da ferramenta por todos os tribunais do país • Utilização dos dados do painel como referência para obtenção de pontuação dos tribunais no prêmio CNJ de qualidade • Disponibilização de acesso para corregedoria nacional de justiça para a extração de dados customizados, além de realização de reuniões periódicas para apresentação do painel, verificação do uso e sugestão de implementações • Desenvolvimento de 6 painéis • Reestruturação do Sistema de Gestão de Tabelas (SGT) em suas tabelas de consultas de classes, movimentos e assuntos | AF32: =TODAY() -> 46176 | AG32: Isabely Fontana da Mota | AH32: DPJ - Departamento de Pesquisas Judiciárias | AJ32: =2024&Tb_Portfólio[[#This Row],[SEI]] -> 202403545/2021 | AK32: =IFERROR(IF(MATCH(AJ32,Atualizações!$P$1:$P$1265,0)>0, "Sim"), "Não") -> Sim | AL32: =2025&Tb_Portfólio[[#This Row],[SEI]] -> 202503545/2021 | AM32: =IFERROR(IF(MATCH(AL32,Atualizações!$P$1:$P$2994,0)>0, "Sim"), "Não") -> Sim | AN32: =2026&Tb_Portfólio[[#This Row],[SEI]] -> 202603545/2021 | AO32: =IFERROR(IF(MATCH(AN32,Atualizações!$P$1:$P$2994,0)>0, "Sim"), "Não") -> Sim | AP32: =_xlfn.XLOOKUP(Tb_Portfólio[[#This Row],[SEI]],Tb_Atualizações[PROCESSO SEI],Tb_Atualizações[Explicações],"",0,-1) -> 0 | AQ32: =_xlfn.XLOOKUP(Tb_Portfólio[[#This Row],[SEI]],Tb_Mapa[SEI],Tb_Mapa[CONSULTOR RESPONSÁVEL],"",0,-1) -> Tony
A33: 03558/2021 | B33: Prevjud - Automação de Processos Previdenciários - Justiça 4.0 | C33: Solução de software para automação dos acessos a informações das bases de dados do INSS, bem como automação do cumprimento, pelo INSS, das decisões judiciais. | D33: Objetivo Geral Desenvolver solução de software para automação dos acessos a informações das bases de dados do INSS, bem como automação do cumprimento, pelo INSS, das decisões judiciais. Objetivos Específicos - Automatizar a requisição aos sistemas do INSS, sem a necessidade de intervenção humana, dos dados do segurado necessários para o andamento da ação judicial. - Automatizar a disponibilização, pelos sistemas do INSS, dos dados do segurado necessários para o andamento da ação judicial; - Automatizar o encaminhamento dos dados das decisões judiciais, de forma estruturada, aos sistemas do INSS; - Automatizar o acompanhamento do cumprimento das decisões judiciais; - Automatizar o recebimento da informação que atesta o cumprimento pelo INSS das decisões judiciais. | E33: Dra. Lívia Cristina Marques Peres | F33: SEP - Secretaria de Estratégia e Projetos | G33: Wallace Fernando Carlos da Silva | H33: PNUD | I33: 07. Fomentar e fortalecer a atuação interinstitucional do CNJ para garantir os direitos dos cidadãos | J33: 03. Agilidade e produtividade na prestação jurisdicional | K33: Resolução 335 /2020 Justiça 4.0 | L33: 44315 | M33: 31/03/2026 | N33: =_xlfn.XLOOKUP(Tb_Portfólio[[#This Row],[SEI]],Tb_Atualizações[PROCESSO SEI],Tb_Atualizações[% PREVISTO],"",0,-1) -> 0.99 | O33: =_xlfn.XLOOKUP(Tb_Portfólio[[#This Row],[SEI]],Tb_Atualizações[PROCESSO SEI],Tb_Atualizações[% EXECUTADO],"",0,-1) -> 1 | P33: =IFERROR(Tb_Portfólio[[#This Row],[% EXECUTADO]]/Tb_Portfólio[[#This Row],[% PREVISTO]],"0%") -> 1.010101 | Q33: =_xlfn.XLOOKUP(Tb_Portfólio[[#This Row],[SEI]],Tb_Atualizações[PROCESSO SEI],Tb_Atualizações[DATA DE ATUALIZAÇÃO],"",0,-1) -> 46136 | R33: =_xlfn.XLOOKUP(Tb_Portfólio[[#This Row],[SEI]],Tb_Atualizações[PROCESSO SEI],Tb_Atualizações[Mês],,0,-1) -> 46113 | T33: Justiça 4.0 | U33: =IF(Tb_Portfólio[[#This Row],[% EXECUTADO]]=100%,"Finalizado",IF(Tb_Portfólio[[#This Row],[PREVISÃO DE TERMINO]]<Tb_Portfólio[[#This Row],[Hoje]],"Atrasado ou Crítico",IF(Tb_Portfólio[[#This Row],[% EXECUTADO]]=0,"Autorizado",IF(Tb_Portfólio[[#This Row],[MEDIÇÃO DE STATUS]]>=95%,"No prazo",IF(Tb_Portfólio[[#This Row],[MEDIÇÃO DE STATUS]]<85%,"Atrasado ou Crítico",IF(Tb_Portfólio[[#This Row],[MEDIÇÃO DE STATUS]]<=95%,"Em atenção")))))) -> Finalizado | V33: https://www.cnj.jus.br/tecnologia-da-informacao-e-comunicacao/justica-4-0/prevjud/ | W33: =IFERROR(Tb_Portfólio[[#This Row],[% EXECUTADO]]/Tb_Portfólio[[#This Row],[% PREVISTO]],0) -> 1.010101 | X33: 1 - Montagem do Ambiente PDPJ - Prover toda a infraestrutura de desenvolvimento do serviço na plataforma PDPJ, o que inclui projeto no Jira, Gitlab e ambientes de desenvolvimento, QA e Produção; 2- Integração com SSO - Permite que os sistemas processuais eletrônicos possam autenticar os usuários no serviço Prevjud pela PDPJ.; 3 - Nova Integração com SSO - Permitir que os sistemas processuais eletrônicos possam receberas notificações do serviço Prevjud pela PDPJ.; 4 - Dossiê Médico - Disponibilizar o relatório de dossiê médico do INSS para os autos dos processos judiciais de forma eletrônica; 5 - Dossiê Previdenciário - Disponibilizar os relatórios do dossiê previdenciário do INSS para os autos dos processos judiciais de forma eletrônica; 6 - PAP - Disponibilizar o relatório de Processo Administrativo Previdenciário do INSS para os autos dos processos judiciais de forma eletrônica; 7 - Módulo de Gestão de Ordens Judiciais - Permite o envio eletrônico de uma ordem judicial ao INSS para o seu cumprimento, evitando uso de e-mail, ofícios e outras formas mais manuais; 8 - Módulo de Extração de Dados - Permite a extração dos dados da intimação judicial da sentença do processo, o que permite o envio desta intimação de forma automática, sem preenchimentos de formulários. | AA33: https://www.cnj.jus.br/tecnologia-da-informacao-e-comunicacao/justica-4-0/ | AB33: Dra. Lívia Cristina Marques Peres | AC33: SEP - Secretaria de Estratégia e Projetos | AD33: 1 - Disponibilização da ferramenta PREVJUD que possa ser utilizada por todos os sistemas processuais eletrônicos.; 2 - Acesso automático de informações previdenciárias, insertas no Dossiê Médico, Dossiê Previdenciário e Processo Administrativo Previdenciário; 3 - Intimação automatizada de ordem judicial dirigida ao INSS. | AE33: Montagem do Ambiente PDPJ Integração com SSO Nova Integração com SSO Dossiê Médico Dossiê Previdenciário PAP Módulo de Gestão de Ordens Judiciais Módulo de Extração de Dados | AF33: =TODAY() -> 46176 | AG33: Antonio Ferreira de Melo Filho | AH33: ECP - Escritório Corporativo de Projetos Institucionais | AJ33: =2024&Tb_Portfólio[[#This Row],[SEI]] -> 202403558/2021 | AK33: =IFERROR(IF(MATCH(AJ33,Atualizações!$P$1:$P$1265,0)>0, "Sim"), "Não") -> Sim | AL33: =2025&Tb_Portfólio[[#This Row],[SEI]] -> 202503558/2021 | AM33: =IFERROR(IF(MATCH(AL33,Atualizações!$P$1:$P$2994,0)>0, "Sim"), "Não") -> Sim | AN33: =2026&Tb_Portfólio[[#This Row],[SEI]] -> 202603558/2021 | AO33: =IFERROR(IF(MATCH(AN33,Atualizações!$P$1:$P$2994,0)>0, "Sim"), "Não") -> Sim | AP33: =_xlfn.XLOOKUP(Tb_Portfólio[[#This Row],[SEI]],Tb_Atualizações[PROCESSO SEI],Tb_Atualizações[Explicações],"",0,-1) -> Projeto finalizado, aguardando assinatura do TEP | AQ33: =_xlfn.XLOOKUP(Tb_Portfólio[[#This Row],[SEI]],Tb_Mapa[SEI],Tb_Mapa[CONSULTOR RESPONSÁVEL],"",0,-1) -> Tony
A34: 03559/2021 | B34: Aperfeiçoamento funcional em temáticas prioritárias para o CNJ e para Justiça Federal (cursos, capacitações, metodologias e ferramentas) | C34: Elaboração de cursos, materiais e ferramentas de capacitação na modalidade de Educação à Distância (EaD) | D34: Objetivo Geral Elaboração de cursos de capacitação com foco no aperfeiçoamento da atuação do Poder Judiciário, disponibilização de ferramentas e metodologias para a gestão do conhecimento e fortalecimento da cultura organizacional. Objetivos Específicos Fortalecer as capacidades institucionais do CNJ e do Poder Judiciário e a promoção da segurança jurídica; Promover o aprimoramento e gestão da informação dos dados judiciários e a integração das informações estratégicas; Desenvolver conteúdos adaptados às demandas de formação dos magistrados e servidores do Poder Judiciário; Aprimorar o acesso à informação, capacitação e o estabelecimento da governança colaborativa no Poder Judiciário. | E34: Dr. Gabriel Da Silveira Matos | F34: SEP - Secretaria de Estratégia e Projetos | G34: Tamires Aparecida Ferreira Souza | H34: PNUD | I34: 16. Aperfeiçoar políticas e práticas de Gestão de Pessoas | J34: 09. Aperfeiçoamento da gestão administrativa e da governança judiciária | K34: Resolução 335 /2020 Justiça 4.0 | L34: 44501 | M34: 45351 | N34: =_xlfn.XLOOKUP(Tb_Portfólio[[#This Row],[SEI]],Tb_Atualizações[PROCESSO SEI],Tb_Atualizações[% PREVISTO],"",0,-1) -> 1 | O34: =_xlfn.XLOOKUP(Tb_Portfólio[[#This Row],[SEI]],Tb_Atualizações[PROCESSO SEI],Tb_Atualizações[% EXECUTADO],"",0,-1) -> 1 | P34: =IFERROR(Tb_Portfólio[[#This Row],[% EXECUTADO]]/Tb_Portfólio[[#This Row],[% PREVISTO]],"0%") -> 1 | Q34: =_xlfn.XLOOKUP(Tb_Portfólio[[#This Row],[SEI]],Tb_Atualizações[PROCESSO SEI],Tb_Atualizações[DATA DE ATUALIZAÇÃO],"",0,-1) -> 45358 | R34: =_xlfn.XLOOKUP(Tb_Portfólio[[#This Row],[SEI]],Tb_Atualizações[PROCESSO SEI],Tb_Atualizações[Mês],,0,-1) -> 45323 | T34: Justiça 4.0 | U34: =IF(Tb_Portfólio[[#This Row],[% EXECUTADO]]=100%,"Finalizado",IF(Tb_Portfólio[[#This Row],[PREVISÃO DE TERMINO]]<Tb_Portfólio[[#This Row],[Hoje]],"Atrasado ou Crítico",IF(Tb_Portfólio[[#This Row],[% EXECUTADO]]=0,"Autorizado",IF(Tb_Portfólio[[#This Row],[MEDIÇÃO DE STATUS]]>=95%,"No prazo",IF(Tb_Portfólio[[#This Row],[MEDIÇÃO DE STATUS]]<85%,"Atrasado ou Crítico",IF(Tb_Portfólio[[#This Row],[MEDIÇÃO DE STATUS]]<=95%,"Em atenção")))))) -> Finalizado | W34: =IFERROR(Tb_Portfólio[[#This Row],[% EXECUTADO]]/Tb_Portfólio[[#This Row],[% PREVISTO]],0) -> 1 | X34: 1. Fundamentos de estatística para Ciência de dados; 2. Excel para análise de dados; 3. R para análise de dados; 4. Python para análise de dados; 5. Dashboards com o Power BI; 6. Dashboards e relatórios dinâmicos com o R e 7. aprendizado de máquina. | AA34: https://www.cnj.jus.br/tecnologia-da-informacao-e-comunicacao/justica-4-0/ | AB34: Dra. Ana Lúcia Andrade de Aguiar | AC34: DPJ - Departamento de Pesquisas Judiciárias | AD34: Benefício 1 - Sensibilizar magistrados e servidores do Poder Judiciário sobre a importância de capacitações na área de Ciência de Dados, a fim de fomentar a cultura de dados no judiciário Benefício 2 - Habilitar o desenvolvimento de capacidades funcionais, na área de Ciência de Dados, de magistrados e servidores do Poder Judiciário | AE34: - Plano de execução detalhada do acordo - 1227309; Curso Fundamentos de Estatística para Ciência de Dados – síncrono e autoinstrucional – 1413430; - Curso Excel para Análise de Dados – síncrono e autoinstrucional - 1489516; - Curso R para Análise de Dados – síncrono e autoinstrucional – 1501914; - Curso Python para Análise de Dados – síncrono e autoinstrucional - 1375897; - Curso Dashboards com o Power BI – síncrono e autoinstrucional - 1382768; - Curso Dashboards e Relatórios Dinâmicos com o R – síncrono e autoinstrucional – 1381256; - Curso Aprendizado de Máquina (Machine Learning) – síncrono e autoinstrucional – 1535861; - Curso Mineração de Texto – síncrono e autoinstrucional – 1535863; - Relatório final das ofertas dos cursos – 1535898; - Plano de trabalho do Curso síncrono de Spark – Distribuição e Processamento de Dados – 1484510; - Curso de Spark – Distribuição e Processamento de Dados – síncrono - 1612642; - Curso de Spark – Distribuição e Processamento de Dados – adaptado ao formato autoinstrucional – 1771992 | AF34: =TODAY() -> 46176 | AG34: Gabriela Moreira de Azevedo Soares | AH34: DPJ - Departamento de Pesquisas Judiciárias | AJ34: =2024&Tb_Portfólio[[#This Row],[SEI]] -> 202403559/2021 | AK34: =IFERROR(IF(MATCH(AJ34,Atualizações!$P$1:$P$1265,0)>0, "Sim"), "Não") -> Sim | AL34: =2025&Tb_Portfólio[[#This Row],[SEI]] -> 202503559/2021 | AM34: =IFERROR(IF(MATCH(AL34,Atualizações!$P$1:$P$2994,0)>0, "Sim"), "Não") -> Não | AN34: =2026&Tb_Portfólio[[#This Row],[SEI]] -> 202603559/2021 | AO34: =IFERROR(IF(MATCH(AN34,Atualizações!$P$1:$P$2994,0)>0, "Sim"), "Não") -> Não | AP34: =_xlfn.XLOOKUP(Tb_Portfólio[[#This Row],[SEI]],Tb_Atualizações[PROCESSO SEI],Tb_Atualizações[Explicações],"",0,-1) -> 0 | AQ34: =_xlfn.XLOOKUP(Tb_Portfólio[[#This Row],[SEI]],Tb_Mapa[SEI],Tb_Mapa[CONSULTOR RESPONSÁVEL],"",0,-1) -> Tony/finalizado
A35: 03924/2023 | B35: Nacionalização SAREF - Sistema de Apresentação Remota por Reconhecimento Facial | C35: Disponibilizar, para todos os tribunais aderentes à PDPJ-BR, o Sistema SAREF (Sistema de Apresentação Remota por Reconhecimento Facial), de modo a nacionalizar a solução. | E35: Dr. Dorotheo Barbosa Neto | F35: SEP - Secretaria de Estratégia e Projetos | G35: Marcelo da Rocha Santos | H35: PNUD | I35: 07. Fomentar e fortalecer a atuação interinstitucional do CNJ para garantir os direitos dos cidadãos | J35: 03. Agilidade e produtividade na prestação jurisdicional | K35: Resolução 335 /2020 Justiça 4.0 | L35: 45200 | M35: 45565 | N35: =_xlfn.XLOOKUP(Tb_Portfólio[[#This Row],[SEI]],Tb_Atualizações[PROCESSO SEI],Tb_Atualizações[% PREVISTO],"",0,-1) -> 1 | O35: =_xlfn.XLOOKUP(Tb_Portfólio[[#This Row],[SEI]],Tb_Atualizações[PROCESSO SEI],Tb_Atualizações[% EXECUTADO],"",0,-1) -> 1 | P35: =IFERROR(Tb_Portfólio[[#This Row],[% EXECUTADO]]/Tb_Portfólio[[#This Row],[% PREVISTO]],"0%") -> 1 | Q35: =_xlfn.XLOOKUP(Tb_Portfólio[[#This Row],[SEI]],Tb_Atualizações[PROCESSO SEI],Tb_Atualizações[DATA DE ATUALIZAÇÃO],"",0,-1) -> 45755 | R35: =_xlfn.XLOOKUP(Tb_Portfólio[[#This Row],[SEI]],Tb_Atualizações[PROCESSO SEI],Tb_Atualizações[Mês],,0,-1) -> 45717 | T35: Justiça 4.0 | U35: =IF(Tb_Portfólio[[#This Row],[% EXECUTADO]]=100%,"Finalizado",IF(Tb_Portfólio[[#This Row],[PREVISÃO DE TERMINO]]<Tb_Portfólio[[#This Row],[Hoje]],"Atrasado ou Crítico",IF(Tb_Portfólio[[#This Row],[% EXECUTADO]]=0,"Autorizado",IF(Tb_Portfólio[[#This Row],[MEDIÇÃO DE STATUS]]>=95%,"No prazo",IF(Tb_Portfólio[[#This Row],[MEDIÇÃO DE STATUS]]<85%,"Atrasado ou Crítico",IF(Tb_Portfólio[[#This Row],[MEDIÇÃO DE STATUS]]<=95%,"Em atenção")))))) -> Finalizado | W35: =IFERROR(Tb_Portfólio[[#This Row],[% EXECUTADO]]/Tb_Portfólio[[#This Row],[% PREVISTO]],0) -> 1 | X35: Documentos iniciais do projeto elaborados e aprovados. Versão inicial dos manuais entregue para revisão pela área de comunicação Revisão do sistema desenvolvido | AA35: https://www.cnj.jus.br/tecnologia-da-informacao-e-comunicacao/justica-4-0/ | AB35: Dr. João Felipe Menezes Lopes | AC35: DMF - Departamento de Monitoramento e Fiscalização do Sistema Carcerário e do Sistema de Execução de Medidas Socioeducativas | AD35: Disponibilização ampla de ferramenta que possibilita o reconhecimento facial de pessoas em alternativas penais | AE35: Identificação e gestão das melhorias necessárias Elaboração de manuais e documentação do sistema Implementação de melhorias conforme necessidades apresentadas e aprovadas pelo DMF Transferência de conhecimento para o CNJ Criação de cenários de testes e realização de testes | AF35: =TODAY() -> 46176 | AG35: Jairo Simão Santana Melo | AH35: DTI - Departamento de Tecnologia da Informação e Comunicação | AJ35: =2024&Tb_Portfólio[[#This Row],[SEI]] -> 202403924/2023 | AK35: =IFERROR(IF(MATCH(AJ35,Atualizações!$P$1:$P$1265,0)>0, "Sim"), "Não") -> Sim | AL35: =2025&Tb_Portfólio[[#This Row],[SEI]] -> 202503924/2023 | AM35: =IFERROR(IF(MATCH(AL35,Atualizações!$P$1:$P$2994,0)>0, "Sim"), "Não") -> Sim | AN35: =2026&Tb_Portfólio[[#This Row],[SEI]] -> 202603924/2023 | AO35: =IFERROR(IF(MATCH(AN35,Atualizações!$P$1:$P$2994,0)>0, "Sim"), "Não") -> Não | AP35: =_xlfn.XLOOKUP(Tb_Portfólio[[#This Row],[SEI]],Tb_Atualizações[PROCESSO SEI],Tb_Atualizações[Explicações],"",0,-1) -> Daniel informa que o projeto finalizou no Programa Justiça 4.0 e será transferido para o Fazendo Justiça. Foi solicitado ao gerente do projeto colocar essa informação no TEP, que se encontra em elaboração. | AQ35: =_xlfn.XLOOKUP(Tb_Portfólio[[#This Row],[SEI]],Tb_Mapa[SEI],Tb_Mapa[CONSULTOR RESPONSÁVEL],"",0,-1) -> Igor/Finalizado
A36: 04137/2024 | B36: Integra - Serviço de Monitoramento de Atos do CNJ | C36: Evoluir de forma digital o serviço de monitoramento de normativos do CNJ, padronizar e automatizar os fluxos do procedimento de Acompanhamento de Cumprimento de Decisão – Cumprdec, tornando um serviço oficial do CNJ. | E36: Ministro Luís Roberto Barroso | F36: Presidência do CNJ | G36: Sandra de Oliveira Carvalho | H36: SERES - Seção de Acompanhamento das Resoluções e Recomendações | I36: 02. Aperfeiçoar os mecanismos de monitoramento de políticas judiciárias | J36: 09. Aperfeiçoamento da gestão administrativa e da governança judiciária | K36: Política de Gestão da Inovação - Resolução CNJ nº 395/2021 | L36: 45352 | M36: 46285 | N36: =_xlfn.XLOOKUP(Tb_Portfólio[[#This Row],[SEI]],Tb_Atualizações[PROCESSO SEI],Tb_Atualizações[% PREVISTO],"",0,-1) -> 0.84 | O36: =_xlfn.XLOOKUP(Tb_Portfólio[[#This Row],[SEI]],Tb_Atualizações[PROCESSO SEI],Tb_Atualizações[% EXECUTADO],"",0,-1) -> 0.82 | P36: =IFERROR(Tb_Portfólio[[#This Row],[% EXECUTADO]]/Tb_Portfólio[[#This Row],[% PREVISTO]],"0%") -> 0.97619048 | Q36: =_xlfn.XLOOKUP(Tb_Portfólio[[#This Row],[SEI]],Tb_Atualizações[PROCESSO SEI],Tb_Atualizações[DATA DE ATUALIZAÇÃO],"",0,-1) -> 46107 | R36: =_xlfn.XLOOKUP(Tb_Portfólio[[#This Row],[SEI]],Tb_Atualizações[PROCESSO SEI],Tb_Atualizações[Mês],,0,-1) -> 46082 | U36: =IF(Tb_Portfólio[[#This Row],[% EXECUTADO]]=100%,"Finalizado",IF(Tb_Portfólio[[#This Row],[PREVISÃO DE TERMINO]]<Tb_Portfólio[[#This Row],[Hoje]],"Atrasado ou Crítico",IF(Tb_Portfólio[[#This Row],[% EXECUTADO]]=0,"Autorizado",IF(Tb_Portfólio[[#This Row],[MEDIÇÃO DE STATUS]]>=95%,"No prazo",IF(Tb_Portfólio[[#This Row],[MEDIÇÃO DE STATUS]]<85%,"Atrasado ou Crítico",IF(Tb_Portfólio[[#This Row],[MEDIÇÃO DE STATUS]]<=95%,"Em atenção")))))) -> No prazo | W36: =IFERROR(Tb_Portfólio[[#This Row],[% EXECUTADO]]/Tb_Portfólio[[#This Row],[% PREVISTO]],0) -> 0.97619048 | X36: Levantar as informações necessárias e criação de fluxo padronizado para monitoramento dos Cumprdecs Realizar ajustes na ferramenta já existente para que seja possível utilizar o fluxo desenvolvido Realizar piloto para análise do fluxo padronizado e do sistema SNMC pelas unidades e pelos tribunais Capacitar os servidores do CNJ e dos tribunais/conselhos que usarão o SNMC. Adesões dos tribunais e conselhos do Poder Judiciário Disponibilizar as informações coletadas no Cumprdec | AB36: Dr. Marcel da Silva Augusto Corrêa | AC36: SG - Secretaria Geral | AD36: • Padronização do fluxo do monitoramento dos atos normativos. • Transparência das informações obtidas nos Cumprdec. • Aperfeiçoamento e centralização do monitoramento e avaliação do cumprimento dos Normativos | AF36: =TODAY() -> 46176 | AG36: Igor Guimarães Pedreira | AH36: DTI - Departamento de Tecnologia da Informação e Comunicação | AJ36: =2024&Tb_Portfólio[[#This Row],[SEI]] -> 202404137/2024 | AK36: =IFERROR(IF(MATCH(AJ36,Atualizações!$P$1:$P$1265,0)>0, "Sim"), "Não") -> Sim | AL36: =2025&Tb_Portfólio[[#This Row],[SEI]] -> 202504137/2024 | AM36: =IFERROR(IF(MATCH(AL36,Atualizações!$P$1:$P$2994,0)>0, "Sim"), "Não") -> Sim | AN36: =2026&Tb_Portfólio[[#This Row],[SEI]] -> 202604137/2024 | AO36: =IFERROR(IF(MATCH(AN36,Atualizações!$P$1:$P$2994,0)>0, "Sim"), "Não") -> Sim | AP36: =_xlfn.XLOOKUP(Tb_Portfólio[[#This Row],[SEI]],Tb_Atualizações[PROCESSO SEI],Tb_Atualizações[Explicações],"",0,-1) -> Data de término atualizada de julho de 2026 para setembro de 2026 devido à necessidade de ajustar o MVP do painel. É esperado que a data de término ainda sofra novas mudanças, tendo em vista que o projeto prevê a criação de novos painéis, os quais ainda não tiveram seu planejamento iniciado. | AQ36: =_xlfn.XLOOKUP(Tb_Portfólio[[#This Row],[SEI]],Tb_Mapa[SEI],Tb_Mapa[CONSULTOR RESPONSÁVEL],"",0,-1) -> Tony
A37: 04751/2022 | B37: CODEX - Melhorias Evolutivas e Corretivas | C37: O projeto visa implementar melhorias evolutivas, correções e novas funcionalidades na plataforma Codex | E37: Dr. Dorotheo Barbosa Neto | F37: SEP - Secretaria de Estratégia e Projetos | G37: Marcos Cardoso | H37: PNUD | I37: 09. Fomentar e incrementar a produção de soluções tecnológicas, com foco em inovação e transformação digital | J37: 12. Fortalecimento da estratégia nacional de TIC e de proteção de dados; e 03. Agilidade e produtividade na prestação jurisdicional | K37: Programa Justiça 4.0 - Eixo Inovação e Tecnologia (soluções disruptivas para transformar o Judiciário e melhorar a prestação de serviços a toda sociedade). O projeto também apoia a Resolução CNJ N. 335/2020, que institui uma política pública de governança e gestão do processo judicial eletrônico, integrando os tribunais por meio da Plataforma Digital do Poder Judiciário Brasileiro (PDPJ-Br), mantendo o PJe como sistema prioritário do CNJ." | L37: 44673 | M37: 46387 | N37: =_xlfn.XLOOKUP(Tb_Portfólio[[#This Row],[SEI]],Tb_Atualizações[PROCESSO SEI],Tb_Atualizações[% PREVISTO],"",0,-1) -> 0.86 | O37: =_xlfn.XLOOKUP(Tb_Portfólio[[#This Row],[SEI]],Tb_Atualizações[PROCESSO SEI],Tb_Atualizações[% EXECUTADO],"",0,-1) -> 0.86 | P37: =IFERROR(Tb_Portfólio[[#This Row],[% EXECUTADO]]/Tb_Portfólio[[#This Row],[% PREVISTO]],"0%") -> 1 | Q37: =_xlfn.XLOOKUP(Tb_Portfólio[[#This Row],[SEI]],Tb_Atualizações[PROCESSO SEI],Tb_Atualizações[DATA DE ATUALIZAÇÃO],"",0,-1) -> 46137 | R37: =_xlfn.XLOOKUP(Tb_Portfólio[[#This Row],[SEI]],Tb_Atualizações[PROCESSO SEI],Tb_Atualizações[Mês],,0,-1) -> 46143 | T37: Justiça 4.0 | U37: =IF(Tb_Portfólio[[#This Row],[% EXECUTADO]]=100%,"Finalizado",IF(Tb_Portfólio[[#This Row],[PREVISÃO DE TERMINO]]<Tb_Portfólio[[#This Row],[Hoje]],"Atrasado ou Crítico",IF(Tb_Portfólio[[#This Row],[% EXECUTADO]]=0,"Autorizado",IF(Tb_Portfólio[[#This Row],[MEDIÇÃO DE STATUS]]>=95%,"No prazo",IF(Tb_Portfólio[[#This Row],[MEDIÇÃO DE STATUS]]<85%,"Atrasado ou Crítico",IF(Tb_Portfólio[[#This Row],[MEDIÇÃO DE STATUS]]<=95%,"Em atenção")))))) -> No prazo | W37: =IFERROR(Tb_Portfólio[[#This Row],[% EXECUTADO]]/Tb_Portfólio[[#This Row],[% PREVISTO]],0) -> 1 | Y37: 4803533.7 | AA37: https://www.cnj.jus.br/tecnologia-da-informacao-e-comunicacao/justica-4-0/ | AB37: Dr. João Thiago de França Guerra | AC37: DTI - Departamento de Tecnologia da Informação e Comunicação | AD37: BENEFÍCIO 1 - Melhoria da estabilidade e Evolução do Codex. | AE37: ENCERRAMENTO DOS EPICOS: •P48 - Integração com Datajud •P45 - Melhorias de Segurança •P44 - Integração do Portal de Serviço •P34 – Latência •P41 - Manutenção/Correção de Bugs •P21 - Esta s ca e Monitoramento •P23 – Observabilidade •P42 - Indicadores | AF37: =TODAY() -> 46176 | AG37: Jairo Simão Santana Melo | AH37: DTI - Departamento de Tecnologia da Informação e Comunicação | AJ37: =2024&Tb_Portfólio[[#This Row],[SEI]] -> 202404751/2022 | AK37: =IFERROR(IF(MATCH(AJ37,Atualizações!$P$1:$P$1265,0)>0, "Sim"), "Não") -> Não | AL37: =2025&Tb_Portfólio[[#This Row],[SEI]] -> 202504751/2022 | AM37: =IFERROR(IF(MATCH(AL37,Atualizações!$P$1:$P$2994,0)>0, "Sim"), "Não") -> Sim | AN37: =2026&Tb_Portfólio[[#This Row],[SEI]] -> 202604751/2022 | AO37: =IFERROR(IF(MATCH(AN37,Atualizações!$P$1:$P$2994,0)>0, "Sim"), "Não") -> Sim | AP37: =_xlfn.XLOOKUP(Tb_Portfólio[[#This Row],[SEI]],Tb_Atualizações[PROCESSO SEI],Tb_Atualizações[Explicações],"",0,-1) -> Entregas realizadas: • Atualização para a versão Backend 1.62.0 com várias correções e ajustes realizados. • Manutenção e correção de vários Bugs detectados. • Melhorias voltadas para a criação solução para atualização de Órgão Julgador. • Verificar volume de mensagens suspensas. • TJMS(SAJ) carga de arquivo. Entregas planejadas para o próximo mês: • Correção de Inconsistências na integração CODEX x SISPREQ. • Ajustar comportamento do botão limpar na listagem de mensagens. • Desabilitar JOB atualização. Outros fatos relevantes a registrar: • Suporte aos tribunais quanto ao Prêmio de Qualidade CNJ.. • Inclusão do ProcessoCompilado no S3 do Data Lake. Em fase final. • Acessos, SSO e incidentes de autenticação. • Desabilitado o JOB de Sincronismo CNPJS e CPFS | AQ37: =_xlfn.XLOOKUP(Tb_Portfólio[[#This Row],[SEI]],Tb_Mapa[SEI],Tb_Mapa[CONSULTOR RESPONSÁVEL],"",0,-1) -> Raphael
A38: 05138/2024 | B38: Consulta Nacional de Pessoas (FAC Nacional) | C38: Desenvolver serviço estruturante de busca nacional de pessoas para o Portal de Serviços, o qual possibilitará a identificação de todos os processos judiciais, bem como informações constantes nas bases de dados da Polícia Federal, a partir da inserção de dados pessoais como cpf, nome da mãe, número da OAB, dentre outros. | E38: Dr. Dorotheo Barbosa Neto | F38: SEP - Secretaria de Estratégia e Projetos | G38: Bruno Cezar Andrade de Souza | H38: SEP - Secretaria de Estratégia e Projetos | I38: 07. Fomentar e fortalecer a atuação interinstitucional do CNJ para garantir os direitos dos cidadãos | J38: 08. Aperfeiçoamento da gestão da justiça criminal | K38: Resolução 335 /2020 Justiça 4.0 | L38: 45404 | M38: 45993 | N38: =_xlfn.XLOOKUP(Tb_Portfólio[[#This Row],[SEI]],Tb_Atualizações[PROCESSO SEI],Tb_Atualizações[% PREVISTO],"",0,-1) -> 0.67 | O38: =_xlfn.XLOOKUP(Tb_Portfólio[[#This Row],[SEI]],Tb_Atualizações[PROCESSO SEI],Tb_Atualizações[% EXECUTADO],"",0,-1) -> 0.67 | P38: =IFERROR(Tb_Portfólio[[#This Row],[% EXECUTADO]]/Tb_Portfólio[[#This Row],[% PREVISTO]],"0%") -> 1 | Q38: =_xlfn.XLOOKUP(Tb_Portfólio[[#This Row],[SEI]],Tb_Atualizações[PROCESSO SEI],Tb_Atualizações[DATA DE ATUALIZAÇÃO],"",0,-1) -> 45920 | R38: =_xlfn.XLOOKUP(Tb_Portfólio[[#This Row],[SEI]],Tb_Atualizações[PROCESSO SEI],Tb_Atualizações[Mês],,0,-1) -> 45870 | U38: Finalizado | W38: =IFERROR(Tb_Portfólio[[#This Row],[% EXECUTADO]]/Tb_Portfólio[[#This Row],[% PREVISTO]],0) -> 1 | X38: Relatório contendo todos os processos judiciais relacionados à pessoa pesquisada Painel amigável possibilitando ao usuário pesquisar dados relacionados a pessoas e aplicar filtros APIs criadas; Acesso aos dados de pessoas existente na base de dados da Polícia Federal Criação de vínculos entre dados que se referem a uma mesma pessoa, mesmo que tenham nome e documentos diferentes; Acesso à Folha de Antecedentes Criminais da Polícia Federal Regras negociais definidas; Perfis de acesso definidos; Folha de Antecedentes Criminais, contendo dados do SINIC e dos quatro grandes repositórios do CNJ, disponibilizada | AA38: https://www.cnj.jus.br/tecnologia-da-informacao-e-comunicacao/justica-4-0/ | AB38: Dr. Dorotheo Barbosa Neto | AC38: SEP - Secretaria de Estratégia e Projetos | AD38: 1 - Disponibilização dos dados sobre antecedentes criminais de todos os tribunais e da polícia federal em um único local. | AF38: =TODAY() -> 46176 | AG38: Thiago de Andrade Vieira | AH38: DTI - Departamento de Tecnologia da Informação e Comunicação | AJ38: =2024&Tb_Portfólio[[#This Row],[SEI]] -> 202405138/2024 | AK38: =IFERROR(IF(MATCH(AJ38,Atualizações!$P$1:$P$1265,0)>0, "Sim"), "Não") -> Sim | AL38: =2025&Tb_Portfólio[[#This Row],[SEI]] -> 202505138/2024 | AM38: =IFERROR(IF(MATCH(AL38,Atualizações!$P$1:$P$2994,0)>0, "Sim"), "Não") -> Sim | AN38: =2026&Tb_Portfólio[[#This Row],[SEI]] -> 202605138/2024 | AO38: =IFERROR(IF(MATCH(AN38,Atualizações!$P$1:$P$2994,0)>0, "Sim"), "Não") -> Não | AP38: =_xlfn.XLOOKUP(Tb_Portfólio[[#This Row],[SEI]],Tb_Atualizações[PROCESSO SEI],Tb_Atualizações[Explicações],"",0,-1) -> Projeto dado como finalizado parcialmente. O resto do escopo será concluído no projeto "API de Pessoas", em execução no programa justiça 4.0. Necessário que o TEP deste projeto tenha essa informação. | AQ38: =_xlfn.XLOOKUP(Tb_Portfólio[[#This Row],[SEI]],Tb_Mapa[SEI],Tb_Mapa[CONSULTOR RESPONSÁVEL],"",0,-1) -> Tony
A39: 05150/2024 | B39: 7ª Edição da Série Justiça Pesquisa - Exercício 2024/2025 | C39: Contratação e realização de pesquisas empíricas no tema “Diagnóstico sobre o Enfrentamento de Litigância Predatória no Poder Judiciário”. | E39: Dra. Lívia Cristina Marques Peres | F39: SEP - Secretaria de Estratégia e Projetos | G39: Gabriela Moreira de Azevedo Soares | H39: DPJ - Departamento de Pesquisas Judiciárias | I39: 01. Desenvolver políticas judiciárias e outros instrumentos para o aperfeiçoamento das atividades dos órgãos do Poder Judiciário e dos seus serviços auxiliares e dos serviços notariais e de registro, e dos demais órgãos correicionais | J39: 02. Fortalecimento da Relação Institucional do Judiciário com a Sociedade | K39: - | L39: 45401 | M39: 46011 | N39: =_xlfn.XLOOKUP(Tb_Portfólio[[#This Row],[SEI]],Tb_Atualizações[PROCESSO SEI],Tb_Atualizações[% PREVISTO],"",0,-1) -> 1 | O39: =_xlfn.XLOOKUP(Tb_Portfólio[[#This Row],[SEI]],Tb_Atualizações[PROCESSO SEI],Tb_Atualizações[% EXECUTADO],"",0,-1) -> 1 | P39: =IFERROR(Tb_Portfólio[[#This Row],[% EXECUTADO]]/Tb_Portfólio[[#This Row],[% PREVISTO]],"0%") -> 1 | Q39: =_xlfn.XLOOKUP(Tb_Portfólio[[#This Row],[SEI]],Tb_Atualizações[PROCESSO SEI],Tb_Atualizações[DATA DE ATUALIZAÇÃO],"",0,-1) -> 46011 | R39: =_xlfn.XLOOKUP(Tb_Portfólio[[#This Row],[SEI]],Tb_Atualizações[PROCESSO SEI],Tb_Atualizações[Mês],,0,-1) -> 45992 | U39: =IF(Tb_Portfólio[[#This Row],[% EXECUTADO]]=100%,"Finalizado",IF(Tb_Portfólio[[#This Row],[PREVISÃO DE TERMINO]]<Tb_Portfólio[[#This Row],[Hoje]],"Atrasado ou Crítico",IF(Tb_Portfólio[[#This Row],[% EXECUTADO]]=0,"Autorizado",IF(Tb_Portfólio[[#This Row],[MEDIÇÃO DE STATUS]]>=95%,"No prazo",IF(Tb_Portfólio[[#This Row],[MEDIÇÃO DE STATUS]]<85%,"Atrasado ou Crítico",IF(Tb_Portfólio[[#This Row],[MEDIÇÃO DE STATUS]]<=95%,"Em atenção")))))) -> Finalizado | W39: =IFERROR(Tb_Portfólio[[#This Row],[% EXECUTADO]]/Tb_Portfólio[[#This Row],[% PREVISTO]],0) -> 1 | X39: - Contratação das empresas - Realização da(s) Pesquisa (s) - Publicação e divulgação final | AB39: Dra. Lívia Cristina Marques Peres | AC39: DPJ - Departamento de Pesquisas Judiciárias | AD39: Diagnóstico sobre o Enfrentamento de Litigância Predatória no Poder Judiciário | AF39: =TODAY() -> 46176 | AJ39: =2024&Tb_Portfólio[[#This Row],[SEI]] -> 202405150/2024 | AK39: =IFERROR(IF(MATCH(AJ39,Atualizações!$P$1:$P$1265,0)>0, "Sim"), "Não") -> Sim | AL39: =2025&Tb_Portfólio[[#This Row],[SEI]] -> 202505150/2024 | AM39: =IFERROR(IF(MATCH(AL39,Atualizações!$P$1:$P$2994,0)>0, "Sim"), "Não") -> Sim | AN39: =2026&Tb_Portfólio[[#This Row],[SEI]] -> 202605150/2024 | AO39: =IFERROR(IF(MATCH(AN39,Atualizações!$P$1:$P$2994,0)>0, "Sim"), "Não") -> Não | AP39: =_xlfn.XLOOKUP(Tb_Portfólio[[#This Row],[SEI]],Tb_Atualizações[PROCESSO SEI],Tb_Atualizações[Explicações],"",0,-1) -> Em conversa com a Dani no dia 14/1, fui informado de que o projeto foi concluído com sucesso no dia 18/12. Combinei com ela que o projeto seria finalizado na nossa base, mas ficamos no aguardo do TEP. | AQ39: =_xlfn.XLOOKUP(Tb_Portfólio[[#This Row],[SEI]],Tb_Mapa[SEI],Tb_Mapa[CONSULTOR RESPONSÁVEL],"",0,-1) -> Igor
A40: 05578/2024 | B40: Conecta | C40: Monitoramento de conformidades na integração de sistemas legados à PDPJ-BR e na produção de novas soluções. | E40: Dr. Alexandre Libonati de Abreu | F40: DTI - Departamento de Tecnologia da Informação e Comunicação | G40: Cesar Henrique de Oliveira Pereira | H40: PNUD | I40: 09. Fomentar e incrementar a produção de soluções tecnológicas, com foco em inovação e transformação digital | J40: 09. Aperfeiçoamento da gestão administrativa e da governança judiciária | K40: Programa Justiça 4.0 (Projeto BRA/20/003) | L40: 45425 | M40: 31/12/2026 | N40: =_xlfn.XLOOKUP(Tb_Portfólio[[#This Row],[SEI]],Tb_Atualizações[PROCESSO SEI],Tb_Atualizações[% PREVISTO],"",0,-1) -> 0.76 | O40: =_xlfn.XLOOKUP(Tb_Portfólio[[#This Row],[SEI]],Tb_Atualizações[PROCESSO SEI],Tb_Atualizações[% EXECUTADO],"",0,-1) -> 0.64 | P40: =IFERROR(Tb_Portfólio[[#This Row],[% EXECUTADO]]/Tb_Portfólio[[#This Row],[% PREVISTO]],"0%") -> 0.84210526 | Q40: =_xlfn.XLOOKUP(Tb_Portfólio[[#This Row],[SEI]],Tb_Atualizações[PROCESSO SEI],Tb_Atualizações[DATA DE ATUALIZAÇÃO],"",0,-1) -> 46167 | R40: =_xlfn.XLOOKUP(Tb_Portfólio[[#This Row],[SEI]],Tb_Atualizações[PROCESSO SEI],Tb_Atualizações[Mês],,0,-1) -> 46143 | T40: Justiça 4.0 | U40: =IF(Tb_Portfólio[[#This Row],[% EXECUTADO]]=100%,"Finalizado",IF(Tb_Portfólio[[#This Row],[PREVISÃO DE TERMINO]]<Tb_Portfólio[[#This Row],[Hoje]],"Atrasado ou Crítico",IF(Tb_Portfólio[[#This Row],[% EXECUTADO]]=0,"Autorizado",IF(Tb_Portfólio[[#This Row],[MEDIÇÃO DE STATUS]]>=95%,"No prazo",IF(Tb_Portfólio[[#This Row],[MEDIÇÃO DE STATUS]]<85%,"Atrasado ou Crítico",IF(Tb_Portfólio[[#This Row],[MEDIÇÃO DE STATUS]]<=95%,"Em atenção")))))) -> Atrasado ou Crítico | W40: =IFERROR(Tb_Portfólio[[#This Row],[% EXECUTADO]]/Tb_Portfólio[[#This Row],[% PREVISTO]],0) -> 0.84210526 | X40: - Inventário Preliminar de Soluções e Levantamento dos Planos Estratégicos dos Tribunais - Implantação do Processo de Monitoramento - Implantação do Processo de Monitoramento para soluções nacionalizadas - Definição e Operacionalização do sistema de monitoramento de conformidades - Identificação de inciativas e Implantação de framework de mentoria - Mentoria de soluções de inovação a serem nacionalizadas - Transferência de Conhecimento para DTI e Termo de Encerramento aprovado | AA40: https://www.cnj.jus.br/tecnologia-da-informacao-e-comunicacao/justica-4-0/ | AB40: Dr. José Faustino Macedo de Souza Ferreira (Juiz de Direito do Tribunal de Justiça do Estado de Pernambuco ) | AC40: DTI - Departamento de Tecnologia da Informação e Comunicação | AD40: Nacionalização de sistemas processuais passíveis de compartilhamento pelos órgãos do Poder Judiciário | AF40: =TODAY() -> 46176 | AG40: Flávio Feitosa | AH40: DTI - Departamento de Tecnologia da Informação e Comunicação | AJ40: =2024&Tb_Portfólio[[#This Row],[SEI]] -> 202405578/2024 | AK40: =IFERROR(IF(MATCH(AJ40,Atualizações!$P$1:$P$1265,0)>0, "Sim"), "Não") -> Sim | AL40: =2025&Tb_Portfólio[[#This Row],[SEI]] -> 202505578/2024 | AM40: =IFERROR(IF(MATCH(AL40,Atualizações!$P$1:$P$2994,0)>0, "Sim"), "Não") -> Sim | AN40: =2026&Tb_Portfólio[[#This Row],[SEI]] -> 202605578/2024 | AO40: =IFERROR(IF(MATCH(AN40,Atualizações!$P$1:$P$2994,0)>0, "Sim"), "Não") -> Sim | AP40: =_xlfn.XLOOKUP(Tb_Portfólio[[#This Row],[SEI]],Tb_Atualizações[PROCESSO SEI],Tb_Atualizações[Explicações],"",0,-1) -> 0 | AQ40: =_xlfn.XLOOKUP(Tb_Portfólio[[#This Row],[SEI]],Tb_Mapa[SEI],Tb_Mapa[CONSULTOR RESPONSÁVEL],"",0,-1) -> Tony
A41: 06767/2022 | B41: Diagnóstico sobre a otimização dos processos de trabalho no Poder Judiciário em face da implementação das Políticas Tecnológicas do Programa Justiça 4.0. | C41: Desenvolver, junto ao universo de 86 tribunais, um estudo diagnóstico sobre a modernização e otimização das estruturas, processos e procedimentos internos instalados nesses órgãos em face da implementação das políticas tecnológicas: Núcleos de Justiça 4.0, Balcão Virtual e Juízo 100% Digital. | E41: Dr. Dorotheo Barbosa Neto | F41: SEP - Secretaria de Estratégia e Projetos | G41: Gustavo Martins Pereira | H41: PNUD | I41: 01. Desenvolver políticas judiciárias e outros instrumentos para o aperfeiçoamento das atividades dos órgãos do Poder Judiciário e dos seus serviços auxiliares e dos serviços notariais e de registro, e dos demais órgãos correicionais | J41: 09. Aperfeiçoamento da gestão administrativa e da governança judiciária | K41: Resolução 335 /2020 Justiça 4.0 | L41: 45161 | M41: 45605 | N41: =_xlfn.XLOOKUP(Tb_Portfólio[[#This Row],[SEI]],Tb_Atualizações[PROCESSO SEI],Tb_Atualizações[% PREVISTO],"",0,-1) -> 1 | O41: =_xlfn.XLOOKUP(Tb_Portfólio[[#This Row],[SEI]],Tb_Atualizações[PROCESSO SEI],Tb_Atualizações[% EXECUTADO],"",0,-1) -> 1 | P41: =IFERROR(Tb_Portfólio[[#This Row],[% EXECUTADO]]/Tb_Portfólio[[#This Row],[% PREVISTO]],"0%") -> 1 | Q41: =_xlfn.XLOOKUP(Tb_Portfólio[[#This Row],[SEI]],Tb_Atualizações[PROCESSO SEI],Tb_Atualizações[DATA DE ATUALIZAÇÃO],"",0,-1) -> 45608 | R41: =_xlfn.XLOOKUP(Tb_Portfólio[[#This Row],[SEI]],Tb_Atualizações[PROCESSO SEI],Tb_Atualizações[Mês],,0,-1) -> 45597 | T41: Justiça 4.0 | U41: =IF(Tb_Portfólio[[#This Row],[% EXECUTADO]]=100%,"Finalizado",IF(Tb_Portfólio[[#This Row],[PREVISÃO DE TERMINO]]<Tb_Portfólio[[#This Row],[Hoje]],"Atrasado ou Crítico",IF(Tb_Portfólio[[#This Row],[% EXECUTADO]]=0,"Autorizado",IF(Tb_Portfólio[[#This Row],[MEDIÇÃO DE STATUS]]>=95%,"No prazo",IF(Tb_Portfólio[[#This Row],[MEDIÇÃO DE STATUS]]<85%,"Atrasado ou Crítico",IF(Tb_Portfólio[[#This Row],[MEDIÇÃO DE STATUS]]<=95%,"Em atenção")))))) -> Finalizado | W41: =IFERROR(Tb_Portfólio[[#This Row],[% EXECUTADO]]/Tb_Portfólio[[#This Row],[% PREVISTO]],0) -> 1 | X41: 1 - Elaboração e validação da metodologia; 2 - Testar a metodologia aplicando o diagnóstico piloto em três tribunais; 3 - Ampliar a aplicação do Diagnóstico em 83 tribunais; 4 - Estruturação das evidências levantas pelo diagnóstico; 5 - Diagnóstico - Textos dos capítulos de a) introdução; b) metodologia da pesquisa diagnóstica, fundamentação para a escolha das hipóteses; e c) contextualização; 6 - Diagnóstico - Capítulo de análise técnica que contenha a análise descritiva dos dados quantitativos previamente produzidos pelas equipes do CNJ e do PNUD; 7 - Diagnóstico - Análise descritiva referente às testagens das hipóteses do projeto; 8 - Diagnóstico - Relatório consolidado, contemplando os documentos produzidos nos Produtos 1, 2, 3 e 4 e com capítulo conclusivo que apresente síntese dos principais resultados encontrados e sugestões de recomendações desenvolvidas com base no diagnóstico; 9 - Diagnóstico - Sumário Executivo com resumo dos principais resultados encontrados nos produtos 1 a 4, bem como apresentando boas práticas; 10 - Exames estatísticos relativos à testagem das hipóteses 1 e 2 do estudo; 11 - Exames estatísticos relativos à testagem das hipóteses 3 e 4 do estudo; 12 - Exames estatísticos relativos à testagem das hipóteses 5 e 6 do estudo; 13 - Apresentação do relatório do diagnóstico. | AA41: https://www.cnj.jus.br/tecnologia-da-informacao-e-comunicacao/justica-4-0/ | AB41: Dr. Dorotheo Barbosa Neto | AC41: SEP - Secretaria de Estratégia e Projetos | AD41: Análise das evidências do estudo acerca da efetividade, eficiência e economicidade da prestação jurisdicional, em face a implementação do Balcão Virtual, do Núcleo de Justiça 4.0 e do Juízo 100% Digital nos tribunais | AE41: • Elaboração e validação da metodologia • Testar a metodologia aplicando o diagnóstico piloto em três tribunais • Ampliar a aplicação do Diagnóstico em 83 tribunais • Estruturação das evidências levantas pelo diagnóstico • Diagnóstico - Textos dos capítulos de a) introdução; b) metodologia da pesquisa diagnóstica, fundamentação para a escolha das hipóteses; e c) contextualização • Diagnóstico - Capítulo de análise técnica que contenha a análise descritiva dos dados quantitativos previamente produzidos pelas equipes do CNJ e do PNUD • Diagnóstico - Capítulo de análise descritiva dos dados quantitativos previamente produzidos pelas equipes do CNJ e do PNUD • Diagnóstico - Análise descritiva referente às testagens das hipóteses do projeto • Diagnóstico - Relatório consolidado, contemplando os documentos produzidos nos Produtos 1, 2, 3 e 4 e com capítulo conclusivo que apresente síntese dos principais resultados encontrados e sugestões de recomendações desenvolvidas com base no diagnóstico. • Diagnóstico - Sumário Executivo com resumo dos principais resultados encontrados nos produtos 1 a 4, bem como apresentando boas práticas. • Exames estatísticos relativos à testagem das hipóteses 1 e 2 do estudo • Exames estatísticos relativos à testagem das hipóteses 3 e 4 do estudo • Exames estatísticos relativos à testagem das hipóteses 5 e 6 do estudo • Apresentação do relatório do diagnóstico | AF41: =TODAY() -> 46176 | AG41: Gabriela Moreira de Azevedo Soares | AH41: DPJ - Departamento de Pesquisas Judiciárias | AJ41: =2024&Tb_Portfólio[[#This Row],[SEI]] -> 202406767/2022 | AK41: =IFERROR(IF(MATCH(AJ41,Atualizações!$P$1:$P$1265,0)>0, "Sim"), "Não") -> Sim | AL41: =2025&Tb_Portfólio[[#This Row],[SEI]] -> 202506767/2022 | AM41: =IFERROR(IF(MATCH(AL41,Atualizações!$P$1:$P$2994,0)>0, "Sim"), "Não") -> Não | AN41: =2026&Tb_Portfólio[[#This Row],[SEI]] -> 202606767/2022 | AO41: =IFERROR(IF(MATCH(AN41,Atualizações!$P$1:$P$2994,0)>0, "Sim"), "Não") -> Não | AP41: =_xlfn.XLOOKUP(Tb_Portfólio[[#This Row],[SEI]],Tb_Atualizações[PROCESSO SEI],Tb_Atualizações[Explicações],"",0,-1) -> 0 | AQ41: =_xlfn.XLOOKUP(Tb_Portfólio[[#This Row],[SEI]],Tb_Mapa[SEI],Tb_Mapa[CONSULTOR RESPONSÁVEL],"",0,-1) -> Igor/Finalizado
A42: 06826/2024 | B42: Sniper BC | C42: Projeto para construção do Sniper BC, que disponibilizará informações de novas bases de acesso restrito pelo poder judiciário, possibilitando ao usuário realize pesquisas de ativos e pedidos judiciais de bloqueio e constrição de bens nesses sistemas de forma integrada, aumentando a eficiência e eficácia jurisdicional nessas atividades | E42: Dr. Dorotheo Barbosa Neto | F42: SEP - Secretaria de Estratégia e Projetos | G42: Carlo Borsoi Moura | H42: PNUD | I42: 13. Estimular a desburocratização no Poder Judiciário | J42: 03. Agilidade e produtividade na prestação jurisdicional | K42: Programa Justiça 4.0 (Projeto BRA/20/003) | L42: 45504 | M42: 46281 | N42: =_xlfn.XLOOKUP(Tb_Portfólio[[#This Row],[SEI]],Tb_Atualizações[PROCESSO SEI],Tb_Atualizações[% PREVISTO],"",0,-1) -> 0.86 | O42: =_xlfn.XLOOKUP(Tb_Portfólio[[#This Row],[SEI]],Tb_Atualizações[PROCESSO SEI],Tb_Atualizações[% EXECUTADO],"",0,-1) -> 0.76 | P42: =IFERROR(Tb_Portfólio[[#This Row],[% EXECUTADO]]/Tb_Portfólio[[#This Row],[% PREVISTO]],"0%") -> 0.88372093 | Q42: =_xlfn.XLOOKUP(Tb_Portfólio[[#This Row],[SEI]],Tb_Atualizações[PROCESSO SEI],Tb_Atualizações[DATA DE ATUALIZAÇÃO],"",0,-1) -> 46167 | R42: =_xlfn.XLOOKUP(Tb_Portfólio[[#This Row],[SEI]],Tb_Atualizações[PROCESSO SEI],Tb_Atualizações[Mês],,0,-1) -> 46143 | T42: Justiça 4.0 | U42: =IF(Tb_Portfólio[[#This Row],[% EXECUTADO]]=100%,"Finalizado",IF(Tb_Portfólio[[#This Row],[PREVISÃO DE TERMINO]]<Tb_Portfólio[[#This Row],[Hoje]],"Atrasado ou Crítico",IF(Tb_Portfólio[[#This Row],[% EXECUTADO]]=0,"Autorizado",IF(Tb_Portfólio[[#This Row],[MEDIÇÃO DE STATUS]]>=95%,"No prazo",IF(Tb_Portfólio[[#This Row],[MEDIÇÃO DE STATUS]]<85%,"Atrasado ou Crítico",IF(Tb_Portfólio[[#This Row],[MEDIÇÃO DE STATUS]]<=95%,"Em atenção")))))) -> Em atenção | W42: =IFERROR(Tb_Portfólio[[#This Row],[% EXECUTADO]]/Tb_Portfólio[[#This Row],[% PREVISTO]],0) -> 0.88372093 | AA42: https://www.cnj.jus.br/tecnologia-da-informacao-e-comunicacao/justica-4-0/ | AB42: Dr. Dorotheo Barbosa Neto | AC42: SEP - Secretaria de Estratégia e Projetos | AD42: Benefício 1 - Ampliação das bases de informação Benefício 2 - Plataforma integrada de busca e constrição | AE42: • Revisões e melhorias no código implementado • Ajustes funcionais e validações no módulo de bloqueio • Revisão de materiais de capacitação • Avanços técnicos decorrentes de alinhamentos com stakeholders institucionais | AF42: =TODAY() -> 46176 | AG42: Francisco Gonçalves de Araújo Filho | AH42: DTI - Departamento de Tecnologia da Informação e Comunicação | AJ42: =2024&Tb_Portfólio[[#This Row],[SEI]] -> 202406826/2024 | AK42: =IFERROR(IF(MATCH(AJ42,Atualizações!$P$1:$P$1265,0)>0, "Sim"), "Não") -> Sim | AL42: =2025&Tb_Portfólio[[#This Row],[SEI]] -> 202506826/2024 | AM42: =IFERROR(IF(MATCH(AL42,Atualizações!$P$1:$P$2994,0)>0, "Sim"), "Não") -> Sim | AN42: =2026&Tb_Portfólio[[#This Row],[SEI]] -> 202606826/2024 | AO42: =IFERROR(IF(MATCH(AN42,Atualizações!$P$1:$P$2994,0)>0, "Sim"), "Não") -> Sim | AP42: =_xlfn.XLOOKUP(Tb_Portfólio[[#This Row],[SEI]],Tb_Atualizações[PROCESSO SEI],Tb_Atualizações[Explicações],"",0,-1) -> Entregas realizadas • Produto 6 -Implantação da integração base de dados da SERP/ONR  Roteiro aprovado  Envio parcial dos vídeos • Produto 9 –Protótipo das Melhorias Evolutivas  Reunião de aprovação com magistrados em  Envio da documentação de requisitos e arquitetura Entregas planejadas para o próximo mês • SNIPERBC-42 Produto 10–Implantação das Melhorias Evolutivas  Relatório descritivo sobre sistema implementado em ambiente de homologação e produção  Relatório descritivo acerca da conclusão da disponibilização de acesso via API  Relatório de testes Outros fatos relevantes a registrar • Limitação de acesso às partes impedem de usar o Sniper para alguns processos e isto tem acontecido com alguns vindos do Datalake( provavelmente sigilosos ). • Chamados abertos para o Sniper mas são limitações de acesso às partes do processo no Datalake. | AQ42: =_xlfn.XLOOKUP(Tb_Portfólio[[#This Row],[SEI]],Tb_Mapa[SEI],Tb_Mapa[CONSULTOR RESPONSÁVEL],"",0,-1) -> Tony
A43: 07855/2022 | B43: Sensibilização e Formação em Integridade e Compliance no Poder Judiciário | C43: Estimular, por meio de ações de sensibilização e de formação de gestores e servidores, a implantação de programas de integridade e compliance no Poder Judiciário. | E43: Dr. Gabriel Da Silveira Matos | F43: SEP - Secretaria de Estratégia e Projetos | G43: Claudia Lopes Correa | H43: PNUD | I43: 16. Aperfeiçoar políticas e práticas de Gestão de Pessoas | J43: 10. Aperfeiçoamento da gestão de pessoas | K43: Resolução 335 /2020 Justiça 4.0 | L43: 44487 | M43: 45412 | N43: =_xlfn.XLOOKUP(Tb_Portfólio[[#This Row],[SEI]],Tb_Atualizações[PROCESSO SEI],Tb_Atualizações[% PREVISTO],"",0,-1) -> 0.5 | O43: =_xlfn.XLOOKUP(Tb_Portfólio[[#This Row],[SEI]],Tb_Atualizações[PROCESSO SEI],Tb_Atualizações[% EXECUTADO],"",0,-1) -> 1 | P43: =IFERROR(Tb_Portfólio[[#This Row],[% EXECUTADO]]/Tb_Portfólio[[#This Row],[% PREVISTO]],"0%") -> 2 | Q43: =_xlfn.XLOOKUP(Tb_Portfólio[[#This Row],[SEI]],Tb_Atualizações[PROCESSO SEI],Tb_Atualizações[DATA DE ATUALIZAÇÃO],"",0,-1) -> 45412 | R43: =_xlfn.XLOOKUP(Tb_Portfólio[[#This Row],[SEI]],Tb_Atualizações[PROCESSO SEI],Tb_Atualizações[Mês],,0,-1) -> 45383 | T43: Justiça 4.0 | U43: =IF(Tb_Portfólio[[#This Row],[% EXECUTADO]]=100%,"Finalizado",IF(Tb_Portfólio[[#This Row],[PREVISÃO DE TERMINO]]<Tb_Portfólio[[#This Row],[Hoje]],"Atrasado ou Crítico",IF(Tb_Portfólio[[#This Row],[% EXECUTADO]]=0,"Autorizado",IF(Tb_Portfólio[[#This Row],[MEDIÇÃO DE STATUS]]>=95%,"No prazo",IF(Tb_Portfólio[[#This Row],[MEDIÇÃO DE STATUS]]<85%,"Atrasado ou Crítico",IF(Tb_Portfólio[[#This Row],[MEDIÇÃO DE STATUS]]<=95%,"Em atenção")))))) -> Finalizado | W43: =IFERROR(Tb_Portfólio[[#This Row],[% EXECUTADO]]/Tb_Portfólio[[#This Row],[% PREVISTO]],0) -> 2 | X43: Planejamento; Contratação; Pro-ensino - Plano de trabalho com projetos pedagógicos; Pro-ensino P2 compledo do curso 1 Princípios básicos de integridade e Compliance para o Poder Judiciário; Pro ensino P3 - Versão final revisada do curso 01; Campanha de sensibilização para engajamento do público alvo do Curso Formação de gestores em sistema de integridade e Compliance; Pro ensino 4 V1 completa do curso Formação de Gestores do Poder Judiciário em Sistema de Integridade Compliance; Pro-ensino P5 - Relatório da Aplicação completa do Curso “Formação de Gestores do Poder Judiciário em Sistemas de Integridade e Compliance”; Pro-Enisno P6 - Adequação do Curso “Formação de Gestores em Sistemas de Integridade e Compliance” para disponibilização em formato assíncrono na plataforma do CEAJud ; Pro-Ensino P7 - Relatório final de atividades e resultados alcançados Termo de Encerramento do Projeto Pesquisa medição de benefícios 1; Campanha de sensibilização do tema do curso 01: Princípios básicos de integridade e Compilance para o Poder Judiciário; | Y43: 256100.06 | AA43: https://www.cnj.jus.br/tecnologia-da-informacao-e-comunicacao/justica-4-0/ | AB43: Dr. Dorotheo Barbosa Neto | AC43: SEP - Secretaria de Estratégia e Projetos | AD43: São benefícios estruturantes: 1. Sensibilizar gestores e servidores do Poder Judiciário sobre os normativos, princípios e mecanismos de Integridade e Compliance. São benefícios híbridos: 2. Gerar o reconhecimento e aplicação prática, por gestores e servidores do Poder Judiciário, dos princípios e mecanismos de integridade de compliance em seu contexto de trabalho. São benefícios de resultado: 3. Manter o tema integridade e compliance como uma premissa da prática diária institucional. 4. Demonstrar os resultados provenientes da implementação de práticas e mecanismos de integridade e compliance pelo Poder Judiciário. | AE43: - Curso “Princípios Básicos em Integridade & Compliance para o Poder Judiciário” assíncrono, ofertado ao público do Judiciário e ao público externo, por meio da plataforma do CEAJUD. O curso atingiu 739 inscritos até janeiro de 2024 - Curso “Formação de Gestores do Poder Judiciário em Sistemas de Integridade e Compliance” síncrono na modalidade EaD ofertado para 193 participantes do Judiciário em posição relacionada a gestão de integridade e indicados para participar do curso por seu respectivo tribunal ou conselho. - Curso “Formação de Gestores do Poder Judiciário em Sistemas de Integridade e Compliance”, ofertado ao público do Judiciário e ao público externo, por meio da plataforma do CEAJUD. O curso atingiu 532 inscritos até janeiro de 2024. - Sensibilização realizada com publicação de matéria no site do CNJ e de série de quatro publicações em redes sociais sobre a Resolução nº 410/2021, que dispõe sobre a instituição de sistemas de integridade no Poder Judiciário. - Pesquisa realizada para medição do conhecimento sobre a Resolução nº 410/2021 e temas relacionados a integridade e compliance por parte dos servidores do Judiciário, atingindo público de mais de 5.397 pessoas. | AF43: =TODAY() -> 46176 | AG43: Thaís Martins Bosch | AH43: SEP - Secretaria de Estratégia e Projetos | AJ43: =2024&Tb_Portfólio[[#This Row],[SEI]] -> 202407855/2022 | AK43: =IFERROR(IF(MATCH(AJ43,Atualizações!$P$1:$P$1265,0)>0, "Sim"), "Não") -> Sim | AL43: =2025&Tb_Portfólio[[#This Row],[SEI]] -> 202507855/2022 | AM43: =IFERROR(IF(MATCH(AL43,Atualizações!$P$1:$P$2994,0)>0, "Sim"), "Não") -> Não | AN43: =2026&Tb_Portfólio[[#This Row],[SEI]] -> 202607855/2022 | AO43: =IFERROR(IF(MATCH(AN43,Atualizações!$P$1:$P$2994,0)>0, "Sim"), "Não") -> Não | AP43: =_xlfn.XLOOKUP(Tb_Portfólio[[#This Row],[SEI]],Tb_Atualizações[PROCESSO SEI],Tb_Atualizações[Explicações],"",0,-1) -> 0 | AQ43: =_xlfn.XLOOKUP(Tb_Portfólio[[#This Row],[SEI]],Tb_Mapa[SEI],Tb_Mapa[CONSULTOR RESPONSÁVEL],"",0,-1) -> Igor/finalizado
A44: 08286/2022 | B44: Implantação do SERP | C44: Implantar o Sistema Eletrônico de Registros Públicos – SERP, nos moldes previsto na Lei 14.382/2022, modernizando e simplificando os procedimentos cartorários. | E44: Ministro Luis Felipe Salomão | F44: Corregedoria Nacional de Justiça | G44: Luciano Almeida Lima | H44: Corregedoria Nacional de Justiça | I44: 06. Fomentar a melhoria dos serviços extrajudiciais | J44: 03. Agilidade e produtividade na prestação jurisdicional | L44: 44854 | M44: 45688 | N44: =_xlfn.XLOOKUP(Tb_Portfólio[[#This Row],[SEI]],Tb_Atualizações[PROCESSO SEI],Tb_Atualizações[% PREVISTO],"",0,-1) -> 0.42 | O44: =_xlfn.XLOOKUP(Tb_Portfólio[[#This Row],[SEI]],Tb_Atualizações[PROCESSO SEI],Tb_Atualizações[% EXECUTADO],"",0,-1) -> 0.42 | P44: =IFERROR(Tb_Portfólio[[#This Row],[% EXECUTADO]]/Tb_Portfólio[[#This Row],[% PREVISTO]],"0%") -> 1 | Q44: =_xlfn.XLOOKUP(Tb_Portfólio[[#This Row],[SEI]],Tb_Atualizações[PROCESSO SEI],Tb_Atualizações[DATA DE ATUALIZAÇÃO],"",0,-1) -> 45680 | R44: =_xlfn.XLOOKUP(Tb_Portfólio[[#This Row],[SEI]],Tb_Atualizações[PROCESSO SEI],Tb_Atualizações[Mês],,0,-1) -> 45200 | U44: =IF(Tb_Portfólio[[#This Row],[% EXECUTADO]]=100%,"Finalizado",IF(Tb_Portfólio[[#This Row],[PREVISÃO DE TERMINO]]<Tb_Portfólio[[#This Row],[Hoje]],"Atrasado ou Crítico",IF(Tb_Portfólio[[#This Row],[% EXECUTADO]]=0,"Autorizado",IF(Tb_Portfólio[[#This Row],[MEDIÇÃO DE STATUS]]>=95%,"No prazo",IF(Tb_Portfólio[[#This Row],[MEDIÇÃO DE STATUS]]<85%,"Atrasado ou Crítico",IF(Tb_Portfólio[[#This Row],[MEDIÇÃO DE STATUS]]<=95%,"Em atenção")))))) -> Atrasado ou Crítico | W44: =IFERROR(Tb_Portfólio[[#This Row],[% EXECUTADO]]/Tb_Portfólio[[#This Row],[% PREVISTO]],0) -> 1 | AB44: Dra. Daniela Pereira Madeira | AC44: Corregedoria Nacional de Justiça | AD44: - Benefício 1 – (Estruturante) simplificar os procedimentos cartorários com novas regras e procedimentos para o funcionamento e compartilhamento de informações; - Benefício 2 – (Estruturante) prover infraestrutura e manutenção adequada ao SERP com a implantação de um fundo arrecadador; - Benefício 3 – (Resultado) modernizar os procedimentos cartorários com a integração dos sistemas de todos os cartórios. | AF44: =TODAY() -> 46176 | AJ44: =2024&Tb_Portfólio[[#This Row],[SEI]] -> 202408286/2022 | AK44: =IFERROR(IF(MATCH(AJ44,Atualizações!$P$1:$P$1265,0)>0, "Sim"), "Não") -> Sim | AL44: =2025&Tb_Portfólio[[#This Row],[SEI]] -> 202508286/2022 | AM44: =IFERROR(IF(MATCH(AL44,Atualizações!$P$1:$P$2994,0)>0, "Sim"), "Não") -> Sim | AN44: =2026&Tb_Portfólio[[#This Row],[SEI]] -> 202608286/2022 | AO44: =IFERROR(IF(MATCH(AN44,Atualizações!$P$1:$P$2994,0)>0, "Sim"), "Não") -> Não | AP44: =_xlfn.XLOOKUP(Tb_Portfólio[[#This Row],[SEI]],Tb_Atualizações[PROCESSO SEI],Tb_Atualizações[Explicações],"",0,-1) -> Medição duplicada apenas para incluir no portfólio de 2025 | AQ44: =_xlfn.XLOOKUP(Tb_Portfólio[[#This Row],[SEI]],Tb_Mapa[SEI],Tb_Mapa[CONSULTOR RESPONSÁVEL],"",0,-1) -> Igor
A45: 08287/2022 | B45: Conciliação e Mediação na prática | C45: Viabilizar a implantação do serviço de conciliação online prévia e posterior ao protesto | D45: Normatização e efetivação da possibilidade da conciliação pré e pós protesto de dívidas por meio de ferramentas remotas. | E45: Ministro Luis Felipe Salomão | F45: Corregedoria Nacional de Justiça | G45: Luciano Almeida Lima | H45: Corregedoria Nacional de Justiça | I45: 08. Fortalecer a política judiciária de soluções alternativas de conflitos e a desjudicialização | J45: 05. Prevenção de litígios e adoção de soluções consensuais para os conflitos | K45: Diretrizes Estratégicas da Corregedorias para o ano de 2023, mais especificamente a DIRETRIZ ESTRATÉGICA 2: “Desenvolver protocolos institucionais entre os Tribunais e as serventias extrajudiciais, com o objetivo de otimizar e documentar as medidas de desjudicialização e desburocratização, inserindo nesse contexto práticas concernentes aos meios consensuais de solução de conflitos.” | L45: 44895 | M45: 45199 | N45: =_xlfn.XLOOKUP(Tb_Portfólio[[#This Row],[SEI]],Tb_Atualizações[PROCESSO SEI],Tb_Atualizações[% PREVISTO],"",0,-1) -> 0.0555 | O45: =_xlfn.XLOOKUP(Tb_Portfólio[[#This Row],[SEI]],Tb_Atualizações[PROCESSO SEI],Tb_Atualizações[% EXECUTADO],"",0,-1) -> 0.011 | P45: =IFERROR(Tb_Portfólio[[#This Row],[% EXECUTADO]]/Tb_Portfólio[[#This Row],[% PREVISTO]],"0%") -> 0.1981982 | Q45: =_xlfn.XLOOKUP(Tb_Portfólio[[#This Row],[SEI]],Tb_Atualizações[PROCESSO SEI],Tb_Atualizações[DATA DE ATUALIZAÇÃO],"",0,-1) -> 45383 | R45: =_xlfn.XLOOKUP(Tb_Portfólio[[#This Row],[SEI]],Tb_Atualizações[PROCESSO SEI],Tb_Atualizações[Mês],,0,-1) -> 45017 | U45: Cancelado | W45: =IFERROR(Tb_Portfólio[[#This Row],[% EXECUTADO]]/Tb_Portfólio[[#This Row],[% PREVISTO]],0) -> 0.1981982 | AB45: Dra. Daniela Pereira Madeira | AC45: Corregedoria Nacional de Justiça | AD45: Benefício 1: Implementação da mediação e conciliação na prática dos cartórios Benefício 2: Impulsionamento da consolidação das medidas autocompositivas de resolução de conflitos nos cartórios | AE45: - | AF45: =TODAY() -> 46176 | AJ45: =2024&Tb_Portfólio[[#This Row],[SEI]] -> 202408287/2022 | AK45: =IFERROR(IF(MATCH(AJ45,Atualizações!$P$1:$P$1265,0)>0, "Sim"), "Não") -> Sim | AL45: =2025&Tb_Portfólio[[#This Row],[SEI]] -> 202508287/2022 | AM45: =IFERROR(IF(MATCH(AL45,Atualizações!$P$1:$P$2994,0)>0, "Sim"), "Não") -> Não | AN45: =2026&Tb_Portfólio[[#This Row],[SEI]] -> 202608287/2022 | AO45: =IFERROR(IF(MATCH(AN45,Atualizações!$P$1:$P$2994,0)>0, "Sim"), "Não") -> Não | AP45: =_xlfn.XLOOKUP(Tb_Portfólio[[#This Row],[SEI]],Tb_Atualizações[PROCESSO SEI],Tb_Atualizações[Explicações],"",0,-1) -> Inclusão no portfólio de 2024 | AQ45: =_xlfn.XLOOKUP(Tb_Portfólio[[#This Row],[SEI]],Tb_Mapa[SEI],Tb_Mapa[CONSULTOR RESPONSÁVEL],"",0,-1) -> Igor/cancelado
A46: 08370/2024 | B46: SNGB - Melhorias evolutivas | C46: Melhoria do Sistema Nacional de Gestão de Bens Apreendidos (SNGB), e manutenção do sistema por meio de ciclos de sprints, com a previsão de transferência gradativa do conhecimento técnico ao CNJ, permitindo que a equipe interna assuma a sustentação de forma plena ao término do projeto. | E46: Dr. Dorotheo Barbosa Neto | F46: SEP - Secretaria de Estratégia e Projetos | G46: Alexandre Alves de Oliveira | H46: PNUD | I46: 09. Fomentar e incrementar a produção de soluções tecnológicas, com foco em inovação e transformação digital | J46: 12. Fortalecimento da estratégia nacional de TIC e de proteção de dados e 03. Agilidade e produtividade na prestação jurisdicional | K46: Política de Gestão da Inovação, Resolução CNJ nº 395/2021 | L46: 45523 | M46: 46101 | N46: =_xlfn.XLOOKUP(Tb_Portfólio[[#This Row],[SEI]],Tb_Atualizações[PROCESSO SEI],Tb_Atualizações[% PREVISTO],"",0,-1) -> 1 | O46: =_xlfn.XLOOKUP(Tb_Portfólio[[#This Row],[SEI]],Tb_Atualizações[PROCESSO SEI],Tb_Atualizações[% EXECUTADO],"",0,-1) -> 1 | P46: =IFERROR(Tb_Portfólio[[#This Row],[% EXECUTADO]]/Tb_Portfólio[[#This Row],[% PREVISTO]],"0%") -> 1 | Q46: =_xlfn.XLOOKUP(Tb_Portfólio[[#This Row],[SEI]],Tb_Atualizações[PROCESSO SEI],Tb_Atualizações[DATA DE ATUALIZAÇÃO],"",0,-1) -> 46112 | R46: =_xlfn.XLOOKUP(Tb_Portfólio[[#This Row],[SEI]],Tb_Atualizações[PROCESSO SEI],Tb_Atualizações[Mês],,0,-1) -> 46082 | T46: Justiça 4.0 | U46: =IF(Tb_Portfólio[[#This Row],[% EXECUTADO]]=100%,"Finalizado",IF(Tb_Portfólio[[#This Row],[PREVISÃO DE TERMINO]]<Tb_Portfólio[[#This Row],[Hoje]],"Atrasado ou Crítico",IF(Tb_Portfólio[[#This Row],[% EXECUTADO]]=0,"Autorizado",IF(Tb_Portfólio[[#This Row],[MEDIÇÃO DE STATUS]]>=95%,"No prazo",IF(Tb_Portfólio[[#This Row],[MEDIÇÃO DE STATUS]]<85%,"Atrasado ou Crítico",IF(Tb_Portfólio[[#This Row],[MEDIÇÃO DE STATUS]]<=95%,"Em atenção")))))) -> Finalizado | W46: =IFERROR(Tb_Portfólio[[#This Row],[% EXECUTADO]]/Tb_Portfólio[[#This Row],[% PREVISTO]],0) -> 1 | AA46: https://www.cnj.jus.br/tecnologia-da-informacao-e-comunicacao/justica-4-0/ | AB46: Dr. Dorotheo Barbosa Neto | AC46: SEP - Secretaria de Estratégia e Projetos | AD46: Benefício 1 - Mellhoria da estabilidade e Evolução do Sistema SNGB - Promover a estabilidade do sistema SNGB e a implementação de melhorias contínuas com base nas demandas operacionais do CNJ. | AF46: =TODAY() -> 46176 | AG46: Marcos Paulo Santos Calixto | AH46: DTI - Departamento de Tecnologia da Informação e Comunicação | AJ46: =2024&Tb_Portfólio[[#This Row],[SEI]] -> 202408370/2024 | AK46: =IFERROR(IF(MATCH(AJ46,Atualizações!$P$1:$P$1265,0)>0, "Sim"), "Não") -> Sim | AL46: =2025&Tb_Portfólio[[#This Row],[SEI]] -> 202508370/2024 | AM46: =IFERROR(IF(MATCH(AL46,Atualizações!$P$1:$P$2994,0)>0, "Sim"), "Não") -> Sim | AN46: =2026&Tb_Portfólio[[#This Row],[SEI]] -> 202608370/2024 | AO46: =IFERROR(IF(MATCH(AN46,Atualizações!$P$1:$P$2994,0)>0, "Sim"), "Não") -> Sim | AP46: =_xlfn.XLOOKUP(Tb_Portfólio[[#This Row],[SEI]],Tb_Atualizações[PROCESSO SEI],Tb_Atualizações[Explicações],"",0,-1) -> 0 | AQ46: =_xlfn.XLOOKUP(Tb_Portfólio[[#This Row],[SEI]],Tb_Mapa[SEI],Tb_Mapa[CONSULTOR RESPONSÁVEL],"",0,-1) -> Raphael
